Workbook
Name Lookup_Choices: [1]SOP!$H$1:$H$6
Name Lookup_Choices: '[2]Leadership 1 '!$H$1:$H$6
Name Lookup_Table: [1]SOP!$H$1:$I$6
Name Lookup_Table: '[2]Leadership 1 '!$H$1:$I$6

Sheet Cover
B7: Cyber Security Assurance Framework
B8: Maturity Assessment-NALCO
F9: Dated: 10.06.2024
I10: Version 2.0
B13: National Aluminium Company Limited (NALCO) is a Schedule ‘A’ Navratna CPSE established on 7th January, 1981 , 2022 NALCO India , A Govt. of India Enterprise
E18: `

Sheet Index
A1: S. No. | B1: Particular | C1: Link
A2: 1 | B2: Read Me | C2: Click Here
A3: 2 | B3: Maturity of Security Domains | C3: Click Here
A4: 3 | B4: Detailed Observations | C4: Click Here

Sheet Read Me
A1: Objective:
A2: The objective of this Workbook is to provide an assurance framework for the cyber security maturity assessment
A4: Domains Covered:
A5: This workbook lists a database of controls against 19 security domains identified for the organization's environment. It may be noted that there may be few controls/ security domains which might not be applicable to a particular organization. The workbook provides ready to use templates which will calculate the control rating of the individual controls and provides an overall domain rating for the respective security domain.
A7: Approach:
A8: This workbook lists a database of controls against 19 security domains identified for the organizations environment. It may be noted that there may be few controls/ security domains which might not be applicable to a particular organization. The workbook provides ready to use templates which will calculate the control rating of the individual controls and provides an overall domain rating for the respective security domain.
A9: 1. Identification of Cyber Security domains defined under Security Domains Tab.
A10: 2. Identification of sub domains under each security domain and covering the controls in the sub domain.
A11: 3. Identification of controls as Preventive, Detective, Corrective controls.
A12: 4. The Key controls are identified within each sub domain and they are given additional 20% more weightage than other controls.
A13: 5. The ratings given against each control is divided among four sections which are Documentation, Implementation, Automation and Monitoring & Review.
A21: 6. Based on each control rating, sub domain rating will be derived followed by Security Domain Maturity Rating aligned to CMMI and NIST.
... A24: Definitions for Risk Criticality:
A25: Risk Rating | B25: Definition | C25: Control rating
A26: High | B26: Observations having direct impact on Impact on CIA, financial/operational data | C26: below 1.74
A27: Medium | B27: Observations having impact on the design and system level controls of the organization | C27: 1.75-2.29
A28: Low | B28: Observations that do not have direct impact on the organizations data, design and system level controls | C28: 2.30-2.74
A29: Information | B29: opportunity for improvement | C29: 2.75-2.99
A30: Note: These control rating are only for guidance purpose.
A32: Version Control:
A33: Version No | B33: Description of changes made
A34: 1 | B34: Initial Version
A35: 2 | B35: Added controls as mentioned below: IS Governance: 1.9; Access Management: 2.5, 2.13, 2.16, 2.24, 2.32, 2.33; Asset Management: 3.4, 3.21, 3.22; Incident Management: 4.19; Infra and Operations Sec: 5.11, 5.12, 5.22, 5.37, 5.40, 5.46, 5.47, 5.48, 5.73, 5.83, 5.84, 5.85, 5.88, 5.89, 5.90, 5.91, 5.92, 5.93; Mobility: 6.8, 6.12, 6.23; Privacy: 7.9, 7.10, 7.11; Cloud: 8.4, 8.5, 8.6, 8.7, 8.8, 8.9, 8.10, 8.14, 8.19, 8.24, 8.25, 8.26, 8.33; Network Security: 10.15, 10.17, 10.19, 10.29, 10.30, 10.43, 10.72, 10.75, 10.76, 10.77, 10.78, 10.83, 10.84, 10.85, 10.86, 10.87, 10.88, 10.89, 10.90, 10.91; Endpoint Security: 11.10, 11.13, 11.14, 11.15, 11.17, 11.22, 11.23, 11.24, 11.25, 11.26, 11.27, 11.28, 11.29, 11.30, 11.31, 11.32, 11.33, 11.34, 11.35, 11.36, 11.37, 11.38, 11.39, 11.40, 11.41, 11.42, 11.43, 11.44; Application Security: 13.1, 13.2, 13.3, 13.19, 13.19, 13.22, 13.32, 13.34, 13.44; Encryption: 14.14, 14.15, 14.16, 14.7, 14.18, 14.19; Risk Management: 15.4, 15.8, 15.15; Business Continuity: 16.19, 16.20; Physical and Environment: 17.21, 17.25; Third Party: 18.7, 18.15, 18.16, 18.17, 18.18, 18.19, 18.20, 18.21, 18.26, 18.27

Sheet Security Domains
A1: S. No. | B1: Domain | C1: Maturity Rating | D1: Maturity Rating Category
A2: 1 | B2: IS Governance | C2: ='IS Governance'!F1 -> 3.2222222 | D2: ='IS Governance'!E1 -> Defined
A3: 2 | B3: Access Management | C3: ='Access Management'!F1 -> 2.6837963 | D3: ='Access Management'!E1 -> Partial
A4: 3 | B4: Asset Management | C4: ='Asset Management'!F1 -> 2.7732564 | D4: ='Asset Management'!E1 -> Partial
A5: 4 | B5: Incident Management | C5: ='Incident Management'!F1 -> 4.7861111 | D5: ='Incident Management'!E1 -> Repeatable
A6: 5 | B6: Infrastructure & Operations Security | C6: ='Infra and Operations Sec'!F1 -> 2.5062484 | D6: ='Infra and Operations Sec'!E1 -> Partial
A7: 6 | B7: Emerging Technologies | C7: ='Emerging Technology'!F1 -> 4.3279672 | D7: ='Emerging Technology'!E1 -> Repeatable
A8: 7 | B8: Network Security | C8: ='Network Security'!F1 -> 2.9475565 | D8: ='Network Security'!E1 -> Partial
A9: 8 | B9: Endpoint Protection | C9: ='Endpoint Protection'!F1 -> 3.0547543 | D9: ='Endpoint Protection'!E1 -> Defined
A10: 9 | B10: Application Security | C10: ='Application Security'!F1 -> 4.1188776 | D10: ='Application Security'!E1 -> Repeatable
A11: 10 | B11: Risk Management | C11: ='Risk Management'!F1 -> 3.9027778 | D11: ='Risk Management'!E1 -> Defined
A12: 11 | B12: Human Resource Security | C12: ='Human Resource Security'!F1 -> 4.5555556 | D12: ='Human Resource Security'!E1 -> Repeatable
A13: 12 | B13: Business Continuity | C13: ='Business Continuity'!F1 -> 3.615812 | D13: ='Business Continuity'!E1 -> Defined
A14: 13 | B14: Physical & Environmental Security | C14: ='Physical and Environment'!F1 -> 3.9193122 | D14: ='Physical and Environment'!E1 -> Defined
A15: 14 | B15: Third Party Security | C15: ='Third Party'!F1 -> 3.931652 | D15: ='Third Party'!E1 -> Defined
A16: 15 | B16: Compliance Management | C16: ='Compliance management'!F1 -> 3.2819444 | D16: ='Compliance management'!E1 -> Defined
B18: Overall Rating | C18: =AVERAGE(C2:C16) -> 3.5751896 | D18: =IF(C18="NA","Not Applicable",VLOOKUP(C19,'Maturity Rating'!G4:H8,2,FALSE)) -> Defined
C19: =ROUNDDOWN(C18,0) -> 3
E20: =ROUND(C18,0) -> 4
B21: Excluded Privacy | C21: =(SUM(C2:C16)-#REF!)/16 -> #REF!

Sheet IS Governance
C1: Average Domain Rating | E1: =IF(F1="NA","Not Applicable",VLOOKUP(T1,'Maturity Rating'!G4:H8,2,FALSE)) -> Defined | F1: =IF(U1="NANANA","NA",AVERAGE(N4:N20)) -> 3.2222222 | T1: =ROUNDDOWN(F1,0) -> 3 | U1: =CONCATENATE(N4,N10,N17) -> 53.666666666666671
A3: S. No. | B3: High Level Description | C3: Control Description | D3: Identified Key Controls (K) | E3: Control | F3: Preventive/ Detective/Corrective | G3: Documentation | H3: Implementation | I3: Automation | J3: Monitor & Review | K3: Control Rating | L3: Rating with Key controls weightage | M3: Average Rating | N3: Maturity Rating (1 - 5) | O3: Category | S3: Doc | T3: Impl | U3: Auto | V3: Review
A4: 1.1 | B4: Policy and procedures | C4: Information Security policy should be established, documented and approved by authorized individuals. The document should be reviewed periodically and updated whenever significant changes occur. | D4: K | E4: Organization should have an Information Security policy defined, approved by the management | F4: Preventive | G4: Formally Documented | H4: 51 - 100% Implemented | I4: Automated | J4: Monitored & Reviewed | K4: =IF(W4="NANANANA",S4,IF(AND(OR(G4="Formally Documented",G4="Informally Documented"),H4="Not Implemented"),0.5*AVERAGE(S4:V4),AVERAGE(S4:V4))) -> 3 | L4: =IF(AND(D4="K",K4=1),'Maturity Rating'!$E$8,IF(K4="NA",K4,IF(D4="K",K4*'Maturity Rating'!$E$7,K4))) -> 3.6 | M4: =IF(X4="NANANANA",K4,AVERAGE(L4:L9)) -> 3.0583333 | N4: =IF(M4<1.1,1,IF(M4="NA",M4,(MIN(5,M4/3*5)))) -> 5 | O4: =IF(N4="NA",N4,VLOOKUP(Q4,'Maturity Rating'!G4:H8,2,FALSE)) -> Adaptive | Q4: =IF(N4="NA",N4,ROUNDDOWN(N4,0)) -> 5 | S4: =VLOOKUP(G4,'Maturity Rating'!A$2:B$5,2,FALSE) -> 3 | T4: =VLOOKUP(H4,'Maturity Rating'!A$8:B$11,2,FALSE) -> 3 | U4: =VLOOKUP(I4,'Maturity Rating'!A$14:B$17,2,FALSE) -> 3 | V4: =VLOOKUP(J4,'Maturity Rating'!A$20:B$23,2,FALSE) -> 3 | W4: =CONCATENATE(S4,T4,U4,V4) -> 3333 | X4: =CONCATENATE(L4,L5,L6,L9) -> 3.632.753
A5: 1.2 | E5: The documents are reviewed, updated and approved as per the defined frequency in the policy/ procedure. | F5: Preventive | G5: Formally Documented | H5: 51 - 100% Implemented | I5: Automated | J5: Monitored & Reviewed | K5: =IF(W5="NANANANA",S5,IF(AND(OR(G5="Formally Documented",G5="Informally Documented"),H5="Not Implemented"),0.5*AVERAGE(S5:V5),AVERAGE(S5:V5))) -> 3 | L5: =IF(AND(D5="K",K5=1),'Maturity Rating'!$E$8,IF(K5="NA",K5,IF(D5="K",K5*'Maturity Rating'!$E$7,K5))) -> 3 | S5: =VLOOKUP(G5,'Maturity Rating'!A$2:B$5,2,FALSE) -> 3 | T5: =VLOOKUP(H5,'Maturity Rating'!A$8:B$11,2,FALSE) -> 3 | U5: =VLOOKUP(I5,'Maturity Rating'!A$14:B$17,2,FALSE) -> 3 | V5: =VLOOKUP(J5,'Maturity Rating'!A$20:B$23,2,FALSE) -> 3 | W5: =CONCATENATE(S5,T5,U5,V5) -> 3333
A6: 1.3 | E6: The Information Security policy covers objectives, scope, ownership and responsibility for the policy. | F6: Preventive | G6: Formally Documented | H6: 51 - 100% Implemented | I6: Automated | J6: Partially Monitored & Reviewed | K6: =IF(W6="NANANANA",S6,IF(AND(OR(G6="Formally Documented",G6="Informally Documented"),H6="Not Implemented"),0.5*AVERAGE(S6:V6),AVERAGE(S6:V6))) -> 2.75 | L6: =IF(AND(D6="K",K6=1),'Maturity Rating'!$E$8,IF(K6="NA",K6,IF(D6="K",K6*'Maturity Rating'!$E$7,K6))) -> 2.75 | S6: =VLOOKUP(G6,'Maturity Rating'!A$2:B$5,2,FALSE) -> 3 | T6: =VLOOKUP(H6,'Maturity Rating'!A$8:B$11,2,FALSE) -> 3 | U6: =VLOOKUP(I6,'Maturity Rating'!A$14:B$17,2,FALSE) -> 3 | V6: =VLOOKUP(J6,'Maturity Rating'!A$20:B$23,2,FALSE) -> 2 | W6: =CONCATENATE(S6,T6,U6,V6) -> 3332
A7: 1.4 | E7: The IS organization structure should be well defined, reviewed and approved by the management. | F7: Preventive | G7: Formally Documented | H7: 51 - 100% Implemented | I7: Automated | J7: Monitored & Reviewed | K7: =IF(W7="NANANANA",S7,IF(AND(OR(G7="Formally Documented",G7="Informally Documented"),H7="Not Implemented"),0.5*AVERAGE(S7:V7),AVERAGE(S7:V7))) -> 3 | L7: =IF(AND(D7="K",K7=1),'Maturity Rating'!$E$8,IF(K7="NA",K7,IF(D7="K",K7*'Maturity Rating'!$E$7,K7))) -> 3 | S7: =VLOOKUP(G7,'Maturity Rating'!A$2:B$5,2,FALSE) -> 3 | T7: =VLOOKUP(H7,'Maturity Rating'!A$8:B$11,2,FALSE) -> 3 | U7: =VLOOKUP(I7,'Maturity Rating'!A$14:B$17,2,FALSE) -> 3 | V7: =VLOOKUP(J7,'Maturity Rating'!A$20:B$23,2,FALSE) -> 3 | W7: =CONCATENATE(S7,T7,U7,V7) -> 3333
A8: 1.5 | E8: The information security policies and procedures shall be communicated to the employees and relevant external parties. | F8: Preventive | G8: Formally Documented | H8: 51 - 100% Implemented | I8: Automated | J8: Monitored & Reviewed | K8: =IF(W8="NANANANA",S8,IF(AND(OR(G8="Formally Documented",G8="Informally Documented"),H8="Not Implemented"),0.5*AVERAGE(S8:V8),AVERAGE(S8:V8))) -> 3 | L8: =IF(AND(D8="K",K8=1),'Maturity Rating'!$E$8,IF(K8="NA",K8,IF(D8="K",K8*'Maturity Rating'!$E$7,K8))) -> 3 | S8: =VLOOKUP(G8,'Maturity Rating'!A$2:B$5,2,FALSE) -> 3 | T8: =VLOOKUP(H8,'Maturity Rating'!A$8:B$11,2,FALSE) -> 3 | U8: =VLOOKUP(I8,'Maturity Rating'!A$14:B$17,2,FALSE) -> 3 | V8: =VLOOKUP(J8,'Maturity Rating'!A$20:B$23,2,FALSE) -> 3 | W8: =CONCATENATE(S8,T8,U8,V8) -> 3333
A9: 1.6 | E9: The version control of the document is maintained | F9: Preventive | G9: Formally Documented | H9: 51 - 100% Implemented | I9: Automated | J9: Monitored & Reviewed | K9: =IF(W9="NANANANA",S9,IF(AND(OR(G9="Formally Documented",G9="Informally Documented"),H9="Not Implemented"),0.5*AVERAGE(S9:V9),AVERAGE(S9:V9))) -> 3 | L9: =IF(AND(D9="K",K9=1),'Maturity Rating'!$E$8,IF(K9="NA",K9,IF(D9="K",K9*'Maturity Rating'!$E$7,K9))) -> 3 | S9: =VLOOKUP(G9,'Maturity Rating'!A$2:B$5,2,FALSE) -> 3 | T9: =VLOOKUP(H9,'Maturity Rating'!A$8:B$11,2,FALSE) -> 3 | U9: =VLOOKUP(I9,'Maturity Rating'!A$14:B$17,2,FALSE) -> 3 | V9: =VLOOKUP(J9,'Maturity Rating'!A$20:B$23,2,FALSE) -> 3 | W9: =CONCATENATE(S9,T9,U9,V9) -> 3333
A10: 1.7 | B10: Organization Structure | C10: Organization should ensure that the roles and responsibilities of all the employees are defined and the organization structure should be well maintained within the organization | D10: K | E10: Organization has a designated Chief Information Security Officer (CISO) responsible for Information security related decisions and operations. | F10: Preventive | G10: Formally Documented | H10: 51 - 100% Implemented | I10: Automated | J10: Monitored & Reviewed | K10: =IF(W10="NANANANA",S10,IF(AND(OR(G10="Formally Documented",G10="Informally Documented"),H10="Not Implemented"),0.5*AVERAGE(S10:V10),AVERAGE(S10:V10))) -> 3 | L10: =IF(AND(D10="K",K10=1),'Maturity Rating'!$E$8,IF(K10="NA",K10,IF(D10="K",K10*'Maturity Rating'!$E$7,K10))) -> 3.6 | M10: =IF(X10="NANANANANANANANA",K10,AVERAGE(L10:L16)) -> 2.2 | N10: =IF(M10<1.1,1,IF(M10="NA",M10,(MIN(5,M10/3*5)))) -> 3.6666667 | O10: =IF(N10="NA",N10,VLOOKUP(Q10,'Maturity Rating'!G4:H8,2,FALSE)) -> Defined | Q10: =IF(N10="NA",N10,ROUNDDOWN(N10,0)) -> 3 | S10: =VLOOKUP(G10,'Maturity Rating'!A$2:B$5,2,FALSE) -> 3 | T10: =VLOOKUP(H10,'Maturity Rating'!A$8:B$11,2,FALSE) -> 3 | U10: =VLOOKUP(I10,'Maturity Rating'!A$14:B$17,2,FALSE) -> 3 | V10: =VLOOKUP(J10,'Maturity Rating'!A$20:B$23,2,FALSE) -> 3 | W10: =CONCATENATE(S10,T10,U10,V10) -> 3333 | X10: =CONCATENATE(L10,L11,L12,L13,L14,L15,L16) -> 3.63310.831
A11: 1.8 | E11: Organization has an IS Steering Committee, the stakeholders are identified and periodicity for steering committee meeting is identified, documented and approved. | F11: Preventive | G11: Formally Documented | H11: 51 - 100% Implemented | I11: Automated | J11: Monitored & Reviewed | K11: =IF(W11="NANANANA",S11,IF(AND(OR(G11="Formally Documented",G11="Informally Documented"),H11="Not Implemented"),0.5*AVERAGE(S11:V11),AVERAGE(S11:V11))) -> 3 | L11: =IF(AND(D11="K",K11=1),'Maturity Rating'!$E$8,IF(K11="NA",K11,IF(D11="K",K11*'Maturity Rating'!$E$7,K11))) -> 3 | S11: =VLOOKUP(G11,'Maturity Rating'!A$2:B$5,2,FALSE) -> 3 | T11: =VLOOKUP(H11,'Maturity Rating'!A$8:B$11,2,FALSE) -> 3 | U11: =VLOOKUP(I11,'Maturity Rating'!A$14:B$17,2,FALSE) -> 3 | V11: =VLOOKUP(J11,'Maturity Rating'!A$20:B$23,2,FALSE) -> 3 | W11: =CONCATENATE(S11,T11,U11,V11) -> 3333
A12: 1.9 | E12: The policies, procedures, and processes to manage / monitor the organization’s regulatory, legal, risk, environmental, and operational requirements are understood and the IS Steering team or equivalent is informed of the cybersecurity risk. | F12: Preventive | G12: Formally Documented | H12: 51 - 100% Implemented | I12: Automated | J12: Monitored & Reviewed | K12: =IF(W12="NANANANA",S12,IF(AND(OR(G12="Formally Documented",G12="Informally Documented"),H12="Not Implemented"),0.5*AVERAGE(S12:V12),AVERAGE(S12:V12))) -> 3 | L12: =IF(AND(D12="K",K12=1),'Maturity Rating'!$E$8,IF(K12="NA",K12,IF(D12="K",K12*'Maturity Rating'!$E$7,K12))) -> 3 | S12: =VLOOKUP(G12,'Maturity Rating'!A$2:B$5,2,FALSE) -> 3 | T12: =VLOOKUP(H12,'Maturity Rating'!A$8:B$11,2,FALSE) -> 3 | U12: =VLOOKUP(I12,'Maturity Rating'!A$14:B$17,2,FALSE) -> 3 | V12: =VLOOKUP(J12,'Maturity Rating'!A$20:B$23,2,FALSE) -> 3 | W12: =CONCATENATE(S12,T12,U12,V12) -> 3333
A13: 1. 10 | E13: All information security responsibilities are defined and allocated to the identified personnel within the organization and among the external partners. | F13: Preventive | G13: Not Documented | H13: Not Applicable | I13: Not Applicable | J13: Not Applicable | K13: =IF(W13="NANANANA",S13,IF(AND(OR(G13="Formally Documented",G13="Informally Documented"),H13="Not Implemented"),0.5*AVERAGE(S13:V13),AVERAGE(S13:V13))) -> 1 | L13: =IF(AND(D13="K",K13=1),'Maturity Rating'!$E$8,IF(K13="NA",K13,IF(D13="K",K13*'Maturity Rating'!$E$7,K13))) -> 1 | S13: =VLOOKUP(G13,'Maturity Rating'!A$2:B$5,2,FALSE) -> 1 | T13: =VLOOKUP(H13,'Maturity Rating'!A$8:B$11,2,FALSE) -> NA | U13: =VLOOKUP(I13,'Maturity Rating'!A$14:B$17,2,FALSE) -> NA | V13: =VLOOKUP(J13,'Maturity Rating'!A$20:B$23,2,FALSE) -> NA | W13: =CONCATENATE(S13,T13,U13,V13) -> 1NANANA
A14: 1.11 | D14: K | E14: There is a RACI Matrix in place to hold the IS Organization Structure | F14: Preventive | G14: Not Documented | H14: Not Applicable | I14: Not Applicable | J14: Not Applicable | K14: =IF(W14="NANANANA",S14,IF(AND(OR(G14="Formally Documented",G14="Informally Documented"),H14="Not Implemented"),0.5*AVERAGE(S14:V14),AVERAGE(S14:V14))) -> 1 | L14: =IF(AND(D14="K",K14=1),'Maturity Rating'!$E$8,IF(K14="NA",K14,IF(D14="K",K14*'Maturity Rating'!$E$7,K14))) -> 0.8 | S14: =VLOOKUP(G14,'Maturity Rating'!A$2:B$5,2,FALSE) -> 1 | T14: =VLOOKUP(H14,'Maturity Rating'!A$8:B$11,2,FALSE) -> NA | U14: =VLOOKUP(I14,'Maturity Rating'!A$14:B$17,2,FALSE) -> NA | V14: =VLOOKUP(J14,'Maturity Rating'!A$20:B$23,2,FALSE) -> NA | W14: =CONCATENATE(S14,T14,U14,V14) -> 1NANANA
A15: 1.12 | E15: There is a clear segregation in functions of security group responsible for information security and the IT team which is responsible for the implementation and maintenance of IT Systems. | F15: Preventive | G15: Formally Documented | H15: 51 - 100% Implemented | I15: Automated | J15: Monitored & Reviewed | K15: =IF(W15="NANANANA",S15,IF(AND(OR(G15="Formally Documented",G15="Informally Documented"),H15="Not Implemented"),0.5*AVERAGE(S15:V15),AVERAGE(S15:V15))) -> 3 | L15: =IF(AND(D15="K",K15=1),'Maturity Rating'!$E$8,IF(K15="NA",K15,IF(D15="K",K15*'Maturity Rating'!$E$7,K15))) -> 3 | S15: =VLOOKUP(G15,'Maturity Rating'!A$2:B$5,2,FALSE) -> 3 | T15: =VLOOKUP(H15,'Maturity Rating'!A$8:B$11,2,FALSE) -> 3 | U15: =VLOOKUP(I15,'Maturity Rating'!A$14:B$17,2,FALSE) -> 3 | V15: =VLOOKUP(J15,'Maturity Rating'!A$20:B$23,2,FALSE) -> 3 | W15: =CONCATENATE(S15,T15,U15,V15) -> 3333
A16: 1.13 | E16: Every staff in the organization is made aware of the applicable laws, regulations, and guidelines pertaining to the usage, deployment and access to IT resources. | F16: Preventive | G16: Not Documented | H16: Not Applicable | I16: Not Applicable | J16: Not Applicable | K16: =IF(W16="NANANANA",S16,IF(AND(OR(G16="Formally Documented",G16="Informally Documented"),H16="Not Implemented"),0.5*AVERAGE(S16:V16),AVERAGE(S16:V16))) -> 1 | L16: =IF(AND(D16="K",K16=1),'Maturity Rating'!$E$8,IF(K16="NA",K16,IF(D16="K",K16*'Maturity Rating'!$E$7,K16))) -> 1 | S16: =VLOOKUP(G16,'Maturity Rating'!A$2:B$5,2,FALSE) -> 1 | T16: =VLOOKUP(H16,'Maturity Rating'!A$8:B$11,2,FALSE) -> NA | U16: =VLOOKUP(I16,'Maturity Rating'!A$14:B$17,2,FALSE) -> NA | V16: =VLOOKUP(J16,'Maturity Rating'!A$20:B$23,2,FALSE) -> NA | W16: =CONCATENATE(S16,T16,U16,V16) -> 1NANANA
A17: 1.14 | B17: Overall Governance of organization | C17: Providing a structure for aligning IT strategy with business strategy and provide management direction for information security | E17: The IS steering committee should ensure the alignment of IS strategy to the vision, mission, objectives and goal statements of the organization. | F17: Preventive | G17: Not Documented | H17: Not Applicable | I17: Not Applicable | J17: Not Applicable | K17: =IF(W17="NANANANA",S17,IF(AND(OR(G17="Formally Documented",G17="Informally Documented"),H17="Not Implemented"),0.5*AVERAGE(S17:V17),AVERAGE(S17:V17))) -> 1 | L17: =IF(AND(D17="K",K17=1),'Maturity Rating'!$E$8,IF(K17="NA",K17,IF(D17="K",K17*'Maturity Rating'!$E$7,K17))) -> 1 | M17: =IF(X17="NANANANANANANANANANA",K17,AVERAGE(L17:L20)) -> 1 | N17: =IF(M17<1.1,1,IF(M17="NA",M17,(MIN(5,M17/3*5)))) -> 1 | O17: =IF(N17="NA",N17,VLOOKUP(Q17,'Maturity Rating'!G4:H8,2,FALSE)) -> Initial | Q17: =IF(N17="NA",N17,ROUNDDOWN(N17,0)) -> 1 | S17: =VLOOKUP(G17,'Maturity Rating'!A$2:B$5,2,FALSE) -> 1 | T17: =VLOOKUP(H17,'Maturity Rating'!A$8:B$11,2,FALSE) -> NA | U17: =VLOOKUP(I17,'Maturity Rating'!A$14:B$17,2,FALSE) -> NA | V17: =VLOOKUP(J17,'Maturity Rating'!A$20:B$23,2,FALSE) -> NA | W17: =CONCATENATE(S17,T17,U17,V17) -> 1NANANA | X17: =CONCATENATE(L17,L18,L19,L20) -> 1111
A18: 1.15 | E18: Governance structure is identified and the personnel should be communicated their roles and responsibilities for effective governance of information security framework | F18: Preventive | G18: Not Documented | H18: Not Applicable | I18: Not Applicable | J18: Not Applicable | K18: =IF(W18="NANANANA",S18,IF(AND(OR(G18="Formally Documented",G18="Informally Documented"),H18="Not Implemented"),0.5*AVERAGE(S18:V18),AVERAGE(S18:V18))) -> 1 | L18: =IF(AND(D18="K",K18=1),'Maturity Rating'!$E$8,IF(K18="NA",K18,IF(D18="K",K18*'Maturity Rating'!$E$7,K18))) -> 1 | S18: =VLOOKUP(G18,'Maturity Rating'!A$2:B$5,2,FALSE) -> 1 | T18: =VLOOKUP(H18,'Maturity Rating'!A$8:B$11,2,FALSE) -> NA | U18: =VLOOKUP(I18,'Maturity Rating'!A$14:B$17,2,FALSE) -> NA | V18: =VLOOKUP(J18,'Maturity Rating'!A$20:B$23,2,FALSE) -> NA | W18: =CONCATENATE(S18,T18,U18,V18) -> 1NANANA
A19: 1.16 | E19: The annual budget for information security is approved by the top management. | F19: Preventive | G19: Not Documented | H19: Not Implemented | I19: Not Automated | J19: Not Monitored & Reviewed | K19: =IF(W19="NANANANA",S19,IF(AND(OR(G19="Formally Documented",G19="Informally Documented"),H19="Not Implemented"),0.5*AVERAGE(S19:V19),AVERAGE(S19:V19))) -> 1 | L19: =IF(AND(D19="K",K19=1),'Maturity Rating'!$E$8,IF(K19="NA",K19,IF(D19="K",K19*'Maturity Rating'!$E$7,K19))) -> 1 | S19: =VLOOKUP(G19,'Maturity Rating'!A$2:B$5,2,FALSE) -> 1 | T19: =VLOOKUP(H19,'Maturity Rating'!A$8:B$11,2,FALSE) -> 1 | U19: =VLOOKUP(I19,'Maturity Rating'!A$14:B$17,2,FALSE) -> 1 | V19: =VLOOKUP(J19,'Maturity Rating'!A$20:B$23,2,FALSE) -> 1 | W19: =CONCATENATE(S19,T19,U19,V19) -> 1111
A20: 1.17 | E20: The organization adopts security standards/guidelines as per the requirements of the industry sector, regulatory body or technology requirements | F20: Preventive | G20: Not Documented | H20: Not Implemented | I20: Not Automated | J20: Not Monitored & Reviewed | K20: =IF(W20="NANANANA",S20,IF(AND(OR(G20="Formally Documented",G20="Informally Documented"),H20="Not Implemented"),0.5*AVERAGE(S20:V20),AVERAGE(S20:V20))) -> 1 | L20: =IF(AND(D20="K",K20=1),'Maturity Rating'!$E$8,IF(K20="NA",K20,IF(D20="K",K20*'Maturity Rating'!$E$7,K20))) -> 1 | S20: =VLOOKUP(G20,'Maturity Rating'!A$2:B$5,2,FALSE) -> 1 | T20: =VLOOKUP(H20,'Maturity Rating'!A$8:B$11,2,FALSE) -> 1 | U20: =VLOOKUP(I20,'Maturity Rating'!A$14:B$17,2,FALSE) -> 1 | V20: =VLOOKUP(J20,'Maturity Rating'!A$20:B$23,2,FALSE) -> 1 | W20: =CONCATENATE(S20,T20,U20,V20) -> 1111

Sheet Access Management
C1: Average Domain Rating | E1: =IF(F1="NA","Not Applicable",VLOOKUP(T1,'Maturity Rating'!G4:H8,2,FALSE)) -> Partial | F1: =IF(U1="NANANANA","NA",AVERAGE(N4:N35)) -> 2.6837963 | T1: =ROUNDDOWN(F1,0) -> 2 | U1: =CONCATENATE(N4,N9,N18,N27) -> 3.355555555555563.259259259259263.120370370370371
A3: S. No. | B3: High Level Description | C3: Control Description | D3: Identified Key Controls (K) | E3: Control | F3: Preventive/ Detective/Corrective | G3: Documentation | H3: Implementation | I3: Automation | J3: Monitor & Review | K3: Control Rating | L3: Rating with Key controls weightage | M3: Average Rating | N3: Maturity Rating (1 - 5) | O3: Category | S3: Doc | T3: Impl | U3: Auto | V3: Review
A4: 2.1 | B4: Policy and procedures | C4: Access control policy should be established, documented and approved by authorised individuals. The document should be reviewed periodically and updated whenever significant changes occur. | D4: K | E4: Organization should have an Access Management policy/ procedure defined, approved by the management | F4: Preventive | G4: Informally Documented | H4: 0 - 50% Implemented | I4: Partially Automated | J4: Partially Monitored & Reviewed | K4: =IF(W4="NANANANA",S4,IF(AND(OR(G4="Formally Documented",G4="Informally Documented"),H4="Not Implemented"),0.5*AVERAGE(S4:V4),AVERAGE(S4:V4))) -> 2 | L4: =IF(AND(D4="K",K4=1),'Maturity Rating'!$E$8,IF(K4="NA",K4,IF(D4="K",K4*'Maturity Rating'!$E$7,K4))) -> 2.4 | M4: =IF(X4="NANANANA",K4,AVERAGE(L4:L8)) -> 2.0133333 | N4: =IF(M4<1.1,1,IF(M4="NA",M4,(MIN(5,M4/3*5)))) -> 3.3555556 | O4: =IF(N4="NA",N4,VLOOKUP(Q4,'Maturity Rating'!G4:H8,2,FALSE)) -> Defined | Q4: =IF(N4="NA",N4,ROUNDDOWN(N4,0)) -> 3 | S4: =VLOOKUP(G4,'Maturity Rating'!A$2:B$5,2,FALSE) -> 2 | T4: =VLOOKUP(H4,'Maturity Rating'!A$8:B$11,2,FALSE) -> 2 | U4: =VLOOKUP(I4,'Maturity Rating'!A$14:B$17,2,FALSE) -> 2 | V4: =VLOOKUP(J4,'Maturity Rating'!A$20:B$23,2,FALSE) -> 2 | W4: =CONCATENATE(S4,T4,U4,V4) -> 2222 | X4: =CONCATENATE(L4,L5,L6,L8) -> 2.421.666666666666671
A5: 2.2 | E5: Organization should have a password policy defined and approved by the management | F5: Preventive | G5: Informally Documented | H5: 0 - 50% Implemented | I5: Partially Automated | J5: Partially Monitored & Reviewed | K5: =IF(W5="NANANANA",S5,IF(AND(OR(G5="Formally Documented",G5="Informally Documented"),H5="Not Implemented"),0.5*AVERAGE(S5:V5),AVERAGE(S5:V5))) -> 2 | L5: =IF(AND(D5="K",K5=1),'Maturity Rating'!$E$8,IF(K5="NA",K5,IF(D5="K",K5*'Maturity Rating'!$E$7,K5))) -> 2 | S5: =VLOOKUP(G5,'Maturity Rating'!A$2:B$5,2,FALSE) -> 2 | T5: =VLOOKUP(H5,'Maturity Rating'!A$8:B$11,2,FALSE) -> 2 | U5: =VLOOKUP(I5,'Maturity Rating'!A$14:B$17,2,FALSE) -> 2 | V5: =VLOOKUP(J5,'Maturity Rating'!A$20:B$23,2,FALSE) -> 2 | W5: =CONCATENATE(S5,T5,U5,V5) -> 2222
A6: 2.3 | E6: The documents are reviewed, updated and approved as per the defined frequency in the policy/ procedure. | F6: Preventive | G6: Informally Documented | H6: 0 - 50% Implemented | I6: Not Automated | J6: Not Applicable | K6: =IF(W6="NANANANA",S6,IF(AND(OR(G6="Formally Documented",G6="Informally Documented"),H6="Not Implemented"),0.5*AVERAGE(S6:V6),AVERAGE(S6:V6))) -> 1.6666667 | L6: =IF(AND(D6="K",K6=1),'Maturity Rating'!$E$8,IF(K6="NA",K6,IF(D6="K",K6*'Maturity Rating'!$E$7,K6))) -> 1.6666667 | S6: =VLOOKUP(G6,'Maturity Rating'!A$2:B$5,2,FALSE) -> 2 | T6: =VLOOKUP(H6,'Maturity Rating'!A$8:B$11,2,FALSE) -> 2 | U6: =VLOOKUP(I6,'Maturity Rating'!A$14:B$17,2,FALSE) -> 1 | V6: =VLOOKUP(J6,'Maturity Rating'!A$20:B$23,2,FALSE) -> NA | W6: =CONCATENATE(S6,T6,U6,V6) -> 221NA
A7: 2.4 | E7: The version control of the documents should be maintained | F7: Preventive | G7: Formally Documented | H7: 51 - 100% Implemented | I7: Automated | J7: Monitored & Reviewed | K7: =IF(W7="NANANANA",S7,IF(AND(OR(G7="Formally Documented",G7="Informally Documented"),H7="Not Implemented"),0.5*AVERAGE(S7:V7),AVERAGE(S7:V7))) -> 3 | L7: =IF(AND(D7="K",K7=1),'Maturity Rating'!$E$8,IF(K7="NA",K7,IF(D7="K",K7*'Maturity Rating'!$E$7,K7))) -> 3 | S7: =VLOOKUP(G7,'Maturity Rating'!A$2:B$5,2,FALSE) -> 3 | T7: =VLOOKUP(H7,'Maturity Rating'!A$8:B$11,2,FALSE) -> 3 | U7: =VLOOKUP(I7,'Maturity Rating'!A$14:B$17,2,FALSE) -> 3 | V7: =VLOOKUP(J7,'Maturity Rating'!A$20:B$23,2,FALSE) -> 3 | W7: =CONCATENATE(S7,T7,U7,V7) -> 3333
A8: 2.5 | E8: There is process defined for the management of the Non-domain ID | F8: Preventive | G8: Not Documented | H8: Not Implemented | I8: Not Applicable | J8: Not Applicable | K8: =IF(W8="NANANANA",S8,IF(AND(OR(G8="Formally Documented",G8="Informally Documented"),H8="Not Implemented"),0.5*AVERAGE(S8:V8),AVERAGE(S8:V8))) -> 1 | L8: =IF(AND(D8="K",K8=1),'Maturity Rating'!$E$8,IF(K8="NA",K8,IF(D8="K",K8*'Maturity Rating'!$E$7,K8))) -> 1 | S8: =VLOOKUP(G8,'Maturity Rating'!A$2:B$5,2,FALSE) -> 1 | T8: =VLOOKUP(H8,'Maturity Rating'!A$8:B$11,2,FALSE) -> 1 | U8: =VLOOKUP(I8,'Maturity Rating'!A$14:B$17,2,FALSE) -> NA | V8: =VLOOKUP(J8,'Maturity Rating'!A$20:B$23,2,FALSE) -> NA | W8: =CONCATENATE(S8,T8,U8,V8) -> 11NANA
A9: 2.6 | B9: Access provisioning and deprovisioning | C9: There is a formal user access provisioning and de-provisioning process defined for granting and revoking access to all information systems and services.(for Employees and Third parties) | E9: Access to information systems and services should be granted only post authorised approvals | F9: Preventive | G9: Formally Documented | H9: 51 - 100% Implemented | I9: Automated | J9: Monitored & Reviewed | K9: =IF(W9="NANANANA",S9,IF(AND(OR(G9="Formally Documented",G9="Informally Documented"),H9="Not Implemented"),0.5*AVERAGE(S9:V9),AVERAGE(S9:V9))) -> 3 | L9: =IF(AND(D9="K",K9=1),'Maturity Rating'!$E$8,IF(K9="NA",K9,IF(D9="K",K9*'Maturity Rating'!$E$7,K9))) -> 3 | M9: =IF(X9="NANANANANANANANA",K9,AVERAGE(L9:L17)) -> 1.9555556 | N9: =IF(M9<1.1,1,IF(M9="NA",M9,(MIN(5,M9/3*5)))) -> 3.2592593 | O9: =IF(N9="NA",N9,VLOOKUP(Q9,'Maturity Rating'!G4:H8,2,FALSE)) -> Defined | Q9: =IF(N9="NA",N9,ROUNDDOWN(N9,0)) -> 3 | S9: =VLOOKUP(G9,'Maturity Rating'!A$2:B$5,2,FALSE) -> 3 | T9: =VLOOKUP(H9,'Maturity Rating'!A$8:B$11,2,FALSE) -> 3 | U9: =VLOOKUP(I9,'Maturity Rating'!A$14:B$17,2,FALSE) -> 3 | V9: =VLOOKUP(J9,'Maturity Rating'!A$20:B$23,2,FALSE) -> 3 | W9: =CONCATENATE(S9,T9,U9,V9) -> 3333 | X9: =CONCATENATE(L9,L10,L11,L12,L13,L14,L15,L16,L17) -> 311.533.612.511
A10: 2.7 | E10: Access rights are granted based on the principle of least privilege | F10: Preventive | G10: Not Documented | H10: Not Implemented | I10: Not Automated | J10: Not Monitored & Reviewed | K10: =IF(W10="NANANANA",S10,IF(AND(OR(G10="Formally Documented",G10="Informally Documented"),H10="Not Implemented"),0.5*AVERAGE(S10:V10),AVERAGE(S10:V10))) -> 1 | L10: =IF(AND(D10="K",K10=1),'Maturity Rating'!$E$8,IF(K10="NA",K10,IF(D10="K",K10*'Maturity Rating'!$E$7,K10))) -> 1 | S10: =VLOOKUP(G10,'Maturity Rating'!A$2:B$5,2,FALSE) -> 1 | T10: =VLOOKUP(H10,'Maturity Rating'!A$8:B$11,2,FALSE) -> 1 | U10: =VLOOKUP(I10,'Maturity Rating'!A$14:B$17,2,FALSE) -> 1 | V10: =VLOOKUP(J10,'Maturity Rating'!A$20:B$23,2,FALSE) -> 1 | W10: =CONCATENATE(S10,T10,U10,V10) -> 1111
A11: 2.8 | E11: User IDs are uniquely created to establish accountability within the organization and generic IDs should be used subject to management approval | F11: Detective | G11: Informally Documented | H11: 0 - 50% Implemented | I11: Not Automated | J11: Not Monitored & Reviewed | K11: =IF(W11="NANANANA",S11,IF(AND(OR(G11="Formally Documented",G11="Informally Documented"),H11="Not Implemented"),0.5*AVERAGE(S11:V11),AVERAGE(S11:V11))) -> 1.5 | L11: =IF(AND(D11="K",K11=1),'Maturity Rating'!$E$8,IF(K11="NA",K11,IF(D11="K",K11*'Maturity Rating'!$E$7,K11))) -> 1.5 | S11: =VLOOKUP(G11,'Maturity Rating'!A$2:B$5,2,FALSE) -> 2 | T11: =VLOOKUP(H11,'Maturity Rating'!A$8:B$11,2,FALSE) -> 2 | U11: =VLOOKUP(I11,'Maturity Rating'!A$14:B$17,2,FALSE) -> 1 | V11: =VLOOKUP(J11,'Maturity Rating'!A$20:B$23,2,FALSE) -> 1 | W11: =CONCATENATE(S11,T11,U11,V11) -> 2211
A12: 2.9 | E12: Central record is maintained of all access rights granted to users. | F12: Detective | G12: Formally Documented | H12: 51 - 100% Implemented | I12: Automated | J12: Monitored & Reviewed | K12: =IF(W12="NANANANA",S12,IF(AND(OR(G12="Formally Documented",G12="Informally Documented"),H12="Not Implemented"),0.5*AVERAGE(S12:V12),AVERAGE(S12:V12))) -> 3 | L12: =IF(AND(D12="K",K12=1),'Maturity Rating'!$E$8,IF(K12="NA",K12,IF(D12="K",K12*'Maturity Rating'!$E$7,K12))) -> 3 | S12: =VLOOKUP(G12,'Maturity Rating'!A$2:B$5,2,FALSE) -> 3 | T12: =VLOOKUP(H12,'Maturity Rating'!A$8:B$11,2,FALSE) -> 3 | U12: =VLOOKUP(I12,'Maturity Rating'!A$14:B$17,2,FALSE) -> 3 | V12: =VLOOKUP(J12,'Maturity Rating'!A$20:B$23,2,FALSE) -> 3 | W12: =CONCATENATE(S12,T12,U12,V12) -> 3333
A13: 2. 10 | D13: K | E13: User access rights are reviewed by the authorised personnel at regular intervals defined in policy/ procedures. | F13: Preventive | G13: Formally Documented | H13: 51 - 100% Implemented | I13: Automated | J13: Monitored & Reviewed | K13: =IF(W13="NANANANA",S13,IF(AND(OR(G13="Formally Documented",G13="Informally Documented"),H13="Not Implemented"),0.5*AVERAGE(S13:V13),AVERAGE(S13:V13))) -> 3 | L13: =IF(AND(D13="K",K13=1),'Maturity Rating'!$E$8,IF(K13="NA",K13,IF(D13="K",K13*'Maturity Rating'!$E$7,K13))) -> 3.6 | S13: =VLOOKUP(G13,'Maturity Rating'!A$2:B$5,2,FALSE) -> 3 | T13: =VLOOKUP(H13,'Maturity Rating'!A$8:B$11,2,FALSE) -> 3 | U13: =VLOOKUP(I13,'Maturity Rating'!A$14:B$17,2,FALSE) -> 3 | V13: =VLOOKUP(J13,'Maturity Rating'!A$20:B$23,2,FALSE) -> 3 | W13: =CONCATENATE(S13,T13,U13,V13) -> 3333
A14: 2.11 | E14: Access to information systems and services should be revoked post termination of the employee within the defined period. | F14: Preventive | G14: Not Documented | H14: Not Implemented | I14: Not Automated | J14: Not Monitored & Reviewed | K14: =IF(W14="NANANANA",S14,IF(AND(OR(G14="Formally Documented",G14="Informally Documented"),H14="Not Implemented"),0.5*AVERAGE(S14:V14),AVERAGE(S14:V14))) -> 1 | L14: =IF(AND(D14="K",K14=1),'Maturity Rating'!$E$8,IF(K14="NA",K14,IF(D14="K",K14*'Maturity Rating'!$E$7,K14))) -> 1 | S14: =VLOOKUP(G14,'Maturity Rating'!A$2:B$5,2,FALSE) -> 1 | T14: =VLOOKUP(H14,'Maturity Rating'!A$8:B$11,2,FALSE) -> 1 | U14: =VLOOKUP(I14,'Maturity Rating'!A$14:B$17,2,FALSE) -> 1 | V14: =VLOOKUP(J14,'Maturity Rating'!A$20:B$23,2,FALSE) -> 1 | W14: =CONCATENATE(S14,T14,U14,V14) -> 1111
A15: 2.12 | E15: "Restricted access and authorised use only" warnings are displayed upon access to all systems | F15: Preventive | G15: Formally Documented | H15: 51 - 100% Implemented | I15: Automated | J15: Not Monitored & Reviewed | K15: =IF(W15="NANANANA",S15,IF(AND(OR(G15="Formally Documented",G15="Informally Documented"),H15="Not Implemented"),0.5*AVERAGE(S15:V15),AVERAGE(S15:V15))) -> 2.5 | L15: =IF(AND(D15="K",K15=1),'Maturity Rating'!$E$8,IF(K15="NA",K15,IF(D15="K",K15*'Maturity Rating'!$E$7,K15))) -> 2.5 | S15: =VLOOKUP(G15,'Maturity Rating'!A$2:B$5,2,FALSE) -> 3 | T15: =VLOOKUP(H15,'Maturity Rating'!A$8:B$11,2,FALSE) -> 3 | U15: =VLOOKUP(I15,'Maturity Rating'!A$14:B$17,2,FALSE) -> 3 | V15: =VLOOKUP(J15,'Maturity Rating'!A$20:B$23,2,FALSE) -> 1 | W15: =CONCATENATE(S15,T15,U15,V15) -> 3331
A16: 2.13 | E16: Application specific user review are performed as per the defined frequency in the policy/ procedure. Also inactive user are disabled. | F16: Preventive | G16: Not Documented | H16: Not Implemented | I16: Not Automated | J16: Not Monitored & Reviewed | K16: =IF(W16="NANANANA",S16,IF(AND(OR(G16="Formally Documented",G16="Informally Documented"),H16="Not Implemented"),0.5*AVERAGE(S16:V16),AVERAGE(S16:V16))) -> 1 | L16: =IF(AND(D16="K",K16=1),'Maturity Rating'!$E$8,IF(K16="NA",K16,IF(D16="K",K16*'Maturity Rating'!$E$7,K16))) -> 1 | S16: =VLOOKUP(G16,'Maturity Rating'!A$2:B$5,2,FALSE) -> 1 | T16: =VLOOKUP(H16,'Maturity Rating'!A$8:B$11,2,FALSE) -> 1 | U16: =VLOOKUP(I16,'Maturity Rating'!A$14:B$17,2,FALSE) -> 1 | V16: =VLOOKUP(J16,'Maturity Rating'!A$20:B$23,2,FALSE) -> 1 | W16: =CONCATENATE(S16,T16,U16,V16) -> 1111
A17: 2.14 | E17: Enable accounts used by vendors for remote maintenance only during the time needed. | F17: Preventive | G17: Not Documented | H17: Not Implemented | I17: Not Automated | J17: Not Monitored & Reviewed | K17: =IF(W17="NANANANA",S17,IF(AND(OR(G17="Formally Documented",G17="Informally Documented"),H17="Not Implemented"),0.5*AVERAGE(S17:V17),AVERAGE(S17:V17))) -> 1 | L17: =IF(AND(D17="K",K17=1),'Maturity Rating'!$E$8,IF(K17="NA",K17,IF(D17="K",K17*'Maturity Rating'!$E$7,K17))) -> 1 | S17: =VLOOKUP(G17,'Maturity Rating'!A$2:B$5,2,FALSE) -> 1 | T17: =VLOOKUP(H17,'Maturity Rating'!A$8:B$11,2,FALSE) -> 1 | U17: =VLOOKUP(I17,'Maturity Rating'!A$14:B$17,2,FALSE) -> 1 | V17: =VLOOKUP(J17,'Maturity Rating'!A$20:B$23,2,FALSE) -> 1 | W17: =CONCATENATE(S17,T17,U17,V17) -> 1111
A18: 2.15 | B18: Password Management | C18: Secure password management processes should be implemented consistently within the organization | E18: Passwords for the end users and administrators must be configured based on the password policy defined for the organization. | F18: Preventive | G18: Not Documented | H18: Not Implemented | I18: Not Applicable | J18: Not Applicable | K18: =IF(W18="NANANANA",S18,IF(AND(OR(G18="Formally Documented",G18="Informally Documented"),H18="Not Implemented"),0.5*AVERAGE(S18:V18),AVERAGE(S18:V18))) -> 1 | L18: =IF(AND(D18="K",K18=1),'Maturity Rating'!$E$8,IF(K18="NA",K18,IF(D18="K",K18*'Maturity Rating'!$E$7,K18))) -> 1 | M18: =IF(X18="NANANANANANANANANANA",K18,AVERAGE(L18:L26)) -> 1.8722222 | N18: =IF(M18<1.1,1,IF(M18="NA",M18,(MIN(5,M18/3*5)))) -> 3.1203704 | O18: =IF(N18="NA",N18,VLOOKUP(Q18,'Maturity Rating'!G4:H8,2,FALSE)) -> Defined | Q18: =IF(N18="NA",N18,ROUNDDOWN(N18,0)) -> 3 | S18: =VLOOKUP(G18,'Maturity Rating'!A$2:B$5,2,FALSE) -> 1 | T18: =VLOOKUP(H18,'Maturity Rating'!A$8:B$11,2,FALSE) -> 1 | U18: =VLOOKUP(I18,'Maturity Rating'!A$14:B$17,2,FALSE) -> NA | V18: =VLOOKUP(J18,'Maturity Rating'!A$20:B$23,2,FALSE) -> NA | W18: =CONCATENATE(S18,T18,U18,V18) -> 11NANA | X18: =CONCATENATE(L18,L19,L20,L21,L22,L23,L24,L26) -> 12.52.753.61131
A19: 2.16 | E19: All default manufacturers passwords and/or end user passwords are changed upon first login. Also the user should be asked to reset its password upon first login | F19: Preventive | G19: Formally Documented | H19: 51 - 100% Implemented | I19: Automated | J19: Not Monitored & Reviewed | K19: =IF(W19="NANANANA",S19,IF(AND(OR(G19="Formally Documented",G19="Informally Documented"),H19="Not Implemented"),0.5*AVERAGE(S19:V19),AVERAGE(S19:V19))) -> 2.5 | L19: =IF(AND(D19="K",K19=1),'Maturity Rating'!$E$8,IF(K19="NA",K19,IF(D19="K",K19*'Maturity Rating'!$E$7,K19))) -> 2.5 | S19: =VLOOKUP(G19,'Maturity Rating'!A$2:B$5,2,FALSE) -> 3 | T19: =VLOOKUP(H19,'Maturity Rating'!A$8:B$11,2,FALSE) -> 3 | U19: =VLOOKUP(I19,'Maturity Rating'!A$14:B$17,2,FALSE) -> 3 | V19: =VLOOKUP(J19,'Maturity Rating'!A$20:B$23,2,FALSE) -> 1 | W19: =CONCATENATE(S19,T19,U19,V19) -> 3331
A20: 2.17 | E20: Password should be stored securely and should not be shared with anyone. | F20: Preventive | G20: Formally Documented | H20: 51 - 100% Implemented | I20: Automated | J20: Partially Monitored & Reviewed | K20: =IF(W20="NANANANA",S20,IF(AND(OR(G20="Formally Documented",G20="Informally Documented"),H20="Not Implemented"),0.5*AVERAGE(S20:V20),AVERAGE(S20:V20))) -> 2.75 | L20: =IF(AND(D20="K",K20=1),'Maturity Rating'!$E$8,IF(K20="NA",K20,IF(D20="K",K20*'Maturity Rating'!$E$7,K20))) -> 2.75 | S20: =VLOOKUP(G20,'Maturity Rating'!A$2:B$5,2,FALSE) -> 3 | T20: =VLOOKUP(H20,'Maturity Rating'!A$8:B$11,2,FALSE) -> 3 | U20: =VLOOKUP(I20,'Maturity Rating'!A$14:B$17,2,FALSE) -> 3 | V20: =VLOOKUP(J20,'Maturity Rating'!A$20:B$23,2,FALSE) -> 2 | W20: =CONCATENATE(S20,T20,U20,V20) -> 3332
A21: 2.18 | D21: K | E21: Password should be alpha numeric, special character, minimum 8 characters and should not include dictionary words. | F21: Preventive | G21: Formally Documented | H21: 51 - 100% Implemented | I21: Automated | J21: Monitored & Reviewed | K21: =IF(W21="NANANANA",S21,IF(AND(OR(G21="Formally Documented",G21="Informally Documented"),H21="Not Implemented"),0.5*AVERAGE(S21:V21),AVERAGE(S21:V21))) -> 3 | L21: =IF(AND(D21="K",K21=1),'Maturity Rating'!$E$8,IF(K21="NA",K21,IF(D21="K",K21*'Maturity Rating'!$E$7,K21))) -> 3.6 | S21: =VLOOKUP(G21,'Maturity Rating'!A$2:B$5,2,FALSE) -> 3 | T21: =VLOOKUP(H21,'Maturity Rating'!A$8:B$11,2,FALSE) -> 3 | U21: =VLOOKUP(I21,'Maturity Rating'!A$14:B$17,2,FALSE) -> 3 | V21: =VLOOKUP(J21,'Maturity Rating'!A$20:B$23,2,FALSE) -> 3 | W21: =CONCATENATE(S21,T21,U21,V21) -> 3333
A22: 2.19 | E22: There is an enforced limit of invalid / failed logon attempts as per the defined password management policy of the organization | F22: Preventive | G22: Not Documented | H22: Not Implemented | I22: Not Automated | J22: Not Monitored & Reviewed | K22: =IF(W22="NANANANA",S22,IF(AND(OR(G22="Formally Documented",G22="Informally Documented"),H22="Not Implemented"),0.5*AVERAGE(S22:V22),AVERAGE(S22:V22))) -> 1 | L22: =IF(AND(D22="K",K22=1),'Maturity Rating'!$E$8,IF(K22="NA",K22,IF(D22="K",K22*'Maturity Rating'!$E$7,K22))) -> 1 | S22: =VLOOKUP(G22,'Maturity Rating'!A$2:B$5,2,FALSE) -> 1 | T22: =VLOOKUP(H22,'Maturity Rating'!A$8:B$11,2,FALSE) -> 1 | U22: =VLOOKUP(I22,'Maturity Rating'!A$14:B$17,2,FALSE) -> 1 | V22: =VLOOKUP(J22,'Maturity Rating'!A$20:B$23,2,FALSE) -> 1 | W22: =CONCATENATE(S22,T22,U22,V22) -> 1111
A23: 2. 20 | E23: The session should be automatically locked as per the duration defined by the organization. | F23: Preventive | G23: Not Documented | H23: Not Implemented | I23: Not Automated | J23: Not Monitored & Reviewed | K23: =IF(W23="NANANANA",S23,IF(AND(OR(G23="Formally Documented",G23="Informally Documented"),H23="Not Implemented"),0.5*AVERAGE(S23:V23),AVERAGE(S23:V23))) -> 1 | L23: =IF(AND(D23="K",K23=1),'Maturity Rating'!$E$8,IF(K23="NA",K23,IF(D23="K",K23*'Maturity Rating'!$E$7,K23))) -> 1 | S23: =VLOOKUP(G23,'Maturity Rating'!A$2:B$5,2,FALSE) -> 1 | T23: =VLOOKUP(H23,'Maturity Rating'!A$8:B$11,2,FALSE) -> 1 | U23: =VLOOKUP(I23,'Maturity Rating'!A$14:B$17,2,FALSE) -> 1 | V23: =VLOOKUP(J23,'Maturity Rating'!A$20:B$23,2,FALSE) -> 1 | W23: =CONCATENATE(S23,T23,U23,V23) -> 1111
A24: 2.23 | E24: Passwords should be changed at periodic intervals as per the password policy of the organization. | F24: Preventive | G24: Formally Documented | H24: 51 - 100% Implemented | I24: Automated | J24: Monitored & Reviewed | K24: =IF(W24="NANANANA",S24,IF(AND(OR(G24="Formally Documented",G24="Informally Documented"),H24="Not Implemented"),0.5*AVERAGE(S24:V24),AVERAGE(S24:V24))) -> 3 | L24: =IF(AND(D24="K",K24=1),'Maturity Rating'!$E$8,IF(K24="NA",K24,IF(D24="K",K24*'Maturity Rating'!$E$7,K24))) -> 3 | S24: =VLOOKUP(G24,'Maturity Rating'!A$2:B$5,2,FALSE) -> 3 | T24: =VLOOKUP(H24,'Maturity Rating'!A$8:B$11,2,FALSE) -> 3 | U24: =VLOOKUP(I24,'Maturity Rating'!A$14:B$17,2,FALSE) -> 3 | V24: =VLOOKUP(J24,'Maturity Rating'!A$20:B$23,2,FALSE) -> 3 | W24: =CONCATENATE(S24,T24,U24,V24) -> 3333
A25: 2.24 | E25: Service accounts with password never expiry are non-interactive. | F25: Preventive | G25: Not Documented | H25: Not Implemented | I25: Not Applicable | J25: Not Monitored & Reviewed | K25: =IF(W25="NANANANA",S25,IF(AND(OR(G25="Formally Documented",G25="Informally Documented"),H25="Not Implemented"),0.5*AVERAGE(S25:V25),AVERAGE(S25:V25))) -> 1 | L25: =IF(AND(D25="K",K25=1),'Maturity Rating'!$E$8,IF(K25="NA",K25,IF(D25="K",K25*'Maturity Rating'!$E$7,K25))) -> 1 | S25: =VLOOKUP(G25,'Maturity Rating'!A$2:B$5,2,FALSE) -> 1 | T25: =VLOOKUP(H25,'Maturity Rating'!A$8:B$11,2,FALSE) -> 1 | U25: =VLOOKUP(I25,'Maturity Rating'!A$14:B$17,2,FALSE) -> NA | V25: =VLOOKUP(J25,'Maturity Rating'!A$20:B$23,2,FALSE) -> 1 | W25: =CONCATENATE(S25,T25,U25,V25) -> 11NA1
A26: 2.25 | E26: Secret authentication information such as tokens, OTPs are used to login on critical applications and systems. | F26: Preventive | G26: Not Documented | H26: Not Implemented | I26: Not Automated | J26: Not Monitored & Reviewed | K26: =IF(W26="NANANANA",S26,IF(AND(OR(G26="Formally Documented",G26="Informally Documented"),H26="Not Implemented"),0.5*AVERAGE(S26:V26),AVERAGE(S26:V26))) -> 1 | L26: =IF(AND(D26="K",K26=1),'Maturity Rating'!$E$8,IF(K26="NA",K26,IF(D26="K",K26*'Maturity Rating'!$E$7,K26))) -> 1 | S26: =VLOOKUP(G26,'Maturity Rating'!A$2:B$5,2,FALSE) -> 1 | T26: =VLOOKUP(H26,'Maturity Rating'!A$8:B$11,2,FALSE) -> 1 | U26: =VLOOKUP(I26,'Maturity Rating'!A$14:B$17,2,FALSE) -> 1 | V26: =VLOOKUP(J26,'Maturity Rating'!A$20:B$23,2,FALSE) -> 1 | W26: =CONCATENATE(S26,T26,U26,V26) -> 1111
A27: 2.26 | B27: Privileged Identity Management | C27: Privileged access to information and services should be given on a need-to-know basis and should be managed securely. Applicability to Production/Dev/UAT and types of system(Servers, DB, Appliances, Network) | D27: K | E27: Access privileges must be granted based on the approvals by an authorised personnel. | F27: Preventive | G27: Not Documented | H27: Not Implemented | I27: Not Applicable | J27: Not Monitored & Reviewed | K27: =IF(W27="NANANANA",S27,IF(AND(OR(G27="Formally Documented",G27="Informally Documented"),H27="Not Implemented"),0.5*AVERAGE(S27:V27),AVERAGE(S27:V27))) -> 1 | L27: =IF(AND(D27="K",K27=1),'Maturity Rating'!$E$8,IF(K27="NA",K27,IF(D27="K",K27*'Maturity Rating'!$E$7,K27))) -> 0.8 | M27: =IF(X27="NANANANANANANA",K27,AVERAGE(L27:L35)) -> 0.975 | N27: =IF(M27<1.1,1,IF(M27="NA",M27,(MIN(5,M27/3*5)))) -> 1 | O27: =IF(N27="NA",N27,VLOOKUP(Q27,'Maturity Rating'!G4:H8,2,FALSE)) -> Initial | Q27: =IF(N27="NA",N27,ROUNDDOWN(N27,0)) -> 1 | S27: =VLOOKUP(G27,'Maturity Rating'!A$2:B$5,2,FALSE) -> 1 | T27: =VLOOKUP(H27,'Maturity Rating'!A$8:B$11,2,FALSE) -> 1 | U27: =VLOOKUP(I27,'Maturity Rating'!A$14:B$17,2,FALSE) -> NA | V27: =VLOOKUP(J27,'Maturity Rating'!A$20:B$23,2,FALSE) -> 1 | W27: =CONCATENATE(S27,T27,U27,V27) -> 11NA1 | X27: =CONCATENATE(L27,L28,L29,L30,L31,L32,L33,L34,L35) -> 0.811111NA11
A28: 2.27 | E28: Administrative activities are logged and the audit trails must be stored. | F28: Detective | G28: Not Documented | H28: Not Implemented | I28: Not Automated | J28: Not Monitored & Reviewed | K28: =IF(W28="NANANANA",S28,IF(AND(OR(G28="Formally Documented",G28="Informally Documented"),H28="Not Implemented"),0.5*AVERAGE(S28:V28),AVERAGE(S28:V28))) -> 1 | L28: =IF(AND(D28="K",K28=1),'Maturity Rating'!$E$8,IF(K28="NA",K28,IF(D28="K",K28*'Maturity Rating'!$E$7,K28))) -> 1 | S28: =VLOOKUP(G28,'Maturity Rating'!A$2:B$5,2,FALSE) -> 1 | T28: =VLOOKUP(H28,'Maturity Rating'!A$8:B$11,2,FALSE) -> 1 | U28: =VLOOKUP(I28,'Maturity Rating'!A$14:B$17,2,FALSE) -> 1 | V28: =VLOOKUP(J28,'Maturity Rating'!A$20:B$23,2,FALSE) -> 1 | W28: =CONCATENATE(S28,T28,U28,V28) -> 1111
A29: 2.28 | E29: Administrative IDs must be reviewed on a periodic basis by authorised personnel | F29: Detective | G29: Not Documented | H29: Not Implemented | I29: Not Automated | J29: Not Monitored & Reviewed | K29: =IF(W29="NANANANA",S29,IF(AND(OR(G29="Formally Documented",G29="Informally Documented"),H29="Not Implemented"),0.5*AVERAGE(S29:V29),AVERAGE(S29:V29))) -> 1 | L29: =IF(AND(D29="K",K29=1),'Maturity Rating'!$E$8,IF(K29="NA",K29,IF(D29="K",K29*'Maturity Rating'!$E$7,K29))) -> 1 | S29: =VLOOKUP(G29,'Maturity Rating'!A$2:B$5,2,FALSE) -> 1 | T29: =VLOOKUP(H29,'Maturity Rating'!A$8:B$11,2,FALSE) -> 1 | U29: =VLOOKUP(I29,'Maturity Rating'!A$14:B$17,2,FALSE) -> 1 | V29: =VLOOKUP(J29,'Maturity Rating'!A$20:B$23,2,FALSE) -> 1 | W29: =CONCATENATE(S29,T29,U29,V29) -> 1111
A30: 2.29 | E30: The privileged access rights must be revoked after the expiration of the validity period as mentioned in the user access management procedure | F30: Preventive | G30: Not Documented | H30: Not Implemented | I30: Not Automated | J30: Not Monitored & Reviewed | K30: =IF(W30="NANANANA",S30,IF(AND(OR(G30="Formally Documented",G30="Informally Documented"),H30="Not Implemented"),0.5*AVERAGE(S30:V30),AVERAGE(S30:V30))) -> 1 | L30: =IF(AND(D30="K",K30=1),'Maturity Rating'!$E$8,IF(K30="NA",K30,IF(D30="K",K30*'Maturity Rating'!$E$7,K30))) -> 1 | S30: =VLOOKUP(G30,'Maturity Rating'!A$2:B$5,2,FALSE) -> 1 | T30: =VLOOKUP(H30,'Maturity Rating'!A$8:B$11,2,FALSE) -> 1 | U30: =VLOOKUP(I30,'Maturity Rating'!A$14:B$17,2,FALSE) -> 1 | V30: =VLOOKUP(J30,'Maturity Rating'!A$20:B$23,2,FALSE) -> 1 | W30: =CONCATENATE(S30,T30,U30,V30) -> 1111
A31: 2. 30 | E31: There is a privilege identity management tool implemented for monitoring the privilege activity | F31: Detective | G31: Not Documented | H31: Not Implemented | I31: Not Automated | J31: Not Monitored & Reviewed | K31: =IF(W31="NANANANA",S31,IF(AND(OR(G31="Formally Documented",G31="Informally Documented"),H31="Not Implemented"),0.5*AVERAGE(S31:V31),AVERAGE(S31:V31))) -> 1 | L31: =IF(AND(D31="K",K31=1),'Maturity Rating'!$E$8,IF(K31="NA",K31,IF(D31="K",K31*'Maturity Rating'!$E$7,K31))) -> 1 | S31: =VLOOKUP(G31,'Maturity Rating'!A$2:B$5,2,FALSE) -> 1 | T31: =VLOOKUP(H31,'Maturity Rating'!A$8:B$11,2,FALSE) -> 1 | U31: =VLOOKUP(I31,'Maturity Rating'!A$14:B$17,2,FALSE) -> 1 | V31: =VLOOKUP(J31,'Maturity Rating'!A$20:B$23,2,FALSE) -> 1 | W31: =CONCATENATE(S31,T31,U31,V31) -> 1111
A32: 2.31 | E32: Privileged accounts are not shared among multiple users. | F32: Preventive | G32: Not Documented | H32: Not Implemented | I32: Not Automated | J32: Not Monitored & Reviewed | K32: =IF(W32="NANANANA",S32,IF(AND(OR(G32="Formally Documented",G32="Informally Documented"),H32="Not Implemented"),0.5*AVERAGE(S32:V32),AVERAGE(S32:V32))) -> 1 | L32: =IF(AND(D32="K",K32=1),'Maturity Rating'!$E$8,IF(K32="NA",K32,IF(D32="K",K32*'Maturity Rating'!$E$7,K32))) -> 1 | S32: =VLOOKUP(G32,'Maturity Rating'!A$2:B$5,2,FALSE) -> 1 | T32: =VLOOKUP(H32,'Maturity Rating'!A$8:B$11,2,FALSE) -> 1 | U32: =VLOOKUP(I32,'Maturity Rating'!A$14:B$17,2,FALSE) -> 1 | V32: =VLOOKUP(J32,'Maturity Rating'!A$20:B$23,2,FALSE) -> 1 | W32: =CONCATENATE(S32,T32,U32,V32) -> 1111
A33: 2.32 | E33: Multifactor authentication should be implemented for PIM | F33: Preventive | G33: Not Applicable | H33: Not Applicable | I33: Not Applicable | J33: Not Applicable | K33: =IF(W33="NANANANA",S33,IF(AND(OR(G33="Formally Documented",G33="Informally Documented"),H33="Not Implemented"),0.5*AVERAGE(S33:V33),AVERAGE(S33:V33))) -> NA | L33: =IF(AND(D33="K",K33=1),'Maturity Rating'!$E$8,IF(K33="NA",K33,IF(D33="K",K33*'Maturity Rating'!$E$7,K33))) -> NA | S33: =VLOOKUP(G33,'Maturity Rating'!A$2:B$5,2,FALSE) -> NA | T33: =VLOOKUP(H33,'Maturity Rating'!A$8:B$11,2,FALSE) -> NA | U33: =VLOOKUP(I33,'Maturity Rating'!A$14:B$17,2,FALSE) -> NA | V33: =VLOOKUP(J33,'Maturity Rating'!A$20:B$23,2,FALSE) -> NA | W33: =CONCATENATE(S33,T33,U33,V33) -> NANANANA
A34: 2.33 | E34: There should be a defined process in place to detect any PIM bypass | F34: Detective | G34: Not Documented | H34: Not Implemented | I34: Not Automated | J34: Not Monitored & Reviewed | K34: =IF(W34="NANANANA",S34,IF(AND(OR(G34="Formally Documented",G34="Informally Documented"),H34="Not Implemented"),0.5*AVERAGE(S34:V34),AVERAGE(S34:V34))) -> 1 | L34: =IF(AND(D34="K",K34=1),'Maturity Rating'!$E$8,IF(K34="NA",K34,IF(D34="K",K34*'Maturity Rating'!$E$7,K34))) -> 1 | S34: =VLOOKUP(G34,'Maturity Rating'!A$2:B$5,2,FALSE) -> 1 | T34: =VLOOKUP(H34,'Maturity Rating'!A$8:B$11,2,FALSE) -> 1 | U34: =VLOOKUP(I34,'Maturity Rating'!A$14:B$17,2,FALSE) -> 1 | V34: =VLOOKUP(J34,'Maturity Rating'!A$20:B$23,2,FALSE) -> 1 | W34: =CONCATENATE(S34,T34,U34,V34) -> 1111
A35: 2.34 | E35: Administrative credentials are stored securely either with an authorised personnel or in a safe custody. | F35: Preventive | G35: Not Documented | H35: Not Implemented | I35: Not Automated | J35: Not Monitored & Reviewed | K35: =IF(W35="NANANANA",S35,IF(AND(OR(G35="Formally Documented",G35="Informally Documented"),H35="Not Implemented"),0.5*AVERAGE(S35:V35),AVERAGE(S35:V35))) -> 1 | L35: =IF(AND(D35="K",K35=1),'Maturity Rating'!$E$8,IF(K35="NA",K35,IF(D35="K",K35*'Maturity Rating'!$E$7,K35))) -> 1 | S35: =VLOOKUP(G35,'Maturity Rating'!A$2:B$5,2,FALSE) -> 1 | T35: =VLOOKUP(H35,'Maturity Rating'!A$8:B$11,2,FALSE) -> 1 | U35: =VLOOKUP(I35,'Maturity Rating'!A$14:B$17,2,FALSE) -> 1 | V35: =VLOOKUP(J35,'Maturity Rating'!A$20:B$23,2,FALSE) -> 1 | W35: =CONCATENATE(S35,T35,U35,V35) -> 1111

Sheet Asset Management
C1: Average Domain Rating | E1: =IF(F1="NA","Not Applicable",VLOOKUP(T1,'Maturity Rating'!G4:H8,2,FALSE)) -> Partial | F1: =IF(U1="NANANA","NA",AVERAGE(N4:N26)) -> 2.7732564 | T1: =ROUNDDOWN(F1,0) -> 2 | U1: =CONCATENATE(N4,N9,N20) -> 4.116666666666672.179292929292932.02380952380952
A3: S. No. | B3: High Level Description | C3: Control Description | D3: Identified Key Controls (K) | E3: Control | F3: Preventive/ Detective/Corrective | G3: Documentation | H3: Implementation | I3: Automation | J3: Monitor & Review | K3: Control Rating | L3: Rating with Key controls weightage | M3: Average Raiding | N3: Maturity Rating (1 - 5) | O3: Category | S3: Doc | T3: Impl | U3: Auto | V3: Review
A4: 3.1 | B4: Policy and procedures | C4: Asset Management policy should be established, documented and approved by authorized individuals. The document should be reviewed periodically and updated whenever significant changes occur. | D4: K | E4: Organization should have an Asset Management policy/ procedure defined, approved by the management | F4: Preventive | G4: Formally Documented | H4: 51 - 100% Implemented | I4: Automated | J4: Monitored & Reviewed | K4: =IF(W4="NANANANA",S4,IF(AND(OR(G4="Formally Documented",G4="Informally Documented"),H4="Not Implemented"),0.5*AVERAGE(S4:V4),AVERAGE(S4:V4))) -> 3 | L4: =IF(AND(D4="K",K4=1),'Maturity Rating'!$E$8,IF(K4="NA",K4,IF(D4="K",K4*'Maturity Rating'!$E$7,K4))) -> 3.6 | M4: =IF(X4="NANANANA",K4,AVERAGE(L4:L8)) -> 2.47 | N4: =IF(M4<1.1,1,IF(M4="NA",M4,(MIN(5,M4/3*5)))) -> 4.1166667 | O4: =IF(N4="NA",N4,VLOOKUP(Q4,'Maturity Rating'!G4:H8,2,FALSE)) -> Repeatable | Q4: =IF(N4="NA",N4,ROUNDDOWN(N4,0)) -> 4 | S4: =VLOOKUP(G4,'Maturity Rating'!A$2:B$5,2,FALSE) -> 3 | T4: =VLOOKUP(H4,'Maturity Rating'!A$8:B$11,2,FALSE) -> 3 | U4: =VLOOKUP(I4,'Maturity Rating'!A$14:B$17,2,FALSE) -> 3 | V4: =VLOOKUP(J4,'Maturity Rating'!A$20:B$23,2,FALSE) -> 3 | W4: =CONCATENATE(S4,T4,U4,V4) -> 3333 | X4: =CONCATENATE(L4,L5,L6,L7,L8) -> 3.632.252.51
A5: 3.2 | E5: Organization should have an Acceptable usage policy/ procedure defined, approved by the management | F5: Preventive | G5: Formally Documented | H5: 51 - 100% Implemented | I5: Automated | J5: Monitored & Reviewed | K5: =IF(W5="NANANANA",S5,IF(AND(OR(G5="Formally Documented",G5="Informally Documented"),H5="Not Implemented"),0.5*AVERAGE(S5:V5),AVERAGE(S5:V5))) -> 3 | L5: =IF(AND(D5="K",K5=1),'Maturity Rating'!$E$8,IF(K5="NA",K5,IF(D5="K",K5*'Maturity Rating'!$E$7,K5))) -> 3 | S5: =VLOOKUP(G5,'Maturity Rating'!A$2:B$5,2,FALSE) -> 3 | T5: =VLOOKUP(H5,'Maturity Rating'!A$8:B$11,2,FALSE) -> 3 | U5: =VLOOKUP(I5,'Maturity Rating'!A$14:B$17,2,FALSE) -> 3 | V5: =VLOOKUP(J5,'Maturity Rating'!A$20:B$23,2,FALSE) -> 3 | W5: =CONCATENATE(S5,T5,U5,V5) -> 3333
A6: 3.3 | E6: The documents are reviewed, updated and approved as per the defined frequency in the policy/ procedure. | F6: Preventive | G6: Formally Documented | H6: 0 - 50% Implemented | I6: Partially Automated | J6: Partially Monitored & Reviewed | K6: =IF(W6="NANANANA",S6,IF(AND(OR(G6="Formally Documented",G6="Informally Documented"),H6="Not Implemented"),0.5*AVERAGE(S6:V6),AVERAGE(S6:V6))) -> 2.25 | L6: =IF(AND(D6="K",K6=1),'Maturity Rating'!$E$8,IF(K6="NA",K6,IF(D6="K",K6*'Maturity Rating'!$E$7,K6))) -> 2.25 | S6: =VLOOKUP(G6,'Maturity Rating'!A$2:B$5,2,FALSE) -> 3 | T6: =VLOOKUP(H6,'Maturity Rating'!A$8:B$11,2,FALSE) -> 2 | U6: =VLOOKUP(I6,'Maturity Rating'!A$14:B$17,2,FALSE) -> 2 | V6: =VLOOKUP(J6,'Maturity Rating'!A$20:B$23,2,FALSE) -> 2 | W6: =CONCATENATE(S6,T6,U6,V6) -> 3222
A7: 3.4 | E7: The process of protecting media against unauthorized access, misuse or corruption, damage during transportation has been defined and implemented | F7: Preventive | G7: Formally Documented | H7: 0 - 50% Implemented | I7: Automated | J7: Partially Monitored & Reviewed | K7: =IF(W7="NANANANA",S7,IF(AND(OR(G7="Formally Documented",G7="Informally Documented"),H7="Not Implemented"),0.5*AVERAGE(S7:V7),AVERAGE(S7:V7))) -> 2.5 | L7: =IF(AND(D7="K",K7=1),'Maturity Rating'!$E$8,IF(K7="NA",K7,IF(D7="K",K7*'Maturity Rating'!$E$7,K7))) -> 2.5 | S7: =VLOOKUP(G7,'Maturity Rating'!A$2:B$5,2,FALSE) -> 3 | T7: =VLOOKUP(H7,'Maturity Rating'!A$8:B$11,2,FALSE) -> 2 | U7: =VLOOKUP(I7,'Maturity Rating'!A$14:B$17,2,FALSE) -> 3 | V7: =VLOOKUP(J7,'Maturity Rating'!A$20:B$23,2,FALSE) -> 2 | W7: =CONCATENATE(S7,T7,U7,V7) -> 3232
A8: 3.5 | E8: The version control of the documents should be maintained | F8: Preventive | G8: Not Documented | H8: Not Implemented | I8: Not Applicable | J8: Not Applicable | K8: =IF(W8="NANANANA",S8,IF(AND(OR(G8="Formally Documented",G8="Informally Documented"),H8="Not Implemented"),0.5*AVERAGE(S8:V8),AVERAGE(S8:V8))) -> 1 | L8: =IF(AND(D8="K",K8=1),'Maturity Rating'!$E$8,IF(K8="NA",K8,IF(D8="K",K8*'Maturity Rating'!$E$7,K8))) -> 1 | S8: =VLOOKUP(G8,'Maturity Rating'!A$2:B$5,2,FALSE) -> 1 | T8: =VLOOKUP(H8,'Maturity Rating'!A$8:B$11,2,FALSE) -> 1 | U8: =VLOOKUP(I8,'Maturity Rating'!A$14:B$17,2,FALSE) -> NA | V8: =VLOOKUP(J8,'Maturity Rating'!A$20:B$23,2,FALSE) -> NA | W8: =CONCATENATE(S8,T8,U8,V8) -> 11NANA
A9: 3.6 | B9: Inventory of Assets | C9: Ensure that all the organizational assets are identified, classified and appropriate level of protection in accordance with its importance to the organization are defined. | E9: There is a centralized configuration management system to manage the assets. | F9: Detective | G9: Not Documented | H9: Not Implemented | I9: Not Automated | J9: Not Monitored & Reviewed | K9: =IF(W9="NANANANA",S9,IF(AND(OR(G9="Formally Documented",G9="Informally Documented"),H9="Not Implemented"),0.5*AVERAGE(S9:V9),AVERAGE(S9:V9))) -> 1 | L9: =IF(AND(D9="K",K9=1),'Maturity Rating'!$E$8,IF(K9="NA",K9,IF(D9="K",K9*'Maturity Rating'!$E$7,K9))) -> 1 | M9: =IF(X9="NANANANA",K9,AVERAGE(L9:L19)) -> 1.3075758 | N9: =IF(M9<1.1,1,IF(M9="NA",M9,(MIN(5,M9/3*5)))) -> 2.1792929 | O9: =IF(N9="NA",N9,VLOOKUP(Q9,'Maturity Rating'!G4:H8,2,FALSE)) -> Partial | Q9: =IF(N9="NA",N9,ROUNDDOWN(N9,0)) -> 2 | S9: =VLOOKUP(G9,'Maturity Rating'!A$2:B$5,2,FALSE) -> 1 | T9: =VLOOKUP(H9,'Maturity Rating'!A$8:B$11,2,FALSE) -> 1 | U9: =VLOOKUP(I9,'Maturity Rating'!A$14:B$17,2,FALSE) -> 1 | V9: =VLOOKUP(J9,'Maturity Rating'!A$20:B$23,2,FALSE) -> 1 | W9: =CONCATENATE(S9,T9,U9,V9) -> 1111 | X9: =CONCATENATE(L9,L10,L11,L12,L13,L14,L15,L16,L17,L18,L19) -> 10.7511.333333333333331.81.251.2511.251.252.5
A10: 3.7 | D10: K | E10: All physical devices, systems, software platforms and applications within the organization are inventoried. | F10: Detective | G10: Informally Documented | H10: Not Implemented | I10: Not Automated | J10: Not Monitored & Reviewed | K10: =IF(W10="NANANANA",S10,IF(AND(OR(G10="Formally Documented",G10="Informally Documented"),H10="Not Implemented"),0.5*AVERAGE(S10:V10),AVERAGE(S10:V10))) -> 0.625 | L10: =IF(AND(D10="K",K10=1),'Maturity Rating'!$E$8,IF(K10="NA",K10,IF(D10="K",K10*'Maturity Rating'!$E$7,K10))) -> 0.75 | S10: =VLOOKUP(G10,'Maturity Rating'!A$2:B$5,2,FALSE) -> 2 | T10: =VLOOKUP(H10,'Maturity Rating'!A$8:B$11,2,FALSE) -> 1 | U10: =VLOOKUP(I10,'Maturity Rating'!A$14:B$17,2,FALSE) -> 1 | V10: =VLOOKUP(J10,'Maturity Rating'!A$20:B$23,2,FALSE) -> 1 | W10: =CONCATENATE(S10,T10,U10,V10) -> 2111
A11: 3.8 | E11: All new assets procured must be approved by an authorized individual. | F11: Preventive | G11: Not Documented | H11: Not Implemented | I11: Not Automated | J11: Not Monitored & Reviewed | K11: =IF(W11="NANANANA",S11,IF(AND(OR(G11="Formally Documented",G11="Informally Documented"),H11="Not Implemented"),0.5*AVERAGE(S11:V11),AVERAGE(S11:V11))) -> 1 | L11: =IF(AND(D11="K",K11=1),'Maturity Rating'!$E$8,IF(K11="NA",K11,IF(D11="K",K11*'Maturity Rating'!$E$7,K11))) -> 1 | S11: =VLOOKUP(G11,'Maturity Rating'!A$2:B$5,2,FALSE) -> 1 | T11: =VLOOKUP(H11,'Maturity Rating'!A$8:B$11,2,FALSE) -> 1 | U11: =VLOOKUP(I11,'Maturity Rating'!A$14:B$17,2,FALSE) -> 1 | V11: =VLOOKUP(J11,'Maturity Rating'!A$20:B$23,2,FALSE) -> 1 | W11: =CONCATENATE(S11,T11,U11,V11) -> 1111
A12: 3.9 | E12: All assets follow the defined asset labelling nomenclature. | F12: Detective | G12: Not Documented | H12: 0 - 50% Implemented | I12: Not Applicable | J12: Not Monitored & Reviewed | K12: =IF(W12="NANANANA",S12,IF(AND(OR(G12="Formally Documented",G12="Informally Documented"),H12="Not Implemented"),0.5*AVERAGE(S12:V12),AVERAGE(S12:V12))) -> 1.3333333 | L12: =IF(AND(D12="K",K12=1),'Maturity Rating'!$E$8,IF(K12="NA",K12,IF(D12="K",K12*'Maturity Rating'!$E$7,K12))) -> 1.3333333 | S12: =VLOOKUP(G12,'Maturity Rating'!A$2:B$5,2,FALSE) -> 1 | T12: =VLOOKUP(H12,'Maturity Rating'!A$8:B$11,2,FALSE) -> 2 | U12: =VLOOKUP(I12,'Maturity Rating'!A$14:B$17,2,FALSE) -> NA | V12: =VLOOKUP(J12,'Maturity Rating'!A$20:B$23,2,FALSE) -> 1 | W12: =CONCATENATE(S12,T12,U12,V12) -> 12NA1
A13: 3. 10 | D13: K | E13: Asset owner, custodian and asset ID are determined for all assets. | F13: Detective | G13: Informally Documented | H13: 0 - 50% Implemented | I13: Not Automated | J13: Not Monitored & Reviewed | K13: =IF(W13="NANANANA",S13,IF(AND(OR(G13="Formally Documented",G13="Informally Documented"),H13="Not Implemented"),0.5*AVERAGE(S13:V13),AVERAGE(S13:V13))) -> 1.5 | L13: =IF(AND(D13="K",K13=1),'Maturity Rating'!$E$8,IF(K13="NA",K13,IF(D13="K",K13*'Maturity Rating'!$E$7,K13))) -> 1.8 | S13: =VLOOKUP(G13,'Maturity Rating'!A$2:B$5,2,FALSE) -> 2 | T13: =VLOOKUP(H13,'Maturity Rating'!A$8:B$11,2,FALSE) -> 2 | U13: =VLOOKUP(I13,'Maturity Rating'!A$14:B$17,2,FALSE) -> 1 | V13: =VLOOKUP(J13,'Maturity Rating'!A$20:B$23,2,FALSE) -> 1 | W13: =CONCATENATE(S13,T13,U13,V13) -> 2211
A14: 3.11 | E14: Assets are classified based on their criticality | F14: Detective | G14: Not Documented | H14: 0 - 50% Implemented | I14: Not Automated | J14: Not Monitored & Reviewed | K14: =IF(W14="NANANANA",S14,IF(AND(OR(G14="Formally Documented",G14="Informally Documented"),H14="Not Implemented"),0.5*AVERAGE(S14:V14),AVERAGE(S14:V14))) -> 1.25 | L14: =IF(AND(D14="K",K14=1),'Maturity Rating'!$E$8,IF(K14="NA",K14,IF(D14="K",K14*'Maturity Rating'!$E$7,K14))) -> 1.25 | S14: =VLOOKUP(G14,'Maturity Rating'!A$2:B$5,2,FALSE) -> 1 | T14: =VLOOKUP(H14,'Maturity Rating'!A$8:B$11,2,FALSE) -> 2 | U14: =VLOOKUP(I14,'Maturity Rating'!A$14:B$17,2,FALSE) -> 1 | V14: =VLOOKUP(J14,'Maturity Rating'!A$20:B$23,2,FALSE) -> 1 | W14: =CONCATENATE(S14,T14,U14,V14) -> 1211
A15: 3.12 | E15: Assets are being used as per the guidelines documented in acceptable usage policy. | F15: Preventive | G15: Not Documented | H15: 0 - 50% Implemented | I15: Not Automated | J15: Not Monitored & Reviewed | K15: =IF(W15="NANANANA",S15,IF(AND(OR(G15="Formally Documented",G15="Informally Documented"),H15="Not Implemented"),0.5*AVERAGE(S15:V15),AVERAGE(S15:V15))) -> 1.25 | L15: =IF(AND(D15="K",K15=1),'Maturity Rating'!$E$8,IF(K15="NA",K15,IF(D15="K",K15*'Maturity Rating'!$E$7,K15))) -> 1.25 | S15: =VLOOKUP(G15,'Maturity Rating'!A$2:B$5,2,FALSE) -> 1 | T15: =VLOOKUP(H15,'Maturity Rating'!A$8:B$11,2,FALSE) -> 2 | U15: =VLOOKUP(I15,'Maturity Rating'!A$14:B$17,2,FALSE) -> 1 | V15: =VLOOKUP(J15,'Maturity Rating'!A$20:B$23,2,FALSE) -> 1 | W15: =CONCATENATE(S15,T15,U15,V15) -> 1211
A16: 3.13 | E16: Asset discovery tool is implemented to identify devices connected to the organization's network and update the hardware asset inventory. | F16: Detective | G16: Not Documented | H16: Not Implemented | I16: Not Automated | J16: Not Monitored & Reviewed | K16: =IF(W16="NANANANA",S16,IF(AND(OR(G16="Formally Documented",G16="Informally Documented"),H16="Not Implemented"),0.5*AVERAGE(S16:V16),AVERAGE(S16:V16))) -> 1 | L16: =IF(AND(D16="K",K16=1),'Maturity Rating'!$E$8,IF(K16="NA",K16,IF(D16="K",K16*'Maturity Rating'!$E$7,K16))) -> 1 | S16: =VLOOKUP(G16,'Maturity Rating'!A$2:B$5,2,FALSE) -> 1 | T16: =VLOOKUP(H16,'Maturity Rating'!A$8:B$11,2,FALSE) -> 1 | U16: =VLOOKUP(I16,'Maturity Rating'!A$14:B$17,2,FALSE) -> 1 | V16: =VLOOKUP(J16,'Maturity Rating'!A$20:B$23,2,FALSE) -> 1 | W16: =CONCATENATE(S16,T16,U16,V16) -> 1111
A17: 3.14 | E17: Employees, contractors must return all IT and non-IT assets at the time of transfer or exit from the organization. | F17: Preventive | G17: Not Documented | H17: 0 - 50% Implemented | I17: Not Automated | J17: Not Monitored & Reviewed | K17: =IF(W17="NANANANA",S17,IF(AND(OR(G17="Formally Documented",G17="Informally Documented"),H17="Not Implemented"),0.5*AVERAGE(S17:V17),AVERAGE(S17:V17))) -> 1.25 | L17: =IF(AND(D17="K",K17=1),'Maturity Rating'!$E$8,IF(K17="NA",K17,IF(D17="K",K17*'Maturity Rating'!$E$7,K17))) -> 1.25 | S17: =VLOOKUP(G17,'Maturity Rating'!A$2:B$5,2,FALSE) -> 1 | T17: =VLOOKUP(H17,'Maturity Rating'!A$8:B$11,2,FALSE) -> 2 | U17: =VLOOKUP(I17,'Maturity Rating'!A$14:B$17,2,FALSE) -> 1 | V17: =VLOOKUP(J17,'Maturity Rating'!A$20:B$23,2,FALSE) -> 1 | W17: =CONCATENATE(S17,T17,U17,V17) -> 1211
A18: 3.15 | E18: Annual maintenance contract should be maintained for all the assets (wherever applicable) present in the organization. | F18: Preventive | G18: Not Documented | H18: 0 - 50% Implemented | I18: Not Automated | J18: Not Monitored & Reviewed | K18: =IF(W18="NANANANA",S18,IF(AND(OR(G18="Formally Documented",G18="Informally Documented"),H18="Not Implemented"),0.5*AVERAGE(S18:V18),AVERAGE(S18:V18))) -> 1.25 | L18: =IF(AND(D18="K",K18=1),'Maturity Rating'!$E$8,IF(K18="NA",K18,IF(D18="K",K18*'Maturity Rating'!$E$7,K18))) -> 1.25 | S18: =VLOOKUP(G18,'Maturity Rating'!A$2:B$5,2,FALSE) -> 1 | T18: =VLOOKUP(H18,'Maturity Rating'!A$8:B$11,2,FALSE) -> 2 | U18: =VLOOKUP(I18,'Maturity Rating'!A$14:B$17,2,FALSE) -> 1 | V18: =VLOOKUP(J18,'Maturity Rating'!A$20:B$23,2,FALSE) -> 1 | W18: =CONCATENATE(S18,T18,U18,V18) -> 1211
A19: 3.16 | E19: The assets are disposed off as per the defined process | F19: Preventive | G19: Formally Documented | H19: 51 - 100% Implemented | I19: Automated | J19: Not Monitored & Reviewed | K19: =IF(W19="NANANANA",S19,IF(AND(OR(G19="Formally Documented",G19="Informally Documented"),H19="Not Implemented"),0.5*AVERAGE(S19:V19),AVERAGE(S19:V19))) -> 2.5 | L19: =IF(AND(D19="K",K19=1),'Maturity Rating'!$E$8,IF(K19="NA",K19,IF(D19="K",K19*'Maturity Rating'!$E$7,K19))) -> 2.5 | S19: =VLOOKUP(G19,'Maturity Rating'!A$2:B$5,2,FALSE) -> 3 | T19: =VLOOKUP(H19,'Maturity Rating'!A$8:B$11,2,FALSE) -> 3 | U19: =VLOOKUP(I19,'Maturity Rating'!A$14:B$17,2,FALSE) -> 3 | V19: =VLOOKUP(J19,'Maturity Rating'!A$20:B$23,2,FALSE) -> 1 | W19: =CONCATENATE(S19,T19,U19,V19) -> 3331
A20: 3.17 | B20: Media Handling | C20: To prevent unauthorized disclosure, modification, removal or destruction of information storage on media. | E20: Auto run option is disabled on machines | F20: Preventive | G20: Not Documented | H20: 0 - 50% Implemented | I20: Automated | J20: Not Monitored & Reviewed | K20: =IF(W20="NANANANA",S20,AVERAGE(S20:V20)) -> 1.75 | L20: =IF(AND(D20="K",K20=1),'Maturity Rating'!$E$8,IF(K20="NA",K20,IF(D20="K",K20*'Maturity Rating'!$E$7,K20))) -> 1.75 | M20: =IF(X20="NANANANANANANA",K20,AVERAGE(L20:L26)) -> 1.2142857 | N20: =IF(M20<1.1,1,IF(M20="NA",M20,(MIN(5,M20/3*5)))) -> 2.0238095 | O20: Partial | S20: =VLOOKUP(G20,'Maturity Rating'!A$2:B$5,2,FALSE) -> 1 | T20: =VLOOKUP(H20,'Maturity Rating'!A$8:B$11,2,FALSE) -> 2 | U20: =VLOOKUP(I20,'Maturity Rating'!A$14:B$17,2,FALSE) -> 3 | V20: =VLOOKUP(J20,'Maturity Rating'!A$20:B$23,2,FALSE) -> 1 | W20: =CONCATENATE(S20,T20,U20,V20) -> 1231 | X20: =CONCATENATE(L20,L21,L22,L23,L24,L25,L26) -> 1.75111111.75
A21: 3.18 | E21: Backup tapes are stored securely or in a fire proof container | F21: Preventive | G21: Not Documented | H21: Not Implemented | I21: Not Automated | J21: Not Monitored & Reviewed | K21: =IF(W21="NANANANA",S21,AVERAGE(S21:V21)) -> 1 | L21: =IF(AND(D21="K",K21=1),'Maturity Rating'!$E$8,IF(K21="NA",K21,IF(D21="K",K21*'Maturity Rating'!$E$7,K21))) -> 1 | S21: =VLOOKUP(G21,'Maturity Rating'!A$2:B$5,2,FALSE) -> 1 | T21: =VLOOKUP(H21,'Maturity Rating'!A$8:B$11,2,FALSE) -> 1 | U21: =VLOOKUP(I21,'Maturity Rating'!A$14:B$17,2,FALSE) -> 1 | V21: =VLOOKUP(J21,'Maturity Rating'!A$20:B$23,2,FALSE) -> 1 | W21: =CONCATENATE(S21,T21,U21,V21) -> 1111
A22: 3.19 | E22: All media devices are stored in a safe, secure environment | F22: Preventive | G22: Not Documented | H22: Not Implemented | I22: Not Automated | J22: Not Monitored & Reviewed | K22: =IF(W22="NANANANA",S22,AVERAGE(S22:V22)) -> 1 | L22: =IF(AND(D22="K",K22=1),'Maturity Rating'!$E$8,IF(K22="NA",K22,IF(D22="K",K22*'Maturity Rating'!$E$7,K22))) -> 1 | S22: =VLOOKUP(G22,'Maturity Rating'!A$2:B$5,2,FALSE) -> 1 | T22: =VLOOKUP(H22,'Maturity Rating'!A$8:B$11,2,FALSE) -> 1 | U22: =VLOOKUP(I22,'Maturity Rating'!A$14:B$17,2,FALSE) -> 1 | V22: =VLOOKUP(J22,'Maturity Rating'!A$20:B$23,2,FALSE) -> 1 | W22: =CONCATENATE(S22,T22,U22,V22) -> 1111
A23: 3. 20 | E23: Access to USB and other media ports should be blocked unless explicitly defined for business use. | F23: Preventive | G23: Not Documented | H23: Not Implemented | I23: Not Automated | J23: Not Monitored & Reviewed | K23: =IF(W23="NANANANA",S23,AVERAGE(S23:V23)) -> 1 | L23: =IF(AND(D23="K",K23=1),'Maturity Rating'!$E$8,IF(K23="NA",K23,IF(D23="K",K23*'Maturity Rating'!$E$7,K23))) -> 1 | S23: =VLOOKUP(G23,'Maturity Rating'!A$2:B$5,2,FALSE) -> 1 | T23: =VLOOKUP(H23,'Maturity Rating'!A$8:B$11,2,FALSE) -> 1 | U23: =VLOOKUP(I23,'Maturity Rating'!A$14:B$17,2,FALSE) -> 1 | V23: =VLOOKUP(J23,'Maturity Rating'!A$20:B$23,2,FALSE) -> 1 | W23: =CONCATENATE(S23,T23,U23,V23) -> 1111
A24: 3.21 | E24: Tape drives are stored at offsite location in a different seismic zone than the primary location | F24: Preventive | G24: Not Documented | H24: Not Implemented | I24: Not Automated | J24: Not Monitored & Reviewed | K24: =IF(W24="NANANANA",S24,AVERAGE(S24:V24)) -> 1 | L24: =IF(AND(D24="K",K24=1),'Maturity Rating'!$E$8,IF(K24="NA",K24,IF(D24="K",K24*'Maturity Rating'!$E$7,K24))) -> 1 | S24: =VLOOKUP(G24,'Maturity Rating'!A$2:B$5,2,FALSE) -> 1 | T24: =VLOOKUP(H24,'Maturity Rating'!A$8:B$11,2,FALSE) -> 1 | U24: =VLOOKUP(I24,'Maturity Rating'!A$14:B$17,2,FALSE) -> 1 | V24: =VLOOKUP(J24,'Maturity Rating'!A$20:B$23,2,FALSE) -> 1 | W24: =CONCATENATE(S24,T24,U24,V24) -> 1111
A25: 3.22 | E25: Fire and shock proof case and/ or cabinet are used for movement of tape drives from one location to another. | F25: Preventive | G25: Not Documented | H25: Not Implemented | I25: Not Automated | J25: Not Monitored & Reviewed | K25: =IF(W25="NANANANA",S25,AVERAGE(S25:V25)) -> 1 | L25: =IF(AND(D25="K",K25=1),'Maturity Rating'!$E$8,IF(K25="NA",K25,IF(D25="K",K25*'Maturity Rating'!$E$7,K25))) -> 1 | S25: =VLOOKUP(G25,'Maturity Rating'!A$2:B$5,2,FALSE) -> 1 | T25: =VLOOKUP(H25,'Maturity Rating'!A$8:B$11,2,FALSE) -> 1 | U25: =VLOOKUP(I25,'Maturity Rating'!A$14:B$17,2,FALSE) -> 1 | V25: =VLOOKUP(J25,'Maturity Rating'!A$20:B$23,2,FALSE) -> 1 | W25: =CONCATENATE(S25,T25,U25,V25) -> 1111
A26: 3.23 | E26: Media which is no longer in use must be disposed off securely by using the following methodologies (not limited to): Sanitization, Degaussing, Destruction. | F26: Preventive | G26: Informally Documented | H26: 0 - 50% Implemented | I26: Partially Automated | J26: Not Monitored & Reviewed | K26: =IF(W26="NANANANA",S26,AVERAGE(S26:V26)) -> 1.75 | L26: =IF(AND(D26="K",K26=1),'Maturity Rating'!$E$8,IF(K26="NA",K26,IF(D26="K",K26*'Maturity Rating'!$E$7,K26))) -> 1.75 | S26: =VLOOKUP(G26,'Maturity Rating'!A$2:B$5,2,FALSE) -> 2 | T26: =VLOOKUP(H26,'Maturity Rating'!A$8:B$11,2,FALSE) -> 2 | U26: =VLOOKUP(I26,'Maturity Rating'!A$14:B$17,2,FALSE) -> 2 | V26: =VLOOKUP(J26,'Maturity Rating'!A$20:B$23,2,FALSE) -> 1 | W26: =CONCATENATE(S26,T26,U26,V26) -> 2221

Sheet Incident Management
C1: Average Domain Rating | E1: =IF(F1="NA","Not Applicable",VLOOKUP(T1,'Maturity Rating'!G4:H8,2,FALSE)) -> Repeatable | F1: =IF(U1="NANANA","NA",AVERAGE(N4:N23)) -> 4.7861111 | T1: =ROUNDDOWN(F1,0) -> 4 | U1: =CONCATENATE(N4,N9,N11) -> 554.35833333333333
A3: S. No. | B3: High Level Description | C3: Control Description | D3: Identified Key Controls (K) | E3: Control | F3: Preventive/ Detective/Corrective | G3: Documentation | H3: Implementation | I3: Automation | J3: Monitor & Review | K3: Control Rating | L3: Rating with Key controls weightage | M3: Average Rating | N3: Maturity Rating (1 - 5) | O3: Category | S3: Doc | T3: Impl | U3: Auto | V3: Review
A4: 4.1 | B4: Policy and procedures | C4: Incident Management policy should be established, documented and approved by authorized individuals. The document should be reviewed periodically and updated whenever significant changes occur. | D4: K | E4: Organization should have an Incident Management policy/ procedure defined, approved by the management | F4: Preventive | G4: Formally Documented | H4: 51 - 100% Implemented | I4: Automated | J4: Monitored & Reviewed | K4: =IF(W4="NANANANA",S4,IF(AND(OR(G4="Formally Documented",G4="Informally Documented"),H4="Not Implemented"),0.5*AVERAGE(S4:V4),AVERAGE(S4:V4))) -> 3 | L4: =IF(AND(D4="K",K4=1),'Maturity Rating'!$E$8,IF(K4="NA",K4,IF(D4="K",K4*'Maturity Rating'!$E$7,K4))) -> 3.6 | M4: =IF(X4="NANANANANA",K4,AVERAGE(L4:L8)) -> 3.07 | N4: =IF(M4="NA",M4,(MIN(5,M4/3*5))) -> 5 | O4: =IF(N4="NA",N4,VLOOKUP(Q4,'Maturity Rating'!G4:H8,2,FALSE)) -> Adaptive | Q4: =IF(N4="NA",N4,ROUNDDOWN(N4,0)) -> 5 | S4: =VLOOKUP(G4,'Maturity Rating'!A$2:B$5,2,FALSE) -> 3 | T4: =VLOOKUP(H4,'Maturity Rating'!A$8:B$11,2,FALSE) -> 3 | U4: =VLOOKUP(I4,'Maturity Rating'!A$14:B$17,2,FALSE) -> 3 | V4: =VLOOKUP(J4,'Maturity Rating'!A$20:B$23,2,FALSE) -> 3 | W4: =CONCATENATE(S4,T4,U4,V4) -> 3333 | X4: =CONCATENATE(L4,L5,L6,L7,L8) -> 3.632.7533
A5: 4.2 | E5: The documents are reviewed, updated and approved as per the defined frequency in the policy/ procedure. | F5: Preventive | G5: Formally Documented | H5: 51 - 100% Implemented | I5: Automated | J5: Monitored & Reviewed | K5: =IF(W5="NANANANA",S5,IF(AND(OR(G5="Formally Documented",G5="Informally Documented"),H5="Not Implemented"),0.5*AVERAGE(S5:V5),AVERAGE(S5:V5))) -> 3 | L5: =IF(AND(D5="K",K5=1),'Maturity Rating'!$E$8,IF(K5="NA",K5,IF(D5="K",K5*'Maturity Rating'!$E$7,K5))) -> 3 | S5: =VLOOKUP(G5,'Maturity Rating'!A$2:B$5,2,FALSE) -> 3 | T5: =VLOOKUP(H5,'Maturity Rating'!A$8:B$11,2,FALSE) -> 3 | U5: =VLOOKUP(I5,'Maturity Rating'!A$14:B$17,2,FALSE) -> 3 | V5: =VLOOKUP(J5,'Maturity Rating'!A$20:B$23,2,FALSE) -> 3 | W5: =CONCATENATE(S5,T5,U5,V5) -> 3333
A6: 4.3 | E6: There is an incident response team existing within the organization | F6: Preventive | G6: Formally Documented | H6: 51 - 100% Implemented | I6: Automated | J6: Partially Monitored & Reviewed | K6: =IF(W6="NANANANA",S6,IF(AND(OR(G6="Formally Documented",G6="Informally Documented"),H6="Not Implemented"),0.5*AVERAGE(S6:V6),AVERAGE(S6:V6))) -> 2.75 | L6: =IF(AND(D6="K",K6=1),'Maturity Rating'!$E$8,IF(K6="NA",K6,IF(D6="K",K6*'Maturity Rating'!$E$7,K6))) -> 2.75 | S6: =VLOOKUP(G6,'Maturity Rating'!A$2:B$5,2,FALSE) -> 3 | T6: =VLOOKUP(H6,'Maturity Rating'!A$8:B$11,2,FALSE) -> 3 | U6: =VLOOKUP(I6,'Maturity Rating'!A$14:B$17,2,FALSE) -> 3 | V6: =VLOOKUP(J6,'Maturity Rating'!A$20:B$23,2,FALSE) -> 2 | W6: =CONCATENATE(S6,T6,U6,V6) -> 3332
A7: 4.4 | E7: There is an Incident response plan executed during or after an incident and the impact of incident is understood by the Incident Response Team | F7: Preventive | G7: Formally Documented | H7: 51 - 100% Implemented | I7: Automated | J7: Monitored & Reviewed | K7: =IF(W7="NANANANA",S7,IF(AND(OR(G7="Formally Documented",G7="Informally Documented"),H7="Not Implemented"),0.5*AVERAGE(S7:V7),AVERAGE(S7:V7))) -> 3 | L7: =IF(AND(D7="K",K7=1),'Maturity Rating'!$E$8,IF(K7="NA",K7,IF(D7="K",K7*'Maturity Rating'!$E$7,K7))) -> 3 | S7: =VLOOKUP(G7,'Maturity Rating'!A$2:B$5,2,FALSE) -> 3 | T7: =VLOOKUP(H7,'Maturity Rating'!A$8:B$11,2,FALSE) -> 3 | U7: =VLOOKUP(I7,'Maturity Rating'!A$14:B$17,2,FALSE) -> 3 | V7: =VLOOKUP(J7,'Maturity Rating'!A$20:B$23,2,FALSE) -> 3 | W7: =CONCATENATE(S7,T7,U7,V7) -> 3333
A8: 4.5 | E8: The version control of the documents should be maintained. | F8: Preventive | G8: Formally Documented | H8: 51 - 100% Implemented | I8: Automated | J8: Monitored & Reviewed | K8: =IF(W8="NANANANA",S8,IF(AND(OR(G8="Formally Documented",G8="Informally Documented"),H8="Not Implemented"),0.5*AVERAGE(S8:V8),AVERAGE(S8:V8))) -> 3 | L8: =IF(AND(D8="K",K8=1),'Maturity Rating'!$E$8,IF(K8="NA",K8,IF(D8="K",K8*'Maturity Rating'!$E$7,K8))) -> 3 | S8: =VLOOKUP(G8,'Maturity Rating'!A$2:B$5,2,FALSE) -> 3 | T8: =VLOOKUP(H8,'Maturity Rating'!A$8:B$11,2,FALSE) -> 3 | U8: =VLOOKUP(I8,'Maturity Rating'!A$14:B$17,2,FALSE) -> 3 | V8: =VLOOKUP(J8,'Maturity Rating'!A$20:B$23,2,FALSE) -> 3 | W8: =CONCATENATE(S8,T8,U8,V8) -> 3333
A9: 4.6 | B9: Roles and Responsibilities | C9: The Incident Response/ Incident Handling team is well informed of their roles and responsibilities in order to effectively carry out the process | E9: The incident response team/ information security team is trained to timely detect and handle the incident or attacker in case of cyber intrusion | F9: Detective | G9: Formally Documented | H9: 51 - 100% Implemented | I9: Automated | J9: Monitored & Reviewed | K9: =IF(W9="NANANANA",S9,IF(AND(OR(G9="Formally Documented",G9="Informally Documented"),H9="Not Implemented"),0.5*AVERAGE(S9:V9),AVERAGE(S9:V9))) -> 3 | L9: =IF(AND(D9="K",K9=1),'Maturity Rating'!$E$8,IF(K9="NA",K9,IF(D9="K",K9*'Maturity Rating'!$E$7,K9))) -> 3 | M9: =IF(X9="NANA",K9,AVERAGE(L9:L10)) -> 3 | N9: =IF(M9="NA",M9,(MIN(5,M9/3*5))) -> 5 | O9: =IF(N9="NA",N9,VLOOKUP(Q9,'Maturity Rating'!G4:H8,2,FALSE)) -> Adaptive | Q9: =IF(N9="NA",N9,ROUNDDOWN(N9,0)) -> 5 | S9: =VLOOKUP(G9,'Maturity Rating'!A$2:B$5,2,FALSE) -> 3 | T9: =VLOOKUP(H9,'Maturity Rating'!A$8:B$11,2,FALSE) -> 3 | U9: =VLOOKUP(I9,'Maturity Rating'!A$14:B$17,2,FALSE) -> 3 | V9: =VLOOKUP(J9,'Maturity Rating'!A$20:B$23,2,FALSE) -> 3 | W9: =CONCATENATE(S9,T9,U9,V9) -> 3333 | X9: =CONCATENATE(L9,L10) -> 33
A10: 4.7 | E10: The incident response team is able to decide the nature of the incident (specifically cyber security incident) | F10: Preventive | G10: Formally Documented | H10: 51 - 100% Implemented | I10: Automated | J10: Monitored & Reviewed | K10: =IF(W10="NANANANA",S10,IF(AND(OR(G10="Formally Documented",G10="Informally Documented"),H10="Not Implemented"),0.5*AVERAGE(S10:V10),AVERAGE(S10:V10))) -> 3 | L10: =IF(AND(D10="K",K10=1),'Maturity Rating'!$E$8,IF(K10="NA",K10,IF(D10="K",K10*'Maturity Rating'!$E$7,K10))) -> 3 | S10: =VLOOKUP(G10,'Maturity Rating'!A$2:B$5,2,FALSE) -> 3 | T10: =VLOOKUP(H10,'Maturity Rating'!A$8:B$11,2,FALSE) -> 3 | U10: =VLOOKUP(I10,'Maturity Rating'!A$14:B$17,2,FALSE) -> 3 | V10: =VLOOKUP(J10,'Maturity Rating'!A$20:B$23,2,FALSE) -> 3 | W10: =CONCATENATE(S10,T10,U10,V10) -> 3333
A11: 4.8 | B11: Incident Response and Resolution | C11: There should be effective Incident Response strategy to deal with post incident damage handling which if not discovered or detected by the organisation in the first place can lead to serious damage to the organisation. | E11: There is a centralised tool to report all the incidents within the organization | F11: Detective | G11: Not Documented | H11: Not Implemented | I11: Not Automated | J11: Not Monitored & Reviewed | K11: =IF(W11="NANANANA",S11,IF(AND(OR(G11="Formally Documented",G11="Informally Documented"),H11="Not Implemented"),0.5*AVERAGE(S11:V11),AVERAGE(S11:V11))) -> 1 | L11: =IF(AND(D11="K",K11=1),'Maturity Rating'!$E$8,IF(K11="NA",K11,IF(D11="K",K11*'Maturity Rating'!$E$7,K11))) -> 1 | M11: =IF(X11="NANANANANANANANANANANA",K11,AVERAGE(L11:L23)) -> 2.615 | N11: =IF(M11="NA",M11,(MIN(5,M11/3*5))) -> 4.3583333 | O11: =IF(N11="NA",N11,VLOOKUP(Q11,'Maturity Rating'!G4:H8,2,FALSE)) -> Repeatable | Q11: =IF(N11="NA",N11,ROUNDDOWN(N11,0)) -> 4 | S11: =VLOOKUP(G11,'Maturity Rating'!A$2:B$5,2,FALSE) -> 1 | T11: =VLOOKUP(H11,'Maturity Rating'!A$8:B$11,2,FALSE) -> 1 | U11: =VLOOKUP(I11,'Maturity Rating'!A$14:B$17,2,FALSE) -> 1 | V11: =VLOOKUP(J11,'Maturity Rating'!A$20:B$23,2,FALSE) -> 1 | W11: =CONCATENATE(S11,T11,U11,V11) -> 1111 | X11: =CONCATENATE(L11,L12,L13,L14,L15,L16,L17,L18,L19,L20,L21,L22,L23) -> 132.4NA3NANA3.633.630.82.75
A12: 4.9 | E12: Employees are made aware about the mediums to report information security and cyber security incidents | F12: Preventive | G12: Formally Documented | H12: 51 - 100% Implemented | I12: Automated | J12: Monitored & Reviewed | K12: =IF(W12="NANANANA",S12,IF(AND(OR(G12="Formally Documented",G12="Informally Documented"),H12="Not Implemented"),0.5*AVERAGE(S12:V12),AVERAGE(S12:V12))) -> 3 | L12: =IF(AND(D12="K",K12=1),'Maturity Rating'!$E$8,IF(K12="NA",K12,IF(D12="K",K12*'Maturity Rating'!$E$7,K12))) -> 3 | S12: =VLOOKUP(G12,'Maturity Rating'!A$2:B$5,2,FALSE) -> 3 | T12: =VLOOKUP(H12,'Maturity Rating'!A$8:B$11,2,FALSE) -> 3 | U12: =VLOOKUP(I12,'Maturity Rating'!A$14:B$17,2,FALSE) -> 3 | V12: =VLOOKUP(J12,'Maturity Rating'!A$20:B$23,2,FALSE) -> 3 | W12: =CONCATENATE(S12,T12,U12,V12) -> 3333
A13: 4. 10 | D13: K | E13: There is a defined escalation matrix shared with all the stakeholders | F13: Preventive | G13: Informally Documented | H13: 0 - 50% Implemented | I13: Partially Automated | J13: Partially Monitored & Reviewed | K13: =IF(W13="NANANANA",S13,IF(AND(OR(G13="Formally Documented",G13="Informally Documented"),H13="Not Implemented"),0.5*AVERAGE(S13:V13),AVERAGE(S13:V13))) -> 2 | L13: =IF(AND(D13="K",K13=1),'Maturity Rating'!$E$8,IF(K13="NA",K13,IF(D13="K",K13*'Maturity Rating'!$E$7,K13))) -> 2.4 | S13: =VLOOKUP(G13,'Maturity Rating'!A$2:B$5,2,FALSE) -> 2 | T13: =VLOOKUP(H13,'Maturity Rating'!A$8:B$11,2,FALSE) -> 2 | U13: =VLOOKUP(I13,'Maturity Rating'!A$14:B$17,2,FALSE) -> 2 | V13: =VLOOKUP(J13,'Maturity Rating'!A$20:B$23,2,FALSE) -> 2 | W13: =CONCATENATE(S13,T13,U13,V13) -> 2222
A14: 4.11 | D14: K | E14: There is an incident classification matrix depicting the classification of cyber incidents | F14: Preventive | G14: Not Applicable | H14: Not Applicable | I14: Not Applicable | J14: Not Applicable | K14: =IF(W14="NANANANA",S14,IF(AND(OR(G14="Formally Documented",G14="Informally Documented"),H14="Not Implemented"),0.5*AVERAGE(S14:V14),AVERAGE(S14:V14))) -> NA | L14: =IF(AND(D14="K",K14=1),'Maturity Rating'!$E$8,IF(K14="NA",K14,IF(D14="K",K14*'Maturity Rating'!$E$7,K14))) -> NA | S14: =VLOOKUP(G14,'Maturity Rating'!A$2:B$5,2,FALSE) -> NA | T14: =VLOOKUP(H14,'Maturity Rating'!A$8:B$11,2,FALSE) -> NA | U14: =VLOOKUP(I14,'Maturity Rating'!A$14:B$17,2,FALSE) -> NA | V14: =VLOOKUP(J14,'Maturity Rating'!A$20:B$23,2,FALSE) -> NA | W14: =CONCATENATE(S14,T14,U14,V14) -> NANANANA
A15: 4.12 | E15: The person raising the incident is informed of the progress of his/ her reported incident | F15: Preventive | G15: Formally Documented | H15: 51 - 100% Implemented | I15: Automated | J15: Monitored & Reviewed | K15: =IF(W15="NANANANA",S15,IF(AND(OR(G15="Formally Documented",G15="Informally Documented"),H15="Not Implemented"),0.5*AVERAGE(S15:V15),AVERAGE(S15:V15))) -> 3 | L15: =IF(AND(D15="K",K15=1),'Maturity Rating'!$E$8,IF(K15="NA",K15,IF(D15="K",K15*'Maturity Rating'!$E$7,K15))) -> 3 | S15: =VLOOKUP(G15,'Maturity Rating'!A$2:B$5,2,FALSE) -> 3 | T15: =VLOOKUP(H15,'Maturity Rating'!A$8:B$11,2,FALSE) -> 3 | U15: =VLOOKUP(I15,'Maturity Rating'!A$14:B$17,2,FALSE) -> 3 | V15: =VLOOKUP(J15,'Maturity Rating'!A$20:B$23,2,FALSE) -> 3 | W15: =CONCATENATE(S15,T15,U15,V15) -> 3333
A16: 4.13 | D16: K | E16: Incidents are categorized consistent with response plans and are classified based on the impact of the incident | F16: Detective | G16: Not Applicable | H16: Not Applicable | I16: Not Applicable | J16: Not Applicable | K16: =IF(W16="NANANANA",S16,IF(AND(OR(G16="Formally Documented",G16="Informally Documented"),H16="Not Implemented"),0.5*AVERAGE(S16:V16),AVERAGE(S16:V16))) -> NA | L16: =IF(AND(D16="K",K16=1),'Maturity Rating'!$E$8,IF(K16="NA",K16,IF(D16="K",K16*'Maturity Rating'!$E$7,K16))) -> NA | S16: =VLOOKUP(G16,'Maturity Rating'!A$2:B$5,2,FALSE) -> NA | T16: =VLOOKUP(H16,'Maturity Rating'!A$8:B$11,2,FALSE) -> NA | U16: =VLOOKUP(I16,'Maturity Rating'!A$14:B$17,2,FALSE) -> NA | V16: =VLOOKUP(J16,'Maturity Rating'!A$20:B$23,2,FALSE) -> NA | W16: =CONCATENATE(S16,T16,U16,V16) -> NANANANA
A17: 4.14 | E17: The evidences related to the incident are collected, retained and presented to the relevant stakeholders if/ when required | F17: Detective | G17: Not Applicable | H17: Not Applicable | I17: Not Applicable | J17: Not Applicable | K17: =IF(W17="NANANANA",S17,IF(AND(OR(G17="Formally Documented",G17="Informally Documented"),H17="Not Implemented"),0.5*AVERAGE(S17:V17),AVERAGE(S17:V17))) -> NA | L17: =IF(AND(D17="K",K17=1),'Maturity Rating'!$E$8,IF(K17="NA",K17,IF(D17="K",K17*'Maturity Rating'!$E$7,K17))) -> NA | S17: =VLOOKUP(G17,'Maturity Rating'!A$2:B$5,2,FALSE) -> NA | T17: =VLOOKUP(H17,'Maturity Rating'!A$8:B$11,2,FALSE) -> NA | U17: =VLOOKUP(I17,'Maturity Rating'!A$14:B$17,2,FALSE) -> NA | V17: =VLOOKUP(J17,'Maturity Rating'!A$20:B$23,2,FALSE) -> NA | W17: =CONCATENATE(S17,T17,U17,V17) -> NANANANA
A18: 4.15 | D18: K | E18: Incidents are resolved within the defined TAT | F18: Corrective | G18: Formally Documented | H18: 51 - 100% Implemented | I18: Automated | J18: Monitored & Reviewed | K18: =IF(W18="NANANANA",S18,IF(AND(OR(G18="Formally Documented",G18="Informally Documented"),H18="Not Implemented"),0.5*AVERAGE(S18:V18),AVERAGE(S18:V18))) -> 3 | L18: =IF(AND(D18="K",K18=1),'Maturity Rating'!$E$8,IF(K18="NA",K18,IF(D18="K",K18*'Maturity Rating'!$E$7,K18))) -> 3.6 | S18: =VLOOKUP(G18,'Maturity Rating'!A$2:B$5,2,FALSE) -> 3 | T18: =VLOOKUP(H18,'Maturity Rating'!A$8:B$11,2,FALSE) -> 3 | U18: =VLOOKUP(I18,'Maturity Rating'!A$14:B$17,2,FALSE) -> 3 | V18: =VLOOKUP(J18,'Maturity Rating'!A$20:B$23,2,FALSE) -> 3 | W18: =CONCATENATE(S18,T18,U18,V18) -> 3333
A19: 4.16 | E19: An information security incident and response register has been established and maintained. All incidents have been recorded within this register | F19: Preventive | G19: Formally Documented | H19: 51 - 100% Implemented | I19: Automated | J19: Monitored & Reviewed | K19: =IF(W19="NANANANA",S19,IF(AND(OR(G19="Formally Documented",G19="Informally Documented"),H19="Not Implemented"),0.5*AVERAGE(S19:V19),AVERAGE(S19:V19))) -> 3 | L19: =IF(AND(D19="K",K19=1),'Maturity Rating'!$E$8,IF(K19="NA",K19,IF(D19="K",K19*'Maturity Rating'!$E$7,K19))) -> 3 | S19: =VLOOKUP(G19,'Maturity Rating'!A$2:B$5,2,FALSE) -> 3 | T19: =VLOOKUP(H19,'Maturity Rating'!A$8:B$11,2,FALSE) -> 3 | U19: =VLOOKUP(I19,'Maturity Rating'!A$14:B$17,2,FALSE) -> 3 | V19: =VLOOKUP(J19,'Maturity Rating'!A$20:B$23,2,FALSE) -> 3 | W19: =CONCATENATE(S19,T19,U19,V19) -> 3333
A20: 4.17 | D20: K | E20: The root cause analysis is done by the incident response team when an incident is reported. | F20: Detective | G20: Formally Documented | H20: 51 - 100% Implemented | I20: Automated | J20: Monitored & Reviewed | K20: =IF(W20="NANANANA",S20,IF(AND(OR(G20="Formally Documented",G20="Informally Documented"),H20="Not Implemented"),0.5*AVERAGE(S20:V20),AVERAGE(S20:V20))) -> 3 | L20: =IF(AND(D20="K",K20=1),'Maturity Rating'!$E$8,IF(K20="NA",K20,IF(D20="K",K20*'Maturity Rating'!$E$7,K20))) -> 3.6 | S20: =VLOOKUP(G20,'Maturity Rating'!A$2:B$5,2,FALSE) -> 3 | T20: =VLOOKUP(H20,'Maturity Rating'!A$8:B$11,2,FALSE) -> 3 | U20: =VLOOKUP(I20,'Maturity Rating'!A$14:B$17,2,FALSE) -> 3 | V20: =VLOOKUP(J20,'Maturity Rating'!A$20:B$23,2,FALSE) -> 3 | W20: =CONCATENATE(S20,T20,U20,V20) -> 3333
A21: 4.18 | E21: Incidents are contained and mitigated in the organization | F21: Detective | G21: Formally Documented | H21: 51 - 100% Implemented | I21: Automated | J21: Monitored & Reviewed | K21: =IF(W21="NANANANA",S21,IF(AND(OR(G21="Formally Documented",G21="Informally Documented"),H21="Not Implemented"),0.5*AVERAGE(S21:V21),AVERAGE(S21:V21))) -> 3 | L21: =IF(AND(D21="K",K21=1),'Maturity Rating'!$E$8,IF(K21="NA",K21,IF(D21="K",K21*'Maturity Rating'!$E$7,K21))) -> 3 | S21: =VLOOKUP(G21,'Maturity Rating'!A$2:B$5,2,FALSE) -> 3 | T21: =VLOOKUP(H21,'Maturity Rating'!A$8:B$11,2,FALSE) -> 3 | U21: =VLOOKUP(I21,'Maturity Rating'!A$14:B$17,2,FALSE) -> 3 | V21: =VLOOKUP(J21,'Maturity Rating'!A$20:B$23,2,FALSE) -> 3 | W21: =CONCATENATE(S21,T21,U21,V21) -> 3333
A22: 4.19 | D22: K | E22: Cyber Incident Response Team (CIRT) should be formed. The CIRT is composed of various members from System, Database, Application, SOC, Network team business owner, HR, legal, Corp comm, etc. as part of CIRT. | F22: Preventive | G22: Not Documented | H22: Not Implemented | I22: Not Applicable | J22: Not Monitored & Reviewed | K22: =IF(W22="NANANANA",S22,IF(AND(OR(G22="Formally Documented",G22="Informally Documented"),H22="Not Implemented"),0.5*AVERAGE(S22:V22),AVERAGE(S22:V22))) -> 1 | L22: =IF(AND(D22="K",K22=1),'Maturity Rating'!$E$8,IF(K22="NA",K22,IF(D22="K",K22*'Maturity Rating'!$E$7,K22))) -> 0.8 | S22: =VLOOKUP(G22,'Maturity Rating'!A$2:B$5,2,FALSE) -> 1 | T22: =VLOOKUP(H22,'Maturity Rating'!A$8:B$11,2,FALSE) -> 1 | U22: =VLOOKUP(I22,'Maturity Rating'!A$14:B$17,2,FALSE) -> NA | V22: =VLOOKUP(J22,'Maturity Rating'!A$20:B$23,2,FALSE) -> 1 | W22: =CONCATENATE(S22,T22,U22,V22) -> 11NA1
A23: 4. 20 | E23: There is an incident trend analysis carried out within the organization | F23: Preventive | G23: Formally Documented | H23: 51 - 100% Implemented | I23: Automated | J23: Partially Monitored & Reviewed | K23: =IF(W23="NANANANA",S23,IF(AND(OR(G23="Formally Documented",G23="Informally Documented"),H23="Not Implemented"),0.5*AVERAGE(S23:V23),AVERAGE(S23:V23))) -> 2.75 | L23: =IF(AND(D23="K",K23=1),'Maturity Rating'!$E$8,IF(K23="NA",K23,IF(D23="K",K23*'Maturity Rating'!$E$7,K23))) -> 2.75 | S23: =VLOOKUP(G23,'Maturity Rating'!A$2:B$5,2,FALSE) -> 3 | T23: =VLOOKUP(H23,'Maturity Rating'!A$8:B$11,2,FALSE) -> 3 | U23: =VLOOKUP(I23,'Maturity Rating'!A$14:B$17,2,FALSE) -> 3 | V23: =VLOOKUP(J23,'Maturity Rating'!A$20:B$23,2,FALSE) -> 2 | W23: =CONCATENATE(S23,T23,U23,V23) -> 3332

Sheet Infra and Operations Sec
C1: Average Domain Rating | E1: =IF(F1="NA","Not Applicable",VLOOKUP(T1,'Maturity Rating'!G4:H8,2,FALSE)) -> Partial | F1: =IF(U1="NANANANANANANANANANA","NA",AVERAGE(N4:N95)) -> 2.5062484 | T1: =ROUNDDOWN(F1,0) -> 2 | U1: =CONCATENATE(N4,N10,N16,N26,N36,N45,N53,N58,N70,N77,N90) -> 2.333333333333333.777777777777784.22.31.9629629629629612.416666666666671.8611111111111121.89743589743593.81944444444444
A3: S. No. | B3: High Level Description | C3: Control Description | D3: Identified Key Controls (K) | E3: Control | F3: Preventive/ Detective/Corrective | G3: Documentation | H3: Implementation | I3: Automation | J3: Monitor & Review | K3: Control Rating | L3: Rating with Key controls weightage | M3: Average Rating | N3: Maturity Rating (1 - 5) | O3: Category | S3: Doc | T3: Impl | U3: Auto | V3: Review
A4: 5.1 | B4: Patch Management | C4: To ensure critical updates installed (OS, middleware, DB, web-layer, virtualization layer, Network and security devices) in timely manner to patch the critical vulnerabilities | D4: K | E4: Organization should have a patch management policy/ procedure defined and approved by the management | F4: Preventive | G4: Formally Documented | H4: 51 - 100% Implemented | I4: Automated | J4: Monitored & Reviewed | K4: =IF(W4="NANANANA",S4,IF(AND(OR(G4="Formally Documented",G4="Informally Documented"),H4="Not Implemented"),0.5*AVERAGE(S4:V4),AVERAGE(S4:V4))) -> 3 | L4: =IF(AND(D4="K",K4=1),'Maturity Rating'!$E$8,IF(K4="NA",K4,IF(D4="K",K4*'Maturity Rating'!$E$7,K4))) -> 3.6 | M4: =IF(X4="NANANANANANA",K4,AVERAGE(L4:L9)) -> 1.4 | N4: =IF(M4<1.1,1,IF(M4="NA",M4,(MIN(5,M4/3*5)))) -> 2.3333333 | O4: =IF(N4="NA",N4,VLOOKUP(Q4,'Maturity Rating'!G4:H8,2,FALSE)) -> Partial | Q4: =IF(N4="NA",N4,ROUNDDOWN(N4,0)) -> 2 | S4: =VLOOKUP(G4,'Maturity Rating'!A$2:B$5,2,FALSE) -> 3 | T4: =VLOOKUP(H4,'Maturity Rating'!A$8:B$11,2,FALSE) -> 3 | U4: =VLOOKUP(I4,'Maturity Rating'!A$14:B$17,2,FALSE) -> 3 | V4: =VLOOKUP(J4,'Maturity Rating'!A$20:B$23,2,FALSE) -> 3 | W4: =CONCATENATE(S4,T4,U4,V4) -> 3333 | X4: =CONCATENATE(L4,L5,L6,L7,L8,L9) -> 3.610.8111
A5: 5.2 | E5: The documents are reviewed, updated and approved as per the defined frequency in the policy/ procedure. | F5: Preventive | G5: Not Documented | H5: Not Implemented | I5: Not Applicable | J5: Not Applicable | K5: =IF(W5="NANANANA",S5,IF(AND(OR(G5="Formally Documented",G5="Informally Documented"),H5="Not Implemented"),0.5*AVERAGE(S5:V5),AVERAGE(S5:V5))) -> 1 | L5: =IF(AND(D5="K",K5=1),'Maturity Rating'!$E$8,IF(K5="NA",K5,IF(D5="K",K5*'Maturity Rating'!$E$7,K5))) -> 1 | S5: =VLOOKUP(G5,'Maturity Rating'!A$2:B$5,2,FALSE) -> 1 | T5: =VLOOKUP(H5,'Maturity Rating'!A$8:B$11,2,FALSE) -> 1 | U5: =VLOOKUP(I5,'Maturity Rating'!A$14:B$17,2,FALSE) -> NA | V5: =VLOOKUP(J5,'Maturity Rating'!A$20:B$23,2,FALSE) -> NA | W5: =CONCATENATE(S5,T5,U5,V5) -> 11NANA
A6: 5.3 | D6: K | E6: Patches are identified for deployment based on their criticality and priority | F6: Preventive | G6: Not Documented | H6: Not Implemented | I6: Not Applicable | J6: Not Applicable | K6: =IF(W6="NANANANA",S6,IF(AND(OR(G6="Formally Documented",G6="Informally Documented"),H6="Not Implemented"),0.5*AVERAGE(S6:V6),AVERAGE(S6:V6))) -> 1 | L6: =IF(AND(D6="K",K6=1),'Maturity Rating'!$E$8,IF(K6="NA",K6,IF(D6="K",K6*'Maturity Rating'!$E$7,K6))) -> 0.8 | S6: =VLOOKUP(G6,'Maturity Rating'!A$2:B$5,2,FALSE) -> 1 | T6: =VLOOKUP(H6,'Maturity Rating'!A$8:B$11,2,FALSE) -> 1 | U6: =VLOOKUP(I6,'Maturity Rating'!A$14:B$17,2,FALSE) -> NA | V6: =VLOOKUP(J6,'Maturity Rating'!A$20:B$23,2,FALSE) -> NA | W6: =CONCATENATE(S6,T6,U6,V6) -> 11NANA
A7: 5.4 | E7: Patches are tested before deployment wherever feasible | F7: Preventive | G7: Not Documented | H7: Not Applicable | I7: Not Automated | J7: Not Monitored & Reviewed | K7: =IF(W7="NANANANA",S7,IF(AND(OR(G7="Formally Documented",G7="Informally Documented"),H7="Not Implemented"),0.5*AVERAGE(S7:V7),AVERAGE(S7:V7))) -> 1 | L7: =IF(AND(D7="K",K7=1),'Maturity Rating'!$E$8,IF(K7="NA",K7,IF(D7="K",K7*'Maturity Rating'!$E$7,K7))) -> 1 | S7: =VLOOKUP(G7,'Maturity Rating'!A$2:B$5,2,FALSE) -> 1 | T7: =VLOOKUP(H7,'Maturity Rating'!A$8:B$11,2,FALSE) -> NA | U7: =VLOOKUP(I7,'Maturity Rating'!A$14:B$17,2,FALSE) -> 1 | V7: =VLOOKUP(J7,'Maturity Rating'!A$20:B$23,2,FALSE) -> 1 | W7: =CONCATENATE(S7,T7,U7,V7) -> 1NA11
A8: 5.5 | E8: There is a process defined to push the failed patches on the systems and to track the ageing of failed patches. | F8: Preventive | G8: Not Documented | H8: Not Implemented | I8: Not Automated | J8: Not Monitored & Reviewed | K8: =IF(W8="NANANANA",S8,IF(AND(OR(G8="Formally Documented",G8="Informally Documented"),H8="Not Implemented"),0.5*AVERAGE(S8:V8),AVERAGE(S8:V8))) -> 1 | L8: =IF(AND(D8="K",K8=1),'Maturity Rating'!$E$8,IF(K8="NA",K8,IF(D8="K",K8*'Maturity Rating'!$E$7,K8))) -> 1 | S8: =VLOOKUP(G8,'Maturity Rating'!A$2:B$5,2,FALSE) -> 1 | T8: =VLOOKUP(H8,'Maturity Rating'!A$8:B$11,2,FALSE) -> 1 | U8: =VLOOKUP(I8,'Maturity Rating'!A$14:B$17,2,FALSE) -> 1 | V8: =VLOOKUP(J8,'Maturity Rating'!A$20:B$23,2,FALSE) -> 1 | W8: =CONCATENATE(S8,T8,U8,V8) -> 1111
A9: 5.6 | E9: Only softwares supported by the vendors for security patches are implemented in the organization | F9: Preventive | G9: Not Documented | H9: Not Implemented | I9: Not Applicable | J9: Not Applicable | K9: =IF(W9="NANANANA",S9,IF(AND(OR(G9="Formally Documented",G9="Informally Documented"),H9="Not Implemented"),0.5*AVERAGE(S9:V9),AVERAGE(S9:V9))) -> 1 | L9: =IF(AND(D9="K",K9=1),'Maturity Rating'!$E$8,IF(K9="NA",K9,IF(D9="K",K9*'Maturity Rating'!$E$7,K9))) -> 1 | S9: =VLOOKUP(G9,'Maturity Rating'!A$2:B$5,2,FALSE) -> 1 | T9: =VLOOKUP(H9,'Maturity Rating'!A$8:B$11,2,FALSE) -> 1 | U9: =VLOOKUP(I9,'Maturity Rating'!A$14:B$17,2,FALSE) -> NA | V9: =VLOOKUP(J9,'Maturity Rating'!A$20:B$23,2,FALSE) -> NA | W9: =CONCATENATE(S9,T9,U9,V9) -> 11NANA
A10: 5.7 | B10: Antivirus & Malware Management | C10: To ensure that information and information processing facilities are protected against malware | E10: There is a defined & documented process for Antivirus management | F10: Preventive | G10: Formally Documented | H10: 51 - 100% Implemented | I10: Automated | J10: Monitored & Reviewed | K10: =IF(W10="NANANANA",S10,IF(AND(OR(G10="Formally Documented",G10="Informally Documented"),H10="Not Implemented"),0.5*AVERAGE(S10:V10),AVERAGE(S10:V10))) -> 3 | L10: =IF(AND(D10="K",K10=1),'Maturity Rating'!$E$8,IF(K10="NA",K10,IF(D10="K",K10*'Maturity Rating'!$E$7,K10))) -> 3 | M10: =IF(X10="NANANANANANANANA",K10,AVERAGE(L10:L15)) -> 2.2666667 | N10: =IF(M10<1.1,1,IF(M10="NA",M10,(MIN(5,M10/3*5)))) -> 3.7777778 | O10: =IF(N10="NA",N10,VLOOKUP(Q10,'Maturity Rating'!G4:H8,2,FALSE)) -> Defined | Q10: =IF(N10="NA",N10,ROUNDDOWN(N10,0)) -> 3 | S10: =VLOOKUP(G10,'Maturity Rating'!A$2:B$5,2,FALSE) -> 3 | T10: =VLOOKUP(H10,'Maturity Rating'!A$8:B$11,2,FALSE) -> 3 | U10: =VLOOKUP(I10,'Maturity Rating'!A$14:B$17,2,FALSE) -> 3 | V10: =VLOOKUP(J10,'Maturity Rating'!A$20:B$23,2,FALSE) -> 3 | W10: =CONCATENATE(S10,T10,U10,V10) -> 3333 | X10: =CONCATENATE(L10,L11,L12,L13,L14,L15) -> 323.6311
A11: 5.8 | E11: The documents are reviewed, updated and approved as per the defined frequency in the policy/ procedure. | F11: Preventive | G11: Informally Documented | H11: 0 - 50% Implemented | I11: Partially Automated | J11: Partially Monitored & Reviewed | K11: =IF(W11="NANANANA",S11,IF(AND(OR(G11="Formally Documented",G11="Informally Documented"),H11="Not Implemented"),0.5*AVERAGE(S11:V11),AVERAGE(S11:V11))) -> 2 | L11: =IF(AND(D11="K",K11=1),'Maturity Rating'!$E$8,IF(K11="NA",K11,IF(D11="K",K11*'Maturity Rating'!$E$7,K11))) -> 2 | S11: =VLOOKUP(G11,'Maturity Rating'!A$2:B$5,2,FALSE) -> 2 | T11: =VLOOKUP(H11,'Maturity Rating'!A$8:B$11,2,FALSE) -> 2 | U11: =VLOOKUP(I11,'Maturity Rating'!A$14:B$17,2,FALSE) -> 2 | V11: =VLOOKUP(J11,'Maturity Rating'!A$20:B$23,2,FALSE) -> 2 | W11: =CONCATENATE(S11,T11,U11,V11) -> 2222
A12: 5.9 | D12: K | E12: Endpoint systems are scanned at defined frequency for malicious files - (full scan, custom scan) | F12: Preventive | G12: Formally Documented | H12: 51 - 100% Implemented | I12: Automated | J12: Monitored & Reviewed | K12: =IF(W12="NANANANA",S12,IF(AND(OR(G12="Formally Documented",G12="Informally Documented"),H12="Not Implemented"),0.5*AVERAGE(S12:V12),AVERAGE(S12:V12))) -> 3 | L12: =IF(AND(D12="K",K12=1),'Maturity Rating'!$E$8,IF(K12="NA",K12,IF(D12="K",K12*'Maturity Rating'!$E$7,K12))) -> 3.6 | S12: =VLOOKUP(G12,'Maturity Rating'!A$2:B$5,2,FALSE) -> 3 | T12: =VLOOKUP(H12,'Maturity Rating'!A$8:B$11,2,FALSE) -> 3 | U12: =VLOOKUP(I12,'Maturity Rating'!A$14:B$17,2,FALSE) -> 3 | V12: =VLOOKUP(J12,'Maturity Rating'!A$20:B$23,2,FALSE) -> 3 | W12: =CONCATENATE(S12,T12,U12,V12) -> 3333
A13: 5. 10 | E13: Antivirus signature definition updation on endpoints and servers are reviewed periodically. | F13: Preventive | G13: Formally Documented | H13: 51 - 100% Implemented | I13: Automated | J13: Monitored & Reviewed | K13: =IF(W13="NANANANA",S13,IF(AND(OR(G13="Formally Documented",G13="Informally Documented"),H13="Not Implemented"),0.5*AVERAGE(S13:V13),AVERAGE(S13:V13))) -> 3 | L13: =IF(AND(D13="K",K13=1),'Maturity Rating'!$E$8,IF(K13="NA",K13,IF(D13="K",K13*'Maturity Rating'!$E$7,K13))) -> 3 | S13: =VLOOKUP(G13,'Maturity Rating'!A$2:B$5,2,FALSE) -> 3 | T13: =VLOOKUP(H13,'Maturity Rating'!A$8:B$11,2,FALSE) -> 3 | U13: =VLOOKUP(I13,'Maturity Rating'!A$14:B$17,2,FALSE) -> 3 | V13: =VLOOKUP(J13,'Maturity Rating'!A$20:B$23,2,FALSE) -> 3 | W13: =CONCATENATE(S13,T13,U13,V13) -> 3333
A14: 5.11 | E14: MIS reports for compliance of all IT systems are regularly shared with the business team | F14: Detective | G14: Not Documented | H14: Not Implemented | I14: Not Automated | J14: Not Monitored & Reviewed | K14: =IF(W14="NANANANA",S14,IF(AND(OR(G14="Formally Documented",G14="Informally Documented"),H14="Not Implemented"),0.5*AVERAGE(S14:V14),AVERAGE(S14:V14))) -> 1 | L14: =IF(AND(D14="K",K14=1),'Maturity Rating'!$E$8,IF(K14="NA",K14,IF(D14="K",K14*'Maturity Rating'!$E$7,K14))) -> 1 | S14: =VLOOKUP(G14,'Maturity Rating'!A$2:B$5,2,FALSE) -> 1 | T14: =VLOOKUP(H14,'Maturity Rating'!A$8:B$11,2,FALSE) -> 1 | U14: =VLOOKUP(I14,'Maturity Rating'!A$14:B$17,2,FALSE) -> 1 | V14: =VLOOKUP(J14,'Maturity Rating'!A$20:B$23,2,FALSE) -> 1 | W14: =CONCATENATE(S14,T14,U14,V14) -> 1111
A15: 5.12 | E15: Organizations has controls in place to prevent malware propagation via the email and web services | F15: Detective | G15: Not Documented | H15: Not Applicable | I15: Not Applicable | J15: Not Applicable | K15: =IF(W15="NANANANA",S15,IF(AND(OR(G15="Formally Documented",G15="Informally Documented"),H15="Not Implemented"),0.5*AVERAGE(S15:V15),AVERAGE(S15:V15))) -> 1 | L15: =IF(AND(D15="K",K15=1),'Maturity Rating'!$E$8,IF(K15="NA",K15,IF(D15="K",K15*'Maturity Rating'!$E$7,K15))) -> 1 | S15: =VLOOKUP(G15,'Maturity Rating'!A$2:B$5,2,FALSE) -> 1 | T15: =VLOOKUP(H15,'Maturity Rating'!A$8:B$11,2,FALSE) -> NA | U15: =VLOOKUP(I15,'Maturity Rating'!A$14:B$17,2,FALSE) -> NA | V15: =VLOOKUP(J15,'Maturity Rating'!A$20:B$23,2,FALSE) -> NA | W15: =CONCATENATE(S15,T15,U15,V15) -> 1NANANA
A16: 5.14 | B16: Backup Management | C16: To ensure data loss should be prevented | E16: There is a defined & documented process for Backup management | F16: Preventive | G16: Not Documented | H16: Not Applicable | I16: Not Applicable | J16: Not Applicable | K16: =IF(W16="NANANANA",S16,IF(AND(OR(G16="Formally Documented",G16="Informally Documented"),H16="Not Implemented"),0.5*AVERAGE(S16:V16),AVERAGE(S16:V16))) -> 1 | L16: =IF(AND(D16="K",K16=1),'Maturity Rating'!$E$8,IF(K16="NA",K16,IF(D16="K",K16*'Maturity Rating'!$E$7,K16))) -> 1 | M16: =IF(X16="NANANANANANANANANA",K16,AVERAGE(L16:L25)) -> 2.52 | N16: =IF(M16<1.1,1,IF(M16="NA",M16,(MIN(5,M16/3*5)))) -> 4.2 | O16: =IF(N16="NA",N16,VLOOKUP(Q16,'Maturity Rating'!G4:H8,2,FALSE)) -> Repeatable | Q16: =IF(N16="NA",N16,ROUNDDOWN(N16,0)) -> 4 | S16: =VLOOKUP(G16,'Maturity Rating'!A$2:B$5,2,FALSE) -> 1 | T16: =VLOOKUP(H16,'Maturity Rating'!A$8:B$11,2,FALSE) -> NA | U16: =VLOOKUP(I16,'Maturity Rating'!A$14:B$17,2,FALSE) -> NA | V16: =VLOOKUP(J16,'Maturity Rating'!A$20:B$23,2,FALSE) -> NA | W16: =CONCATENATE(S16,T16,U16,V16) -> 1NANANA | X16: =CONCATENATE(L16,L17,L18,L19,L20,L21,L22,L23,L24,L25) -> 113.6133.63333
A17: 5.15 | E17: The documents are reviewed, updated and approved as per the defined frequency in the policy/ procedure. | F17: Preventive | G17: Not Documented | H17: Not Applicable | I17: Not Applicable | J17: Not Applicable | K17: =IF(W17="NANANANA",S17,IF(AND(OR(G17="Formally Documented",G17="Informally Documented"),H17="Not Implemented"),0.5*AVERAGE(S17:V17),AVERAGE(S17:V17))) -> 1 | L17: =IF(AND(D17="K",K17=1),'Maturity Rating'!$E$8,IF(K17="NA",K17,IF(D17="K",K17*'Maturity Rating'!$E$7,K17))) -> 1 | S17: =VLOOKUP(G17,'Maturity Rating'!A$2:B$5,2,FALSE) -> 1 | T17: =VLOOKUP(H17,'Maturity Rating'!A$8:B$11,2,FALSE) -> NA | U17: =VLOOKUP(I17,'Maturity Rating'!A$14:B$17,2,FALSE) -> NA | V17: =VLOOKUP(J17,'Maturity Rating'!A$20:B$23,2,FALSE) -> NA | W17: =CONCATENATE(S17,T17,U17,V17) -> 1NANANA
A18: 5.16 | D18: K | E18: Data backups are performed for critical systems as per predefined schedules. | F18: Preventive | G18: Formally Documented | H18: 51 - 100% Implemented | I18: Automated | J18: Monitored & Reviewed | K18: =IF(W18="NANANANA",S18,IF(AND(OR(G18="Formally Documented",G18="Informally Documented"),H18="Not Implemented"),0.5*AVERAGE(S18:V18),AVERAGE(S18:V18))) -> 3 | L18: =IF(AND(D18="K",K18=1),'Maturity Rating'!$E$8,IF(K18="NA",K18,IF(D18="K",K18*'Maturity Rating'!$E$7,K18))) -> 3.6 | S18: =VLOOKUP(G18,'Maturity Rating'!A$2:B$5,2,FALSE) -> 3 | T18: =VLOOKUP(H18,'Maturity Rating'!A$8:B$11,2,FALSE) -> 3 | U18: =VLOOKUP(I18,'Maturity Rating'!A$14:B$17,2,FALSE) -> 3 | V18: =VLOOKUP(J18,'Maturity Rating'!A$20:B$23,2,FALSE) -> 3 | W18: =CONCATENATE(S18,T18,U18,V18) -> 3333
A19: 5.17 | E19: Access to backup data is limited to authorized individuals wherever applicable | F19: Preventive | G19: Not Documented | H19: Not Applicable | I19: Not Applicable | J19: Not Applicable | K19: =IF(W19="NANANANA",S19,IF(AND(OR(G19="Formally Documented",G19="Informally Documented"),H19="Not Implemented"),0.5*AVERAGE(S19:V19),AVERAGE(S19:V19))) -> 1 | L19: =IF(AND(D19="K",K19=1),'Maturity Rating'!$E$8,IF(K19="NA",K19,IF(D19="K",K19*'Maturity Rating'!$E$7,K19))) -> 1 | S19: =VLOOKUP(G19,'Maturity Rating'!A$2:B$5,2,FALSE) -> 1 | T19: =VLOOKUP(H19,'Maturity Rating'!A$8:B$11,2,FALSE) -> NA | U19: =VLOOKUP(I19,'Maturity Rating'!A$14:B$17,2,FALSE) -> NA | V19: =VLOOKUP(J19,'Maturity Rating'!A$20:B$23,2,FALSE) -> NA | W19: =CONCATENATE(S19,T19,U19,V19) -> 1NANANA
A20: 5.18 | E20: Backup data is encrypted | F20: Preventive | G20: Formally Documented | H20: 51 - 100% Implemented | I20: Automated | J20: Monitored & Reviewed | K20: =IF(W20="NANANANA",S20,IF(AND(OR(G20="Formally Documented",G20="Informally Documented"),H20="Not Implemented"),0.5*AVERAGE(S20:V20),AVERAGE(S20:V20))) -> 3 | L20: =IF(AND(D20="K",K20=1),'Maturity Rating'!$E$8,IF(K20="NA",K20,IF(D20="K",K20*'Maturity Rating'!$E$7,K20))) -> 3 | S20: =VLOOKUP(G20,'Maturity Rating'!A$2:B$5,2,FALSE) -> 3 | T20: =VLOOKUP(H20,'Maturity Rating'!A$8:B$11,2,FALSE) -> 3 | U20: =VLOOKUP(I20,'Maturity Rating'!A$14:B$17,2,FALSE) -> 3 | V20: =VLOOKUP(J20,'Maturity Rating'!A$20:B$23,2,FALSE) -> 3 | W20: =CONCATENATE(S20,T20,U20,V20) -> 3333
A21: 5.19 | D21: K | E21: Backup schedules are monitored for failure and the logs are stored centrally | F21: Detective | G21: Formally Documented | H21: 51 - 100% Implemented | I21: Automated | J21: Monitored & Reviewed | K21: =IF(W21="NANANANA",S21,IF(AND(OR(G21="Formally Documented",G21="Informally Documented"),H21="Not Implemented"),0.5*AVERAGE(S21:V21),AVERAGE(S21:V21))) -> 3 | L21: =IF(AND(D21="K",K21=1),'Maturity Rating'!$E$8,IF(K21="NA",K21,IF(D21="K",K21*'Maturity Rating'!$E$7,K21))) -> 3.6 | S21: =VLOOKUP(G21,'Maturity Rating'!A$2:B$5,2,FALSE) -> 3 | T21: =VLOOKUP(H21,'Maturity Rating'!A$8:B$11,2,FALSE) -> 3 | U21: =VLOOKUP(I21,'Maturity Rating'!A$14:B$17,2,FALSE) -> 3 | V21: =VLOOKUP(J21,'Maturity Rating'!A$20:B$23,2,FALSE) -> 3 | W21: =CONCATENATE(S21,T21,U21,V21) -> 3333
A22: 5. 20 | E22: Backups are retained as per the defined policy | F22: Preventive | G22: Formally Documented | H22: 51 - 100% Implemented | I22: Automated | J22: Monitored & Reviewed | K22: =IF(W22="NANANANA",S22,IF(AND(OR(G22="Formally Documented",G22="Informally Documented"),H22="Not Implemented"),0.5*AVERAGE(S22:V22),AVERAGE(S22:V22))) -> 3 | L22: =IF(AND(D22="K",K22=1),'Maturity Rating'!$E$8,IF(K22="NA",K22,IF(D22="K",K22*'Maturity Rating'!$E$7,K22))) -> 3 | S22: =VLOOKUP(G22,'Maturity Rating'!A$2:B$5,2,FALSE) -> 3 | T22: =VLOOKUP(H22,'Maturity Rating'!A$8:B$11,2,FALSE) -> 3 | U22: =VLOOKUP(I22,'Maturity Rating'!A$14:B$17,2,FALSE) -> 3 | V22: =VLOOKUP(J22,'Maturity Rating'!A$20:B$23,2,FALSE) -> 3 | W22: =CONCATENATE(S22,T22,U22,V22) -> 3333
A23: 5.21 | E23: Backed up data is restored periodically to test the integrity of the backups | F23: Detective | G23: Formally Documented | H23: 51 - 100% Implemented | I23: Automated | J23: Monitored & Reviewed | K23: =IF(W23="NANANANA",S23,IF(AND(OR(G23="Formally Documented",G23="Informally Documented"),H23="Not Implemented"),0.5*AVERAGE(S23:V23),AVERAGE(S23:V23))) -> 3 | L23: =IF(AND(D23="K",K23=1),'Maturity Rating'!$E$8,IF(K23="NA",K23,IF(D23="K",K23*'Maturity Rating'!$E$7,K23))) -> 3 | S23: =VLOOKUP(G23,'Maturity Rating'!A$2:B$5,2,FALSE) -> 3 | T23: =VLOOKUP(H23,'Maturity Rating'!A$8:B$11,2,FALSE) -> 3 | U23: =VLOOKUP(I23,'Maturity Rating'!A$14:B$17,2,FALSE) -> 3 | V23: =VLOOKUP(J23,'Maturity Rating'!A$20:B$23,2,FALSE) -> 3 | W23: =CONCATENATE(S23,T23,U23,V23) -> 3333
A24: 5.22 | E24: Backup should be performed with respect to the RPO defined | F24: Preventive | G24: Formally Documented | H24: 51 - 100% Implemented | I24: Automated | J24: Monitored & Reviewed | K24: =IF(W24="NANANANA",S24,IF(AND(OR(G24="Formally Documented",G24="Informally Documented"),H24="Not Implemented"),0.5*AVERAGE(S24:V24),AVERAGE(S24:V24))) -> 3 | L24: =IF(AND(D24="K",K24=1),'Maturity Rating'!$E$8,IF(K24="NA",K24,IF(D24="K",K24*'Maturity Rating'!$E$7,K24))) -> 3 | S24: =VLOOKUP(G24,'Maturity Rating'!A$2:B$5,2,FALSE) -> 3 | T24: =VLOOKUP(H24,'Maturity Rating'!A$8:B$11,2,FALSE) -> 3 | U24: =VLOOKUP(I24,'Maturity Rating'!A$14:B$17,2,FALSE) -> 3 | V24: =VLOOKUP(J24,'Maturity Rating'!A$20:B$23,2,FALSE) -> 3 | W24: =CONCATENATE(S24,T24,U24,V24) -> 3333
A25: 5.23 | E25: Backed up data is stored at online and offsite locations | F25: Preventive | G25: Formally Documented | H25: 51 - 100% Implemented | I25: Automated | J25: Monitored & Reviewed | K25: =IF(W25="NANANANA",S25,IF(AND(OR(G25="Formally Documented",G25="Informally Documented"),H25="Not Implemented"),0.5*AVERAGE(S25:V25),AVERAGE(S25:V25))) -> 3 | L25: =IF(AND(D25="K",K25=1),'Maturity Rating'!$E$8,IF(K25="NA",K25,IF(D25="K",K25*'Maturity Rating'!$E$7,K25))) -> 3 | S25: =VLOOKUP(G25,'Maturity Rating'!A$2:B$5,2,FALSE) -> 3 | T25: =VLOOKUP(H25,'Maturity Rating'!A$8:B$11,2,FALSE) -> 3 | U25: =VLOOKUP(I25,'Maturity Rating'!A$14:B$17,2,FALSE) -> 3 | V25: =VLOOKUP(J25,'Maturity Rating'!A$20:B$23,2,FALSE) -> 3 | W25: =CONCATENATE(S25,T25,U25,V25) -> 3333
A26: 5.24 | B26: Change Management | C26: To Ensure that all changes to the organization's information processing facilities are controlled | D26: K | E26: There is a defined and documented process for Change management | F26: Preventive | G26: Formally Documented | H26: 0 - 50% Implemented | I26: Partially Automated | J26: Monitored & Reviewed | K26: =IF(W26="NANANANA",S26,IF(AND(OR(G26="Formally Documented",G26="Informally Documented"),H26="Not Implemented"),0.5*AVERAGE(S26:V26),AVERAGE(S26:V26))) -> 2.5 | L26: =IF(AND(D26="K",K26=1),'Maturity Rating'!$E$8,IF(K26="NA",K26,IF(D26="K",K26*'Maturity Rating'!$E$7,K26))) -> 3 | M26: =IF(X26="NANANANANANANANANANANANA",K26,AVERAGE(L26:L35)) -> 1.38 | N26: =IF(M26<1.1,1,IF(M26="NA",M26,(MIN(5,M26/3*5)))) -> 2.3 | O26: =IF(N26="NA",N26,VLOOKUP(Q26,'Maturity Rating'!G4:H8,2,FALSE)) -> Partial | Q26: =IF(N26="NA",N26,ROUNDDOWN(N26,0)) -> 2 | S26: =VLOOKUP(G26,'Maturity Rating'!A$2:B$5,2,FALSE) -> 3 | T26: =VLOOKUP(H26,'Maturity Rating'!A$8:B$11,2,FALSE) -> 2 | U26: =VLOOKUP(I26,'Maturity Rating'!A$14:B$17,2,FALSE) -> 2 | V26: =VLOOKUP(J26,'Maturity Rating'!A$20:B$23,2,FALSE) -> 3 | W26: =CONCATENATE(S26,T26,U26,V26) -> 3223 | X26: =CONCATENATE(L26,L27,L28,L29,L30,L31,L32,L33,L34,L35) -> 330.81111111
A27: 5.25 | E27: The documents are reviewed, updated and approved as per the defined frequency in the policy/ procedure. | F27: Preventive | G27: Formally Documented | H27: 51 - 100% Implemented | I27: Automated | J27: Monitored & Reviewed | K27: =IF(W27="NANANANA",S27,IF(AND(OR(G27="Formally Documented",G27="Informally Documented"),H27="Not Implemented"),0.5*AVERAGE(S27:V27),AVERAGE(S27:V27))) -> 3 | L27: =IF(AND(D27="K",K27=1),'Maturity Rating'!$E$8,IF(K27="NA",K27,IF(D27="K",K27*'Maturity Rating'!$E$7,K27))) -> 3 | S27: =VLOOKUP(G27,'Maturity Rating'!A$2:B$5,2,FALSE) -> 3 | T27: =VLOOKUP(H27,'Maturity Rating'!A$8:B$11,2,FALSE) -> 3 | U27: =VLOOKUP(I27,'Maturity Rating'!A$14:B$17,2,FALSE) -> 3 | V27: =VLOOKUP(J27,'Maturity Rating'!A$20:B$23,2,FALSE) -> 3 | W27: =CONCATENATE(S27,T27,U27,V27) -> 3333
A28: 5.26 | D28: K | E28: There is a defined process for handling emergency changes | F28: Preventive | G28: Not Documented | H28: Not Applicable | I28: Not Applicable | J28: Not Applicable | K28: =IF(W28="NANANANA",S28,IF(AND(OR(G28="Formally Documented",G28="Informally Documented"),H28="Not Implemented"),0.5*AVERAGE(S28:V28),AVERAGE(S28:V28))) -> 1 | L28: =IF(AND(D28="K",K28=1),'Maturity Rating'!$E$8,IF(K28="NA",K28,IF(D28="K",K28*'Maturity Rating'!$E$7,K28))) -> 0.8 | S28: =VLOOKUP(G28,'Maturity Rating'!A$2:B$5,2,FALSE) -> 1 | T28: =VLOOKUP(H28,'Maturity Rating'!A$8:B$11,2,FALSE) -> NA | U28: =VLOOKUP(I28,'Maturity Rating'!A$14:B$17,2,FALSE) -> NA | V28: =VLOOKUP(J28,'Maturity Rating'!A$20:B$23,2,FALSE) -> NA | W28: =CONCATENATE(S28,T28,U28,V28) -> 1NANANA
A29: 5.27 | E29: Change requests are classified based on their priority. | F29: Preventive | G29: Not Documented | H29: Not Applicable | I29: Not Applicable | J29: Not Applicable | K29: =IF(W29="NANANANA",S29,IF(AND(OR(G29="Formally Documented",G29="Informally Documented"),H29="Not Implemented"),0.5*AVERAGE(S29:V29),AVERAGE(S29:V29))) -> 1 | L29: =IF(AND(D29="K",K29=1),'Maturity Rating'!$E$8,IF(K29="NA",K29,IF(D29="K",K29*'Maturity Rating'!$E$7,K29))) -> 1 | S29: =VLOOKUP(G29,'Maturity Rating'!A$2:B$5,2,FALSE) -> 1 | T29: =VLOOKUP(H29,'Maturity Rating'!A$8:B$11,2,FALSE) -> NA | U29: =VLOOKUP(I29,'Maturity Rating'!A$14:B$17,2,FALSE) -> NA | V29: =VLOOKUP(J29,'Maturity Rating'!A$20:B$23,2,FALSE) -> NA | W29: =CONCATENATE(S29,T29,U29,V29) -> 1NANANA
A30: 5.28 | E30: All change requests are logged and tracked. | F30: Preventive | G30: Not Documented | H30: Not Applicable | I30: Not Applicable | J30: Not Applicable | K30: =IF(W30="NANANANA",S30,IF(AND(OR(G30="Formally Documented",G30="Informally Documented"),H30="Not Implemented"),0.5*AVERAGE(S30:V30),AVERAGE(S30:V30))) -> 1 | L30: =IF(AND(D30="K",K30=1),'Maturity Rating'!$E$8,IF(K30="NA",K30,IF(D30="K",K30*'Maturity Rating'!$E$7,K30))) -> 1 | S30: =VLOOKUP(G30,'Maturity Rating'!A$2:B$5,2,FALSE) -> 1 | T30: =VLOOKUP(H30,'Maturity Rating'!A$8:B$11,2,FALSE) -> NA | U30: =VLOOKUP(I30,'Maturity Rating'!A$14:B$17,2,FALSE) -> NA | V30: =VLOOKUP(J30,'Maturity Rating'!A$20:B$23,2,FALSE) -> NA | W30: =CONCATENATE(S30,T30,U30,V30) -> 1NANANA
A31: 5.29 | E31: Changes are tested before deployment into production | F31: Preventive | G31: Not Documented | H31: Not Applicable | I31: Not Applicable | J31: Not Applicable | K31: =IF(W31="NANANANA",S31,IF(AND(OR(G31="Formally Documented",G31="Informally Documented"),H31="Not Implemented"),0.5*AVERAGE(S31:V31),AVERAGE(S31:V31))) -> 1 | L31: =IF(AND(D31="K",K31=1),'Maturity Rating'!$E$8,IF(K31="NA",K31,IF(D31="K",K31*'Maturity Rating'!$E$7,K31))) -> 1 | S31: =VLOOKUP(G31,'Maturity Rating'!A$2:B$5,2,FALSE) -> 1 | T31: =VLOOKUP(H31,'Maturity Rating'!A$8:B$11,2,FALSE) -> NA | U31: =VLOOKUP(I31,'Maturity Rating'!A$14:B$17,2,FALSE) -> NA | V31: =VLOOKUP(J31,'Maturity Rating'!A$20:B$23,2,FALSE) -> NA | W31: =CONCATENATE(S31,T31,U31,V31) -> 1NANANA
A32: 5. 30 | E32: Changes are deployed in production only post approval from authorized individuals | F32: Preventive | G32: Not Documented | H32: Not Applicable | I32: Not Applicable | J32: Not Applicable | K32: =IF(W32="NANANANA",S32,IF(AND(OR(G32="Formally Documented",G32="Informally Documented"),H32="Not Implemented"),0.5*AVERAGE(S32:V32),AVERAGE(S32:V32))) -> 1 | L32: =IF(AND(D32="K",K32=1),'Maturity Rating'!$E$8,IF(K32="NA",K32,IF(D32="K",K32*'Maturity Rating'!$E$7,K32))) -> 1 | S32: =VLOOKUP(G32,'Maturity Rating'!A$2:B$5,2,FALSE) -> 1 | T32: =VLOOKUP(H32,'Maturity Rating'!A$8:B$11,2,FALSE) -> NA | U32: =VLOOKUP(I32,'Maturity Rating'!A$14:B$17,2,FALSE) -> NA | V32: =VLOOKUP(J32,'Maturity Rating'!A$20:B$23,2,FALSE) -> NA | W32: =CONCATENATE(S32,T32,U32,V32) -> 1NANANA
A33: 5.31 | E33: Changes are deployed into production at a defined frequency based on their criticality | F33: Preventive | G33: Not Documented | H33: Not Applicable | I33: Not Applicable | J33: Not Applicable | K33: =IF(W33="NANANANA",S33,IF(AND(OR(G33="Formally Documented",G33="Informally Documented"),H33="Not Implemented"),0.5*AVERAGE(S33:V33),AVERAGE(S33:V33))) -> 1 | L33: =IF(AND(D33="K",K33=1),'Maturity Rating'!$E$8,IF(K33="NA",K33,IF(D33="K",K33*'Maturity Rating'!$E$7,K33))) -> 1 | S33: =VLOOKUP(G33,'Maturity Rating'!A$2:B$5,2,FALSE) -> 1 | T33: =VLOOKUP(H33,'Maturity Rating'!A$8:B$11,2,FALSE) -> NA | U33: =VLOOKUP(I33,'Maturity Rating'!A$14:B$17,2,FALSE) -> NA | V33: =VLOOKUP(J33,'Maturity Rating'!A$20:B$23,2,FALSE) -> NA | W33: =CONCATENATE(S33,T33,U33,V33) -> 1NANANA
A34: 5.32 | E34: There is a turn around time defined for closing the changes based on the criticality | F34: Preventive | G34: Not Documented | H34: Not Applicable | I34: Not Applicable | J34: Not Applicable | K34: =IF(W34="NANANANA",S34,IF(AND(OR(G34="Formally Documented",G34="Informally Documented"),H34="Not Implemented"),0.5*AVERAGE(S34:V34),AVERAGE(S34:V34))) -> 1 | L34: =IF(AND(D34="K",K34=1),'Maturity Rating'!$E$8,IF(K34="NA",K34,IF(D34="K",K34*'Maturity Rating'!$E$7,K34))) -> 1 | S34: =VLOOKUP(G34,'Maturity Rating'!A$2:B$5,2,FALSE) -> 1 | T34: =VLOOKUP(H34,'Maturity Rating'!A$8:B$11,2,FALSE) -> NA | U34: =VLOOKUP(I34,'Maturity Rating'!A$14:B$17,2,FALSE) -> NA | V34: =VLOOKUP(J34,'Maturity Rating'!A$20:B$23,2,FALSE) -> NA | W34: =CONCATENATE(S34,T34,U34,V34) -> 1NANANA
A35: 5.33 | E35: Roll back procedures are defined for all changes before making changes to production. | F35: Preventive | G35: Not Documented | H35: Not Applicable | I35: Not Applicable | J35: Not Applicable | K35: =IF(W35="NANANANA",S35,IF(AND(OR(G35="Formally Documented",G35="Informally Documented"),H35="Not Implemented"),0.5*AVERAGE(S35:V35),AVERAGE(S35:V35))) -> 1 | L35: =IF(AND(D35="K",K35=1),'Maturity Rating'!$E$8,IF(K35="NA",K35,IF(D35="K",K35*'Maturity Rating'!$E$7,K35))) -> 1 | S35: =VLOOKUP(G35,'Maturity Rating'!A$2:B$5,2,FALSE) -> 1 | T35: =VLOOKUP(H35,'Maturity Rating'!A$8:B$11,2,FALSE) -> NA | U35: =VLOOKUP(I35,'Maturity Rating'!A$14:B$17,2,FALSE) -> NA | V35: =VLOOKUP(J35,'Maturity Rating'!A$20:B$23,2,FALSE) -> NA | W35: =CONCATENATE(S35,T35,U35,V35) -> 1NANANA
A36: 5.34 | B36: Audit and Event Logging | C36: To ensure sufficient data is available for audit and investigation purposes of all critical events | E36: There is a formally defined and documented procedure for log management | F36: Preventive | G36: Formally Documented | H36: 51 - 100% Implemented | I36: Automated | J36: Monitored & Reviewed | K36: =IF(W36="NANANANA",S36,IF(AND(OR(G36="Formally Documented",G36="Informally Documented"),H36="Not Implemented"),0.5*AVERAGE(S36:V36),AVERAGE(S36:V36))) -> 3 | L36: =IF(AND(D36="K",K36=1),'Maturity Rating'!$E$8,IF(K36="NA",K36,IF(D36="K",K36*'Maturity Rating'!$E$7,K36))) -> 3 | M36: =IF(X36="NANANANANANANA",K36,AVERAGE(L36:L44)) -> 1.1777778 | N36: =IF(M36<1.1,1,IF(M36="NA",M36,(MIN(5,M36/3*5)))) -> 1.962963 | O36: =IF(N36="NA",N36,VLOOKUP(Q36,'Maturity Rating'!G4:H8,2,FALSE)) -> Initial | Q36: =IF(N36="NA",N36,ROUNDDOWN(N36,0)) -> 1 | S36: =VLOOKUP(G36,'Maturity Rating'!A$2:B$5,2,FALSE) -> 3 | T36: =VLOOKUP(H36,'Maturity Rating'!A$8:B$11,2,FALSE) -> 3 | U36: =VLOOKUP(I36,'Maturity Rating'!A$14:B$17,2,FALSE) -> 3 | V36: =VLOOKUP(J36,'Maturity Rating'!A$20:B$23,2,FALSE) -> 3 | W36: =CONCATENATE(S36,T36,U36,V36) -> 3333 | X36: =CONCATENATE(L36,L37,L38,L39,L40,L41,L42,L43,L44) -> 310.8110.8111
A37: 5.35 | E37: The documents are reviewed, updated and approved as per the defined frequency in the policy/ procedure. | F37: Preventive | G37: Not Documented | H37: Not Applicable | I37: Not Applicable | J37: Not Applicable | K37: =IF(W37="NANANANA",S37,IF(AND(OR(G37="Formally Documented",G37="Informally Documented"),H37="Not Implemented"),0.5*AVERAGE(S37:V37),AVERAGE(S37:V37))) -> 1 | L37: =IF(AND(D37="K",K37=1),'Maturity Rating'!$E$8,IF(K37="NA",K37,IF(D37="K",K37*'Maturity Rating'!$E$7,K37))) -> 1 | S37: =VLOOKUP(G37,'Maturity Rating'!A$2:B$5,2,FALSE) -> 1 | T37: =VLOOKUP(H37,'Maturity Rating'!A$8:B$11,2,FALSE) -> NA | U37: =VLOOKUP(I37,'Maturity Rating'!A$14:B$17,2,FALSE) -> NA | V37: =VLOOKUP(J37,'Maturity Rating'!A$20:B$23,2,FALSE) -> NA | W37: =CONCATENATE(S37,T37,U37,V37) -> 1NANANA
A38: 5.36 | D38: K | E38: Logging is enabled for all administrative activities | F38: Detective | G38: Not Documented | H38: Not Applicable | I38: Not Applicable | J38: Not Applicable | K38: =IF(W38="NANANANA",S38,IF(AND(OR(G38="Formally Documented",G38="Informally Documented"),H38="Not Implemented"),0.5*AVERAGE(S38:V38),AVERAGE(S38:V38))) -> 1 | L38: =IF(AND(D38="K",K38=1),'Maturity Rating'!$E$8,IF(K38="NA",K38,IF(D38="K",K38*'Maturity Rating'!$E$7,K38))) -> 0.8 | S38: =VLOOKUP(G38,'Maturity Rating'!A$2:B$5,2,FALSE) -> 1 | T38: =VLOOKUP(H38,'Maturity Rating'!A$8:B$11,2,FALSE) -> NA | U38: =VLOOKUP(I38,'Maturity Rating'!A$14:B$17,2,FALSE) -> NA | V38: =VLOOKUP(J38,'Maturity Rating'!A$20:B$23,2,FALSE) -> NA | W38: =CONCATENATE(S38,T38,U38,V38) -> 1NANANA
A39: 5.37 | E39: Event logging should be enabled for all systems | F39: Detective | G39: Not Documented | H39: Not Applicable | I39: Not Applicable | J39: Not Applicable | K39: =IF(W39="NANANANA",S39,IF(AND(OR(G39="Formally Documented",G39="Informally Documented"),H39="Not Implemented"),0.5*AVERAGE(S39:V39),AVERAGE(S39:V39))) -> 1 | L39: =IF(AND(D39="K",K39=1),'Maturity Rating'!$E$8,IF(K39="NA",K39,IF(D39="K",K39*'Maturity Rating'!$E$7,K39))) -> 1 | S39: =VLOOKUP(G39,'Maturity Rating'!A$2:B$5,2,FALSE) -> 1 | T39: =VLOOKUP(H39,'Maturity Rating'!A$8:B$11,2,FALSE) -> NA | U39: =VLOOKUP(I39,'Maturity Rating'!A$14:B$17,2,FALSE) -> NA | V39: =VLOOKUP(J39,'Maturity Rating'!A$20:B$23,2,FALSE) -> NA | W39: =CONCATENATE(S39,T39,U39,V39) -> 1NANANA
A40: 5.38 | E40: Level of logging is defined for all the log sources | F40: Preventive | G40: Not Documented | H40: Not Applicable | I40: Not Applicable | J40: Not Applicable | K40: =IF(W40="NANANANA",S40,IF(AND(OR(G40="Formally Documented",G40="Informally Documented"),H40="Not Implemented"),0.5*AVERAGE(S40:V40),AVERAGE(S40:V40))) -> 1 | L40: =IF(AND(D40="K",K40=1),'Maturity Rating'!$E$8,IF(K40="NA",K40,IF(D40="K",K40*'Maturity Rating'!$E$7,K40))) -> 1 | S40: =VLOOKUP(G40,'Maturity Rating'!A$2:B$5,2,FALSE) -> 1 | T40: =VLOOKUP(H40,'Maturity Rating'!A$8:B$11,2,FALSE) -> NA | U40: =VLOOKUP(I40,'Maturity Rating'!A$14:B$17,2,FALSE) -> NA | V40: =VLOOKUP(J40,'Maturity Rating'!A$20:B$23,2,FALSE) -> NA | W40: =CONCATENATE(S40,T40,U40,V40) -> 1NANANA
A41: 5.39 | D41: K | E41: Log data is centrally stored, backed up and retained for a defined time period | F41: Detective | G41: Not Documented | H41: Not Applicable | I41: Not Applicable | J41: Not Applicable | K41: =IF(W41="NANANANA",S41,IF(AND(OR(G41="Formally Documented",G41="Informally Documented"),H41="Not Implemented"),0.5*AVERAGE(S41:V41),AVERAGE(S41:V41))) -> 1 | L41: =IF(AND(D41="K",K41=1),'Maturity Rating'!$E$8,IF(K41="NA",K41,IF(D41="K",K41*'Maturity Rating'!$E$7,K41))) -> 0.8 | S41: =VLOOKUP(G41,'Maturity Rating'!A$2:B$5,2,FALSE) -> 1 | T41: =VLOOKUP(H41,'Maturity Rating'!A$8:B$11,2,FALSE) -> NA | U41: =VLOOKUP(I41,'Maturity Rating'!A$14:B$17,2,FALSE) -> NA | V41: =VLOOKUP(J41,'Maturity Rating'!A$20:B$23,2,FALSE) -> NA | W41: =CONCATENATE(S41,T41,U41,V41) -> 1NANANA
A42: 5. 40 | E42: Security logging should be enabled for all critical infrastructure as per the policy/ procedure. | F42: Detective | G42: Not Documented | H42: Not Applicable | I42: Not Applicable | J42: Not Applicable | K42: =IF(W42="NANANANA",S42,IF(AND(OR(G42="Formally Documented",G42="Informally Documented"),H42="Not Implemented"),0.5*AVERAGE(S42:V42),AVERAGE(S42:V42))) -> 1 | L42: =IF(AND(D42="K",K42=1),'Maturity Rating'!$E$8,IF(K42="NA",K42,IF(D42="K",K42*'Maturity Rating'!$E$7,K42))) -> 1 | S42: =VLOOKUP(G42,'Maturity Rating'!A$2:B$5,2,FALSE) -> 1 | T42: =VLOOKUP(H42,'Maturity Rating'!A$8:B$11,2,FALSE) -> NA | U42: =VLOOKUP(I42,'Maturity Rating'!A$14:B$17,2,FALSE) -> NA | V42: =VLOOKUP(J42,'Maturity Rating'!A$20:B$23,2,FALSE) -> NA | W42: =CONCATENATE(S42,T42,U42,V42) -> 1NANANA
A43: 5.41 | E43: Critical infrastructure devices are integrated with SIEM for log correlation and alerting | F43: Detective | G43: Not Documented | H43: Not Applicable | I43: Not Applicable | J43: Not Applicable | K43: =IF(W43="NANANANA",S43,IF(AND(OR(G43="Formally Documented",G43="Informally Documented"),H43="Not Implemented"),0.5*AVERAGE(S43:V43),AVERAGE(S43:V43))) -> 1 | L43: =IF(AND(D43="K",K43=1),'Maturity Rating'!$E$8,IF(K43="NA",K43,IF(D43="K",K43*'Maturity Rating'!$E$7,K43))) -> 1 | S43: =VLOOKUP(G43,'Maturity Rating'!A$2:B$5,2,FALSE) -> 1 | T43: =VLOOKUP(H43,'Maturity Rating'!A$8:B$11,2,FALSE) -> NA | U43: =VLOOKUP(I43,'Maturity Rating'!A$14:B$17,2,FALSE) -> NA | V43: =VLOOKUP(J43,'Maturity Rating'!A$20:B$23,2,FALSE) -> NA | W43: =CONCATENATE(S43,T43,U43,V43) -> 1NANANA
A44: 5.42 | E44: All critical devices are integrated with the same NTP for clock synchronization and time stamp consistency | F44: Detective | G44: Not Documented | H44: Not Applicable | I44: Not Applicable | J44: Not Applicable | K44: =IF(W44="NANANANA",S44,IF(AND(OR(G44="Formally Documented",G44="Informally Documented"),H44="Not Implemented"),0.5*AVERAGE(S44:V44),AVERAGE(S44:V44))) -> 1 | L44: =IF(AND(D44="K",K44=1),'Maturity Rating'!$E$8,IF(K44="NA",K44,IF(D44="K",K44*'Maturity Rating'!$E$7,K44))) -> 1 | S44: =VLOOKUP(G44,'Maturity Rating'!A$2:B$5,2,FALSE) -> 1 | T44: =VLOOKUP(H44,'Maturity Rating'!A$8:B$11,2,FALSE) -> NA | U44: =VLOOKUP(I44,'Maturity Rating'!A$14:B$17,2,FALSE) -> NA | V44: =VLOOKUP(J44,'Maturity Rating'!A$20:B$23,2,FALSE) -> NA | W44: =CONCATENATE(S44,T44,U44,V44) -> 1NANANA
A45: 5.43 | B45: Secure Configuration & Design | C45: To ensure security is considered in the configuration and deployment of network devices | D45: K | E45: There is a configuration hardening process document defined for all critical infrastructure systems | F45: Preventive | G45: Not Documented | H45: Not Applicable | I45: Not Applicable | J45: Not Applicable | K45: =IF(W45="NANANANA",S45,IF(AND(OR(G45="Formally Documented",G45="Informally Documented"),H45="Not Implemented"),0.5*AVERAGE(S45:V45),AVERAGE(S45:V45))) -> 1 | L45: =IF(AND(D45="K",K45=1),'Maturity Rating'!$E$8,IF(K45="NA",K45,IF(D45="K",K45*'Maturity Rating'!$E$7,K45))) -> 0.8 | M45: =IF(X45="NANANANA",K45,AVERAGE(L45:L52)) -> 0.95 | N45: =IF(M45<1.1,1,IF(M45="NA",M45,(MIN(5,M45/3*5)))) -> 1 | O45: =IF(N45="NA",N45,VLOOKUP(Q45,'Maturity Rating'!G4:H8,2,FALSE)) -> Initial | Q45: =IF(N45="NA",N45,ROUNDDOWN(N45,0)) -> 1 | S45: =VLOOKUP(G45,'Maturity Rating'!A$2:B$5,2,FALSE) -> 1 | T45: =VLOOKUP(H45,'Maturity Rating'!A$8:B$11,2,FALSE) -> NA | U45: =VLOOKUP(I45,'Maturity Rating'!A$14:B$17,2,FALSE) -> NA | V45: =VLOOKUP(J45,'Maturity Rating'!A$20:B$23,2,FALSE) -> NA | W45: =CONCATENATE(S45,T45,U45,V45) -> 1NANANA | X45: =CONCATENATE(L45,L46,L47,L48,L49,L50,L51,L52) -> 0.810.811111
A46: 5.44 | E46: The hardening document is updated and reviewed at periodic intervals | F46: Preventive | G46: Not Documented | H46: Not Applicable | I46: Not Applicable | J46: Not Applicable | K46: =IF(W46="NANANANA",S46,IF(AND(OR(G46="Formally Documented",G46="Informally Documented"),H46="Not Implemented"),0.5*AVERAGE(S46:V46),AVERAGE(S46:V46))) -> 1 | L46: =IF(AND(D46="K",K46=1),'Maturity Rating'!$E$8,IF(K46="NA",K46,IF(D46="K",K46*'Maturity Rating'!$E$7,K46))) -> 1 | S46: =VLOOKUP(G46,'Maturity Rating'!A$2:B$5,2,FALSE) -> 1 | T46: =VLOOKUP(H46,'Maturity Rating'!A$8:B$11,2,FALSE) -> NA | U46: =VLOOKUP(I46,'Maturity Rating'!A$14:B$17,2,FALSE) -> NA | V46: =VLOOKUP(J46,'Maturity Rating'!A$20:B$23,2,FALSE) -> NA | W46: =CONCATENATE(S46,T46,U46,V46) -> 1NANANA
A47: 5.45 | D47: K | E47: The configuration of all infrastructure devices are hardened before deployment in production | F47: Preventive | G47: Not Documented | H47: Not Applicable | I47: Not Applicable | J47: Not Applicable | K47: =IF(W47="NANANANA",S47,IF(AND(OR(G47="Formally Documented",G47="Informally Documented"),H47="Not Implemented"),0.5*AVERAGE(S47:V47),AVERAGE(S47:V47))) -> 1 | L47: =IF(AND(D47="K",K47=1),'Maturity Rating'!$E$8,IF(K47="NA",K47,IF(D47="K",K47*'Maturity Rating'!$E$7,K47))) -> 0.8 | S47: =VLOOKUP(G47,'Maturity Rating'!A$2:B$5,2,FALSE) -> 1 | T47: =VLOOKUP(H47,'Maturity Rating'!A$8:B$11,2,FALSE) -> NA | U47: =VLOOKUP(I47,'Maturity Rating'!A$14:B$17,2,FALSE) -> NA | V47: =VLOOKUP(J47,'Maturity Rating'!A$20:B$23,2,FALSE) -> NA | W47: =CONCATENATE(S47,T47,U47,V47) -> 1NANANA
A48: 5.46 | E48: The development, test & production environments are logically segregated | F48: Preventive | G48: Not Documented | H48: Not Applicable | I48: Not Applicable | J48: Not Applicable | K48: =IF(W48="NANANANA",S48,IF(AND(OR(G48="Formally Documented",G48="Informally Documented"),H48="Not Implemented"),0.5*AVERAGE(S48:V48),AVERAGE(S48:V48))) -> 1 | L48: =IF(AND(D48="K",K48=1),'Maturity Rating'!$E$8,IF(K48="NA",K48,IF(D48="K",K48*'Maturity Rating'!$E$7,K48))) -> 1 | S48: =VLOOKUP(G48,'Maturity Rating'!A$2:B$5,2,FALSE) -> 1 | T48: =VLOOKUP(H48,'Maturity Rating'!A$8:B$11,2,FALSE) -> NA | U48: =VLOOKUP(I48,'Maturity Rating'!A$14:B$17,2,FALSE) -> NA | V48: =VLOOKUP(J48,'Maturity Rating'!A$20:B$23,2,FALSE) -> NA | W48: =CONCATENATE(S48,T48,U48,V48) -> 1NANANA
A49: 5.47 | E49: There is segregation of duties wherein developers do not have access to the QA & production environment | F49: Preventive | G49: Not Documented | H49: Not Applicable | I49: Not Applicable | J49: Not Applicable | K49: =IF(W49="NANANANA",S49,IF(AND(OR(G49="Formally Documented",G49="Informally Documented"),H49="Not Implemented"),0.5*AVERAGE(S49:V49),AVERAGE(S49:V49))) -> 1 | L49: =IF(AND(D49="K",K49=1),'Maturity Rating'!$E$8,IF(K49="NA",K49,IF(D49="K",K49*'Maturity Rating'!$E$7,K49))) -> 1 | S49: =VLOOKUP(G49,'Maturity Rating'!A$2:B$5,2,FALSE) -> 1 | T49: =VLOOKUP(H49,'Maturity Rating'!A$8:B$11,2,FALSE) -> NA | U49: =VLOOKUP(I49,'Maturity Rating'!A$14:B$17,2,FALSE) -> NA | V49: =VLOOKUP(J49,'Maturity Rating'!A$20:B$23,2,FALSE) -> NA | W49: =CONCATENATE(S49,T49,U49,V49) -> 1NANANA
A50: 5.48 | E50: CIS benchmark are followed for hardening templates. | F50: Preventive | G50: Not Documented | H50: Not Implemented | I50: Not Automated | J50: Not Monitored & Reviewed | K50: =IF(W50="NANANANA",S50,IF(AND(OR(G50="Formally Documented",G50="Informally Documented"),H50="Not Implemented"),0.5*AVERAGE(S50:V50),AVERAGE(S50:V50))) -> 1 | L50: =IF(AND(D50="K",K50=1),'Maturity Rating'!$E$8,IF(K50="NA",K50,IF(D50="K",K50*'Maturity Rating'!$E$7,K50))) -> 1 | S50: =VLOOKUP(G50,'Maturity Rating'!A$2:B$5,2,FALSE) -> 1 | T50: =VLOOKUP(H50,'Maturity Rating'!A$8:B$11,2,FALSE) -> 1 | U50: =VLOOKUP(I50,'Maturity Rating'!A$14:B$17,2,FALSE) -> 1 | V50: =VLOOKUP(J50,'Maturity Rating'!A$20:B$23,2,FALSE) -> 1 | W50: =CONCATENATE(S50,T50,U50,V50) -> 1111
A51: 5.49 | E51: System architecture is designed and implemented securely | F51: Preventive | G51: Not Documented | H51: Not Applicable | I51: Not Applicable | J51: Not Applicable | K51: =IF(W51="NANANANA",S51,IF(AND(OR(G51="Formally Documented",G51="Informally Documented"),H51="Not Implemented"),0.5*AVERAGE(S51:V51),AVERAGE(S51:V51))) -> 1 | L51: =IF(AND(D51="K",K51=1),'Maturity Rating'!$E$8,IF(K51="NA",K51,IF(D51="K",K51*'Maturity Rating'!$E$7,K51))) -> 1 | S51: =VLOOKUP(G51,'Maturity Rating'!A$2:B$5,2,FALSE) -> 1 | T51: =VLOOKUP(H51,'Maturity Rating'!A$8:B$11,2,FALSE) -> NA | U51: =VLOOKUP(I51,'Maturity Rating'!A$14:B$17,2,FALSE) -> NA | V51: =VLOOKUP(J51,'Maturity Rating'!A$20:B$23,2,FALSE) -> NA | W51: =CONCATENATE(S51,T51,U51,V51) -> 1NANANA
A52: 5. 50 | E52: Configuration of infrastructure devices is reviewed periodically for compliance to the hardening guideline | F52: Preventive | G52: Not Documented | H52: Not Applicable | I52: Not Applicable | J52: Not Applicable | K52: =IF(W52="NANANANA",S52,IF(AND(OR(G52="Formally Documented",G52="Informally Documented"),H52="Not Implemented"),0.5*AVERAGE(S52:V52),AVERAGE(S52:V52))) -> 1 | L52: =IF(AND(D52="K",K52=1),'Maturity Rating'!$E$8,IF(K52="NA",K52,IF(D52="K",K52*'Maturity Rating'!$E$7,K52))) -> 1 | S52: =VLOOKUP(G52,'Maturity Rating'!A$2:B$5,2,FALSE) -> 1 | T52: =VLOOKUP(H52,'Maturity Rating'!A$8:B$11,2,FALSE) -> NA | U52: =VLOOKUP(I52,'Maturity Rating'!A$14:B$17,2,FALSE) -> NA | V52: =VLOOKUP(J52,'Maturity Rating'!A$20:B$23,2,FALSE) -> NA | W52: =CONCATENATE(S52,T52,U52,V52) -> 1NANANA
A53: 5.51 | B53: Capacity Management | C53: To ensure use of resources should be monitored, tuned and projections made of future capacity requirements to ensure the required system performance | E53: There is a defined and documented policy for capacity management | F53: Preventive | G53: Not Applicable | H53: Not Applicable | I53: Not Applicable | J53: Not Applicable | K53: =IF(W53="NANANANA",S53,IF(AND(OR(G53="Formally Documented",G53="Informally Documented"),H53="Not Implemented"),0.5*AVERAGE(S53:V53),AVERAGE(S53:V53))) -> NA | L53: =IF(AND(D53="K",K53=1),'Maturity Rating'!$E$8,IF(K53="NA",K53,IF(D53="K",K53*'Maturity Rating'!$E$7,K53))) -> NA | M53: =IF(X53="NANANANANA",K53,AVERAGE(L53:L57)) -> 1.45 | N53: =IF(M53<1.1,1,IF(M53="NA",M53,(MIN(5,M53/3*5)))) -> 2.4166667 | O53: =IF(N53="NA",N53,VLOOKUP(Q53,'Maturity Rating'!G4:H8,2,FALSE)) -> Partial | Q53: =IF(N53="NA",N53,ROUNDDOWN(N53,0)) -> 2 | S53: =VLOOKUP(G53,'Maturity Rating'!A$2:B$5,2,FALSE) -> NA | T53: =VLOOKUP(H53,'Maturity Rating'!A$8:B$11,2,FALSE) -> NA | U53: =VLOOKUP(I53,'Maturity Rating'!A$14:B$17,2,FALSE) -> NA | V53: =VLOOKUP(J53,'Maturity Rating'!A$20:B$23,2,FALSE) -> NA | W53: =CONCATENATE(S53,T53,U53,V53) -> NANANANA | X53: =CONCATENATE(L53,L54,L55,L56,L57) -> NA30.811
A54: 5.52 | E54: The documents are reviewed, updated and approved as per the defined frequency in the policy/ procedure. | F54: Preventive | G54: Formally Documented | H54: 51 - 100% Implemented | I54: Automated | J54: Monitored & Reviewed | K54: =IF(W54="NANANANA",S54,IF(AND(OR(G54="Formally Documented",G54="Informally Documented"),H54="Not Implemented"),0.5*AVERAGE(S54:V54),AVERAGE(S54:V54))) -> 3 | L54: =IF(AND(D54="K",K54=1),'Maturity Rating'!$E$8,IF(K54="NA",K54,IF(D54="K",K54*'Maturity Rating'!$E$7,K54))) -> 3 | S54: =VLOOKUP(G54,'Maturity Rating'!A$2:B$5,2,FALSE) -> 3 | T54: =VLOOKUP(H54,'Maturity Rating'!A$8:B$11,2,FALSE) -> 3 | U54: =VLOOKUP(I54,'Maturity Rating'!A$14:B$17,2,FALSE) -> 3 | V54: =VLOOKUP(J54,'Maturity Rating'!A$20:B$23,2,FALSE) -> 3 | W54: =CONCATENATE(S54,T54,U54,V54) -> 3333
A55: 5.53 | D55: K | E55: There is continuous monitoring of the resource utilization of systems | F55: Preventive | G55: Not Documented | H55: Not Applicable | I55: Not Applicable | J55: Not Applicable | K55: =IF(W55="NANANANA",S55,IF(AND(OR(G55="Formally Documented",G55="Informally Documented"),H55="Not Implemented"),0.5*AVERAGE(S55:V55),AVERAGE(S55:V55))) -> 1 | L55: =IF(AND(D55="K",K55=1),'Maturity Rating'!$E$8,IF(K55="NA",K55,IF(D55="K",K55*'Maturity Rating'!$E$7,K55))) -> 0.8 | S55: =VLOOKUP(G55,'Maturity Rating'!A$2:B$5,2,FALSE) -> 1 | T55: =VLOOKUP(H55,'Maturity Rating'!A$8:B$11,2,FALSE) -> NA | U55: =VLOOKUP(I55,'Maturity Rating'!A$14:B$17,2,FALSE) -> NA | V55: =VLOOKUP(J55,'Maturity Rating'!A$20:B$23,2,FALSE) -> NA | W55: =CONCATENATE(S55,T55,U55,V55) -> 1NANANA
A56: 5.54 | E56: There are thresholds defined for acceptable utilization of system resources | F56: Preventive | G56: Not Documented | H56: Not Applicable | I56: Not Applicable | J56: Not Applicable | K56: =IF(W56="NANANANA",S56,IF(AND(OR(G56="Formally Documented",G56="Informally Documented"),H56="Not Implemented"),0.5*AVERAGE(S56:V56),AVERAGE(S56:V56))) -> 1 | L56: =IF(AND(D56="K",K56=1),'Maturity Rating'!$E$8,IF(K56="NA",K56,IF(D56="K",K56*'Maturity Rating'!$E$7,K56))) -> 1 | S56: =VLOOKUP(G56,'Maturity Rating'!A$2:B$5,2,FALSE) -> 1 | T56: =VLOOKUP(H56,'Maturity Rating'!A$8:B$11,2,FALSE) -> NA | U56: =VLOOKUP(I56,'Maturity Rating'!A$14:B$17,2,FALSE) -> NA | V56: =VLOOKUP(J56,'Maturity Rating'!A$20:B$23,2,FALSE) -> NA | W56: =CONCATENATE(S56,T56,U56,V56) -> 1NANANA
A57: 5.55 | E57: Reports of capacity utilization should be analyzed, actions needed to be taken and should be communicated to the senior management | F57: Detective | G57: Not Documented | H57: Not Applicable | I57: Not Applicable | J57: Not Applicable | K57: =IF(W57="NANANANA",S57,IF(AND(OR(G57="Formally Documented",G57="Informally Documented"),H57="Not Implemented"),0.5*AVERAGE(S57:V57),AVERAGE(S57:V57))) -> 1 | L57: =IF(AND(D57="K",K57=1),'Maturity Rating'!$E$8,IF(K57="NA",K57,IF(D57="K",K57*'Maturity Rating'!$E$7,K57))) -> 1 | S57: =VLOOKUP(G57,'Maturity Rating'!A$2:B$5,2,FALSE) -> 1 | T57: =VLOOKUP(H57,'Maturity Rating'!A$8:B$11,2,FALSE) -> NA | U57: =VLOOKUP(I57,'Maturity Rating'!A$14:B$17,2,FALSE) -> NA | V57: =VLOOKUP(J57,'Maturity Rating'!A$20:B$23,2,FALSE) -> NA | W57: =CONCATENATE(S57,T57,U57,V57) -> 1NANANA
A58: 5.56 | B58: Database Security | C58: To ensure that there are effective measures defined and implemented to protect and secure the database. | D58: K | E58: There is a defined and documented process for database security management | F58: Preventive | G58: Not Documented | H58: Not Applicable | I58: Not Applicable | J58: Not Applicable | K58: =IF(W58="NANANANA",S58,IF(AND(OR(G58="Formally Documented",G58="Informally Documented"),H58="Not Implemented"),0.5*AVERAGE(S58:V58),AVERAGE(S58:V58))) -> 1 | L58: =IF(AND(D58="K",K58=1),'Maturity Rating'!$E$8,IF(K58="NA",K58,IF(D58="K",K58*'Maturity Rating'!$E$7,K58))) -> 0.8 | M58: =IF(X58="NANANANANANANANANANANANA",K58,AVERAGE(L58:L69)) -> 1.1166667 | N58: =IF(M58<1.1,1,IF(M58="NA",M58,(MIN(5,M58/3*5)))) -> 1.8611111 | O58: =IF(N58="NA",N58,VLOOKUP(Q58,'Maturity Rating'!G4:H8,2,FALSE)) -> Initial | Q58: =IF(N58="NA",N58,ROUNDDOWN(N58,0)) -> 1 | S58: =VLOOKUP(G58,'Maturity Rating'!A$2:B$5,2,FALSE) -> 1 | T58: =VLOOKUP(H58,'Maturity Rating'!A$8:B$11,2,FALSE) -> NA | U58: =VLOOKUP(I58,'Maturity Rating'!A$14:B$17,2,FALSE) -> NA | V58: =VLOOKUP(J58,'Maturity Rating'!A$20:B$23,2,FALSE) -> NA | W58: =CONCATENATE(S58,T58,U58,V58) -> 1NANANA | X58: =CONCATENATE(L58,L59,L60,L61,L62,L63,L64,L65,L66,L67,L68,L69) -> 0.81110.811130.811
A59: 5.57 | E59: The documents are reviewed, updated and approved as per the defined frequency in the policy/ procedure. | F59: Preventive | G59: Not Documented | H59: Not Applicable | I59: Not Applicable | J59: Not Applicable | K59: =IF(W59="NANANANA",S59,IF(AND(OR(G59="Formally Documented",G59="Informally Documented"),H59="Not Implemented"),0.5*AVERAGE(S59:V59),AVERAGE(S59:V59))) -> 1 | L59: =IF(AND(D59="K",K59=1),'Maturity Rating'!$E$8,IF(K59="NA",K59,IF(D59="K",K59*'Maturity Rating'!$E$7,K59))) -> 1 | S59: =VLOOKUP(G59,'Maturity Rating'!A$2:B$5,2,FALSE) -> 1 | T59: =VLOOKUP(H59,'Maturity Rating'!A$8:B$11,2,FALSE) -> NA | U59: =VLOOKUP(I59,'Maturity Rating'!A$14:B$17,2,FALSE) -> NA | V59: =VLOOKUP(J59,'Maturity Rating'!A$20:B$23,2,FALSE) -> NA | W59: =CONCATENATE(S59,T59,U59,V59) -> 1NANANA
A60: 5.58 | E60: Access to database should be given based on the principle of least privilege | F60: Preventive | G60: Not Documented | H60: Not Applicable | I60: Not Applicable | J60: Not Applicable | K60: =IF(W60="NANANANA",S60,IF(AND(OR(G60="Formally Documented",G60="Informally Documented"),H60="Not Implemented"),0.5*AVERAGE(S60:V60),AVERAGE(S60:V60))) -> 1 | L60: =IF(AND(D60="K",K60=1),'Maturity Rating'!$E$8,IF(K60="NA",K60,IF(D60="K",K60*'Maturity Rating'!$E$7,K60))) -> 1 | S60: =VLOOKUP(G60,'Maturity Rating'!A$2:B$5,2,FALSE) -> 1 | T60: =VLOOKUP(H60,'Maturity Rating'!A$8:B$11,2,FALSE) -> NA | U60: =VLOOKUP(I60,'Maturity Rating'!A$14:B$17,2,FALSE) -> NA | V60: =VLOOKUP(J60,'Maturity Rating'!A$20:B$23,2,FALSE) -> NA | W60: =CONCATENATE(S60,T60,U60,V60) -> 1NANANA
A61: 5.59 | E61: The access to database/ tables is restricted to authorized individuals | F61: Preventive | G61: Not Documented | H61: Not Applicable | I61: Not Applicable | J61: Not Applicable | K61: =IF(W61="NANANANA",S61,IF(AND(OR(G61="Formally Documented",G61="Informally Documented"),H61="Not Implemented"),0.5*AVERAGE(S61:V61),AVERAGE(S61:V61))) -> 1 | L61: =IF(AND(D61="K",K61=1),'Maturity Rating'!$E$8,IF(K61="NA",K61,IF(D61="K",K61*'Maturity Rating'!$E$7,K61))) -> 1 | S61: =VLOOKUP(G61,'Maturity Rating'!A$2:B$5,2,FALSE) -> 1 | T61: =VLOOKUP(H61,'Maturity Rating'!A$8:B$11,2,FALSE) -> NA | U61: =VLOOKUP(I61,'Maturity Rating'!A$14:B$17,2,FALSE) -> NA | V61: =VLOOKUP(J61,'Maturity Rating'!A$20:B$23,2,FALSE) -> NA | W61: =CONCATENATE(S61,T61,U61,V61) -> 1NANANA
A62: 5. 60 | D62: K | E62: The privileged access rights associated with the database management system is identified | F62: Preventive | G62: Not Documented | H62: Not Applicable | I62: Not Applicable | J62: Not Applicable | K62: =IF(W62="NANANANA",S62,IF(AND(OR(G62="Formally Documented",G62="Informally Documented"),H62="Not Implemented"),0.5*AVERAGE(S62:V62),AVERAGE(S62:V62))) -> 1 | L62: =IF(AND(D62="K",K62=1),'Maturity Rating'!$E$8,IF(K62="NA",K62,IF(D62="K",K62*'Maturity Rating'!$E$7,K62))) -> 0.8 | S62: =VLOOKUP(G62,'Maturity Rating'!A$2:B$5,2,FALSE) -> 1 | T62: =VLOOKUP(H62,'Maturity Rating'!A$8:B$11,2,FALSE) -> NA | U62: =VLOOKUP(I62,'Maturity Rating'!A$14:B$17,2,FALSE) -> NA | V62: =VLOOKUP(J62,'Maturity Rating'!A$20:B$23,2,FALSE) -> NA | W62: =CONCATENATE(S62,T62,U62,V62) -> 1NANANA
A63: 5.61 | E63: There is a continuous logging and monitoring of activities performed using privileged IDs | F63: Preventive | G63: Not Documented | H63: Not Applicable | I63: Not Applicable | J63: Not Applicable | K63: =IF(W63="NANANANA",S63,IF(AND(OR(G63="Formally Documented",G63="Informally Documented"),H63="Not Implemented"),0.5*AVERAGE(S63:V63),AVERAGE(S63:V63))) -> 1 | L63: =IF(AND(D63="K",K63=1),'Maturity Rating'!$E$8,IF(K63="NA",K63,IF(D63="K",K63*'Maturity Rating'!$E$7,K63))) -> 1 | S63: =VLOOKUP(G63,'Maturity Rating'!A$2:B$5,2,FALSE) -> 1 | T63: =VLOOKUP(H63,'Maturity Rating'!A$8:B$11,2,FALSE) -> NA | U63: =VLOOKUP(I63,'Maturity Rating'!A$14:B$17,2,FALSE) -> NA | V63: =VLOOKUP(J63,'Maturity Rating'!A$20:B$23,2,FALSE) -> NA | W63: =CONCATENATE(S63,T63,U63,V63) -> 1NANANA
A64: 5.62 | E64: There are no test/ unused default accounts present in the production database | F64: Preventive | G64: Not Documented | H64: Not Applicable | I64: Not Applicable | J64: Not Applicable | K64: =IF(W64="NANANANA",S64,IF(AND(OR(G64="Formally Documented",G64="Informally Documented"),H64="Not Implemented"),0.5*AVERAGE(S64:V64),AVERAGE(S64:V64))) -> 1 | L64: =IF(AND(D64="K",K64=1),'Maturity Rating'!$E$8,IF(K64="NA",K64,IF(D64="K",K64*'Maturity Rating'!$E$7,K64))) -> 1 | S64: =VLOOKUP(G64,'Maturity Rating'!A$2:B$5,2,FALSE) -> 1 | T64: =VLOOKUP(H64,'Maturity Rating'!A$8:B$11,2,FALSE) -> NA | U64: =VLOOKUP(I64,'Maturity Rating'!A$14:B$17,2,FALSE) -> NA | V64: =VLOOKUP(J64,'Maturity Rating'!A$20:B$23,2,FALSE) -> NA | W64: =CONCATENATE(S64,T64,U64,V64) -> 1NANANA
A65: 5.63 | E65: There is a minimum baseline for secure configuration of databases | F65: Preventive | G65: Not Documented | H65: Not Applicable | I65: Not Applicable | J65: Not Applicable | K65: =IF(W65="NANANANA",S65,IF(AND(OR(G65="Formally Documented",G65="Informally Documented"),H65="Not Implemented"),0.5*AVERAGE(S65:V65),AVERAGE(S65:V65))) -> 1 | L65: =IF(AND(D65="K",K65=1),'Maturity Rating'!$E$8,IF(K65="NA",K65,IF(D65="K",K65*'Maturity Rating'!$E$7,K65))) -> 1 | S65: =VLOOKUP(G65,'Maturity Rating'!A$2:B$5,2,FALSE) -> 1 | T65: =VLOOKUP(H65,'Maturity Rating'!A$8:B$11,2,FALSE) -> NA | U65: =VLOOKUP(I65,'Maturity Rating'!A$14:B$17,2,FALSE) -> NA | V65: =VLOOKUP(J65,'Maturity Rating'!A$20:B$23,2,FALSE) -> NA | W65: =CONCATENATE(S65,T65,U65,V65) -> 1NANANA
A66: 5.64 | E66: There are adequate password parameters on the database as per the defined password policy of the organization | F66: Preventive | G66: Formally Documented | H66: 51 - 100% Implemented | I66: Automated | J66: Monitored & Reviewed | K66: =IF(W66="NANANANA",S66,IF(AND(OR(G66="Formally Documented",G66="Informally Documented"),H66="Not Implemented"),0.5*AVERAGE(S66:V66),AVERAGE(S66:V66))) -> 3 | L66: =IF(AND(D66="K",K66=1),'Maturity Rating'!$E$8,IF(K66="NA",K66,IF(D66="K",K66*'Maturity Rating'!$E$7,K66))) -> 3 | S66: =VLOOKUP(G66,'Maturity Rating'!A$2:B$5,2,FALSE) -> 3 | T66: =VLOOKUP(H66,'Maturity Rating'!A$8:B$11,2,FALSE) -> 3 | U66: =VLOOKUP(I66,'Maturity Rating'!A$14:B$17,2,FALSE) -> 3 | V66: =VLOOKUP(J66,'Maturity Rating'!A$20:B$23,2,FALSE) -> 3 | W66: =CONCATENATE(S66,T66,U66,V66) -> 3333
A67: 5.65 | D67: K | E67: The PII and SPI data stored in the database is encrypted | F67: Detective | G67: Not Documented | H67: Not Applicable | I67: Not Applicable | J67: Not Applicable | K67: =IF(W67="NANANANA",S67,IF(AND(OR(G67="Formally Documented",G67="Informally Documented"),H67="Not Implemented"),0.5*AVERAGE(S67:V67),AVERAGE(S67:V67))) -> 1 | L67: =IF(AND(D67="K",K67=1),'Maturity Rating'!$E$8,IF(K67="NA",K67,IF(D67="K",K67*'Maturity Rating'!$E$7,K67))) -> 0.8 | S67: =VLOOKUP(G67,'Maturity Rating'!A$2:B$5,2,FALSE) -> 1 | T67: =VLOOKUP(H67,'Maturity Rating'!A$8:B$11,2,FALSE) -> NA | U67: =VLOOKUP(I67,'Maturity Rating'!A$14:B$17,2,FALSE) -> NA | V67: =VLOOKUP(J67,'Maturity Rating'!A$20:B$23,2,FALSE) -> NA | W67: =CONCATENATE(S67,T67,U67,V67) -> 1NANANA
A68: 5.66 | E68: The changes in the database is logged and should be performed by authorized individuals only | F68: Preventive | G68: Not Documented | H68: Not Applicable | I68: Not Applicable | J68: Not Applicable | K68: =IF(W68="NANANANA",S68,IF(AND(OR(G68="Formally Documented",G68="Informally Documented"),H68="Not Implemented"),0.5*AVERAGE(S68:V68),AVERAGE(S68:V68))) -> 1 | L68: =IF(AND(D68="K",K68=1),'Maturity Rating'!$E$8,IF(K68="NA",K68,IF(D68="K",K68*'Maturity Rating'!$E$7,K68))) -> 1 | S68: =VLOOKUP(G68,'Maturity Rating'!A$2:B$5,2,FALSE) -> 1 | T68: =VLOOKUP(H68,'Maturity Rating'!A$8:B$11,2,FALSE) -> NA | U68: =VLOOKUP(I68,'Maturity Rating'!A$14:B$17,2,FALSE) -> NA | V68: =VLOOKUP(J68,'Maturity Rating'!A$20:B$23,2,FALSE) -> NA | W68: =CONCATENATE(S68,T68,U68,V68) -> 1NANANA
A69: 5.67 | E69: Database backups are performed for critical systems as per predefined schedules. | F69: Detective | G69: Not Documented | H69: Not Applicable | I69: Not Applicable | J69: Not Applicable | K69: =IF(W69="NANANANA",S69,IF(AND(OR(G69="Formally Documented",G69="Informally Documented"),H69="Not Implemented"),0.5*AVERAGE(S69:V69),AVERAGE(S69:V69))) -> 1 | L69: =IF(AND(D69="K",K69=1),'Maturity Rating'!$E$8,IF(K69="NA",K69,IF(D69="K",K69*'Maturity Rating'!$E$7,K69))) -> 1 | S69: =VLOOKUP(G69,'Maturity Rating'!A$2:B$5,2,FALSE) -> 1 | T69: =VLOOKUP(H69,'Maturity Rating'!A$8:B$11,2,FALSE) -> NA | U69: =VLOOKUP(I69,'Maturity Rating'!A$14:B$17,2,FALSE) -> NA | V69: =VLOOKUP(J69,'Maturity Rating'!A$20:B$23,2,FALSE) -> NA | W69: =CONCATENATE(S69,T69,U69,V69) -> 1NANANA
A70: 5.68 | B70: Data Security | C70: To ensure controls are in place to identify & protect critical business data and to prevent its unauthorized exfiltration | E70: There is a defined and documented process for managing data security in organization | F70: Preventive | G70: Not Documented | H70: Not Applicable | I70: Not Applicable | J70: Not Applicable | K70: =IF(W70="NANANANA",S70,IF(AND(OR(G70="Formally Documented",G70="Informally Documented"),H70="Not Implemented"),0.5*AVERAGE(S70:V70),AVERAGE(S70:V70))) -> 1 | L70: =IF(AND(D70="K",K70=1),'Maturity Rating'!$E$8,IF(K70="NA",K70,IF(D70="K",K70*'Maturity Rating'!$E$7,K70))) -> 1 | M70: =IF(X70="NANANANANANANA",K70,AVERAGE(L70:L76)) -> 1.2 | N70: =IF(M70<1.1,1,IF(M70="NA",M70,(MIN(5,M70/3*5)))) -> 2 | O70: =IF(N70="NA",N70,VLOOKUP(Q70,'Maturity Rating'!G4:H8,2,FALSE)) -> Partial | Q70: =IF(N70="NA",N70,ROUNDDOWN(N70,0)) -> 2 | S70: =VLOOKUP(G70,'Maturity Rating'!A$2:B$5,2,FALSE) -> 1 | T70: =VLOOKUP(H70,'Maturity Rating'!A$8:B$11,2,FALSE) -> NA | U70: =VLOOKUP(I70,'Maturity Rating'!A$14:B$17,2,FALSE) -> NA | V70: =VLOOKUP(J70,'Maturity Rating'!A$20:B$23,2,FALSE) -> NA | W70: =CONCATENATE(S70,T70,U70,V70) -> 1NANANA | X70: =CONCATENATE(L70,L71,L72,L73,L74,L76) -> 112.4111
A71: 5.69 | E71: The documents are reviewed, updated and approved as per the defined frequency in the policy/ procedure. | F71: Preventive | G71: Not Documented | H71: Not Applicable | I71: Not Applicable | J71: Not Applicable | K71: =IF(W71="NANANANA",S71,IF(AND(OR(G71="Formally Documented",G71="Informally Documented"),H71="Not Implemented"),0.5*AVERAGE(S71:V71),AVERAGE(S71:V71))) -> 1 | L71: =IF(AND(D71="K",K71=1),'Maturity Rating'!$E$8,IF(K71="NA",K71,IF(D71="K",K71*'Maturity Rating'!$E$7,K71))) -> 1 | S71: =VLOOKUP(G71,'Maturity Rating'!A$2:B$5,2,FALSE) -> 1 | T71: =VLOOKUP(H71,'Maturity Rating'!A$8:B$11,2,FALSE) -> NA | U71: =VLOOKUP(I71,'Maturity Rating'!A$14:B$17,2,FALSE) -> NA | V71: =VLOOKUP(J71,'Maturity Rating'!A$20:B$23,2,FALSE) -> NA | W71: =CONCATENATE(S71,T71,U71,V71) -> 1NANANA
A72: 5. 70 | D72: K | E72: Data flow analysis or equivalent process is performed for identification of critical data | F72: Detective | G72: Informally Documented | H72: 0 - 50% Implemented | I72: Partially Automated | J72: Partially Monitored & Reviewed | K72: =IF(W72="NANANANA",S72,IF(AND(OR(G72="Formally Documented",G72="Informally Documented"),H72="Not Implemented"),0.5*AVERAGE(S72:V72),AVERAGE(S72:V72))) -> 2 | L72: =IF(AND(D72="K",K72=1),'Maturity Rating'!$E$8,IF(K72="NA",K72,IF(D72="K",K72*'Maturity Rating'!$E$7,K72))) -> 2.4 | S72: =VLOOKUP(G72,'Maturity Rating'!A$2:B$5,2,FALSE) -> 2 | T72: =VLOOKUP(H72,'Maturity Rating'!A$8:B$11,2,FALSE) -> 2 | U72: =VLOOKUP(I72,'Maturity Rating'!A$14:B$17,2,FALSE) -> 2 | V72: =VLOOKUP(J72,'Maturity Rating'!A$20:B$23,2,FALSE) -> 2 | W72: =CONCATENATE(S72,T72,U72,V72) -> 2222
A73: 5.71 | E73: There is a defined process to classify data based on its criticality and confidentiality. | F73: Preventive | G73: Not Documented | H73: Not Applicable | I73: Not Applicable | J73: Not Applicable | K73: =IF(W73="NANANANA",S73,IF(AND(OR(G73="Formally Documented",G73="Informally Documented"),H73="Not Implemented"),0.5*AVERAGE(S73:V73),AVERAGE(S73:V73))) -> 1 | L73: =IF(AND(D73="K",K73=1),'Maturity Rating'!$E$8,IF(K73="NA",K73,IF(D73="K",K73*'Maturity Rating'!$E$7,K73))) -> 1 | S73: =VLOOKUP(G73,'Maturity Rating'!A$2:B$5,2,FALSE) -> 1 | T73: =VLOOKUP(H73,'Maturity Rating'!A$8:B$11,2,FALSE) -> NA | U73: =VLOOKUP(I73,'Maturity Rating'!A$14:B$17,2,FALSE) -> NA | V73: =VLOOKUP(J73,'Maturity Rating'!A$20:B$23,2,FALSE) -> NA | W73: =CONCATENATE(S73,T73,U73,V73) -> 1NANANA
A74: 5.72 | E74: Controls are implemented to prevent unauthorized exfiltration of confidential data out of the organization | F74: Preventive | G74: Not Documented | H74: Not Applicable | I74: Not Applicable | J74: Not Applicable | K74: =IF(W74="NANANANA",S74,IF(AND(OR(G74="Formally Documented",G74="Informally Documented"),H74="Not Implemented"),0.5*AVERAGE(S74:V74),AVERAGE(S74:V74))) -> 1 | L74: =IF(AND(D74="K",K74=1),'Maturity Rating'!$E$8,IF(K74="NA",K74,IF(D74="K",K74*'Maturity Rating'!$E$7,K74))) -> 1 | S74: =VLOOKUP(G74,'Maturity Rating'!A$2:B$5,2,FALSE) -> 1 | T74: =VLOOKUP(H74,'Maturity Rating'!A$8:B$11,2,FALSE) -> NA | U74: =VLOOKUP(I74,'Maturity Rating'!A$14:B$17,2,FALSE) -> NA | V74: =VLOOKUP(J74,'Maturity Rating'!A$20:B$23,2,FALSE) -> NA | W74: =CONCATENATE(S74,T74,U74,V74) -> 1NANANA
A75: 5.73 | E75: Sensitive files are watermarked with users’ usernames, timestamps & disclaimer | F75: Preventive | G75: Not Documented | H75: Not Applicable | I75: Not Applicable | J75: Not Applicable | K75: =IF(W75="NANANANA",S75,IF(AND(OR(G75="Formally Documented",G75="Informally Documented"),H75="Not Implemented"),0.5*AVERAGE(S75:V75),AVERAGE(S75:V75))) -> 1 | L75: =IF(AND(D75="K",K75=1),'Maturity Rating'!$E$8,IF(K75="NA",K75,IF(D75="K",K75*'Maturity Rating'!$E$7,K75))) -> 1 | S75: =VLOOKUP(G75,'Maturity Rating'!A$2:B$5,2,FALSE) -> 1 | T75: =VLOOKUP(H75,'Maturity Rating'!A$8:B$11,2,FALSE) -> NA | U75: =VLOOKUP(I75,'Maturity Rating'!A$14:B$17,2,FALSE) -> NA | V75: =VLOOKUP(J75,'Maturity Rating'!A$20:B$23,2,FALSE) -> NA | W75: =CONCATENATE(S75,T75,U75,V75) -> 1NANANA
A76: 5.74 | E76: Rules configured on DLP for identification of critical business data should be periodically reviewed for completeness and reduction of false positives | F76: Preventive | G76: Not Documented | H76: Not Applicable | I76: Not Applicable | J76: Not Applicable | K76: =IF(W76="NANANANA",S76,IF(AND(OR(G76="Formally Documented",G76="Informally Documented"),H76="Not Implemented"),0.5*AVERAGE(S76:V76),AVERAGE(S76:V76))) -> 1 | L76: =IF(AND(D76="K",K76=1),'Maturity Rating'!$E$8,IF(K76="NA",K76,IF(D76="K",K76*'Maturity Rating'!$E$7,K76))) -> 1 | S76: =VLOOKUP(G76,'Maturity Rating'!A$2:B$5,2,FALSE) -> 1 | T76: =VLOOKUP(H76,'Maturity Rating'!A$8:B$11,2,FALSE) -> NA | U76: =VLOOKUP(I76,'Maturity Rating'!A$14:B$17,2,FALSE) -> NA | V76: =VLOOKUP(J76,'Maturity Rating'!A$20:B$23,2,FALSE) -> NA | W76: =CONCATENATE(S76,T76,U76,V76) -> 1NANANA
A77: 5.75 | B77: Virtualization Security | C77: To ensure that there are effective measures in place for protection of a virtualization environment | E77: Only authorized administrative personnel should have physical access to the host system to prevent unauthorized changes. | F77: Preventive | G77: Formally Documented | H77: 51 - 100% Implemented | I77: Automated | J77: Monitored & Reviewed | K77: =IF(W77="NANANANA",S77,IF(AND(OR(G77="Formally Documented",G77="Informally Documented"),H77="Not Implemented"),0.5*AVERAGE(S77:V77),AVERAGE(S77:V77))) -> 3 | L77: =IF(AND(D77="K",K77=1),'Maturity Rating'!$E$8,IF(K77="NA",K77,IF(D77="K",K77*'Maturity Rating'!$E$7,K77))) -> 3 | M77: =IF(X77="NANANANANANANANANANANA",K77,AVERAGE(L77:L89)) -> 1.1384615 | N77: =IF(M77<1.1,1,IF(M77="NA",M77,(MIN(5,M77/3*5)))) -> 1.8974359 | O77: =IF(N77="NA",N77,VLOOKUP(Q77,'Maturity Rating'!G4:H8,2,FALSE)) -> Initial | Q77: =IF(N77="NA",N77,ROUNDDOWN(N77,0)) -> 1 | S77: =VLOOKUP(G77,'Maturity Rating'!A$2:B$5,2,FALSE) -> 3 | T77: =VLOOKUP(H77,'Maturity Rating'!A$8:B$11,2,FALSE) -> 3 | U77: =VLOOKUP(I77,'Maturity Rating'!A$14:B$17,2,FALSE) -> 3 | V77: =VLOOKUP(J77,'Maturity Rating'!A$20:B$23,2,FALSE) -> 3 | W77: =CONCATENATE(S77,T77,U77,V77) -> 3333 | X77: =CONCATENATE(L77,L78,L79,L80,L81,L82,L83,L84,L85,L86,L87,L88,L89) -> 31110.811111111
A78: 5.76 | E78: Set limits on the use of resources (e.g., processors, memory, disk space, virtual network interfaces) by each VM, to prevent a single VM from monopolizing resources on a system. | F78: Detective | G78: Not Documented | H78: Not Applicable | I78: Not Applicable | J78: Not Applicable | K78: =IF(W78="NANANANA",S78,IF(AND(OR(G78="Formally Documented",G78="Informally Documented"),H78="Not Implemented"),0.5*AVERAGE(S78:V78),AVERAGE(S78:V78))) -> 1 | L78: =IF(AND(D78="K",K78=1),'Maturity Rating'!$E$8,IF(K78="NA",K78,IF(D78="K",K78*'Maturity Rating'!$E$7,K78))) -> 1 | S78: =VLOOKUP(G78,'Maturity Rating'!A$2:B$5,2,FALSE) -> 1 | T78: =VLOOKUP(H78,'Maturity Rating'!A$8:B$11,2,FALSE) -> NA | U78: =VLOOKUP(I78,'Maturity Rating'!A$14:B$17,2,FALSE) -> NA | V78: =VLOOKUP(J78,'Maturity Rating'!A$20:B$23,2,FALSE) -> NA | W78: =CONCATENATE(S78,T78,U78,V78) -> 1NANANA
A79: 5.77 | E79: Ensure that host and guests use synchronized time | F79: Preventive | G79: Not Documented | H79: Not Applicable | I79: Not Applicable | J79: Not Applicable | K79: =IF(W79="NANANANA",S79,IF(AND(OR(G79="Formally Documented",G79="Informally Documented"),H79="Not Implemented"),0.5*AVERAGE(S79:V79),AVERAGE(S79:V79))) -> 1 | L79: =IF(AND(D79="K",K79=1),'Maturity Rating'!$E$8,IF(K79="NA",K79,IF(D79="K",K79*'Maturity Rating'!$E$7,K79))) -> 1 | S79: =VLOOKUP(G79,'Maturity Rating'!A$2:B$5,2,FALSE) -> 1 | T79: =VLOOKUP(H79,'Maturity Rating'!A$8:B$11,2,FALSE) -> NA | U79: =VLOOKUP(I79,'Maturity Rating'!A$14:B$17,2,FALSE) -> NA | V79: =VLOOKUP(J79,'Maturity Rating'!A$20:B$23,2,FALSE) -> NA | W79: =CONCATENATE(S79,T79,U79,V79) -> 1NANANA
A80: 5.78 | E80: Host OS must be patched regularly and in a timely fashion to ensure that the host OS is protecting the system and guest OSs properly. | F80: Preventive | G80: Not Documented | H80: Not Applicable | I80: Not Applicable | J80: Not Applicable | K80: =IF(W80="NANANANA",S80,IF(AND(OR(G80="Formally Documented",G80="Informally Documented"),H80="Not Implemented"),0.5*AVERAGE(S80:V80),AVERAGE(S80:V80))) -> 1 | L80: =IF(AND(D80="K",K80=1),'Maturity Rating'!$E$8,IF(K80="NA",K80,IF(D80="K",K80*'Maturity Rating'!$E$7,K80))) -> 1 | S80: =VLOOKUP(G80,'Maturity Rating'!A$2:B$5,2,FALSE) -> 1 | T80: =VLOOKUP(H80,'Maturity Rating'!A$8:B$11,2,FALSE) -> NA | U80: =VLOOKUP(I80,'Maturity Rating'!A$14:B$17,2,FALSE) -> NA | V80: =VLOOKUP(J80,'Maturity Rating'!A$20:B$23,2,FALSE) -> NA | W80: =CONCATENATE(S80,T80,U80,V80) -> 1NANANA
A81: 5.79 | D81: K | E81: Host OS should be hardened as per the hardening guidelines | F81: Detective | G81: Not Documented | H81: Not Applicable | I81: Not Applicable | J81: Not Applicable | K81: =IF(W81="NANANANA",S81,IF(AND(OR(G81="Formally Documented",G81="Informally Documented"),H81="Not Implemented"),0.5*AVERAGE(S81:V81),AVERAGE(S81:V81))) -> 1 | L81: =IF(AND(D81="K",K81=1),'Maturity Rating'!$E$8,IF(K81="NA",K81,IF(D81="K",K81*'Maturity Rating'!$E$7,K81))) -> 0.8 | S81: =VLOOKUP(G81,'Maturity Rating'!A$2:B$5,2,FALSE) -> 1 | T81: =VLOOKUP(H81,'Maturity Rating'!A$8:B$11,2,FALSE) -> NA | U81: =VLOOKUP(I81,'Maturity Rating'!A$14:B$17,2,FALSE) -> NA | V81: =VLOOKUP(J81,'Maturity Rating'!A$20:B$23,2,FALSE) -> NA | W81: =CONCATENATE(S81,T81,U81,V81) -> 1NANANA
A82: 5. 80 | E82: Logging should be enabled on all host and VMs. Also logs should be retained as per the retention policy | F82: Detective | G82: Not Documented | H82: Not Applicable | I82: Not Applicable | J82: Not Applicable | K82: =IF(W82="NANANANA",S82,IF(AND(OR(G82="Formally Documented",G82="Informally Documented"),H82="Not Implemented"),0.5*AVERAGE(S82:V82),AVERAGE(S82:V82))) -> 1 | L82: =IF(AND(D82="K",K82=1),'Maturity Rating'!$E$8,IF(K82="NA",K82,IF(D82="K",K82*'Maturity Rating'!$E$7,K82))) -> 1 | S82: =VLOOKUP(G82,'Maturity Rating'!A$2:B$5,2,FALSE) -> 1 | T82: =VLOOKUP(H82,'Maturity Rating'!A$8:B$11,2,FALSE) -> NA | U82: =VLOOKUP(I82,'Maturity Rating'!A$14:B$17,2,FALSE) -> NA | V82: =VLOOKUP(J82,'Maturity Rating'!A$20:B$23,2,FALSE) -> NA | W82: =CONCATENATE(S82,T82,U82,V82) -> 1NANANA
A83: 5.81 | E83: All hosts must be integrated with central log management | F83: Preventive | G83: Not Documented | H83: Not Applicable | I83: Not Applicable | J83: Not Applicable | K83: =IF(W83="NANANANA",S83,IF(AND(OR(G83="Formally Documented",G83="Informally Documented"),H83="Not Implemented"),0.5*AVERAGE(S83:V83),AVERAGE(S83:V83))) -> 1 | L83: =IF(AND(D83="K",K83=1),'Maturity Rating'!$E$8,IF(K83="NA",K83,IF(D83="K",K83*'Maturity Rating'!$E$7,K83))) -> 1 | S83: =VLOOKUP(G83,'Maturity Rating'!A$2:B$5,2,FALSE) -> 1 | T83: =VLOOKUP(H83,'Maturity Rating'!A$8:B$11,2,FALSE) -> NA | U83: =VLOOKUP(I83,'Maturity Rating'!A$14:B$17,2,FALSE) -> NA | V83: =VLOOKUP(J83,'Maturity Rating'!A$20:B$23,2,FALSE) -> NA | W83: =CONCATENATE(S83,T83,U83,V83) -> 1NANANA
A84: 5.82 | E84: Role based access should be provided for management of host and VMs. | F84: Preventive | G84: Not Documented | H84: Not Applicable | I84: Not Applicable | J84: Not Applicable | K84: =IF(W84="NANANANA",S84,IF(AND(OR(G84="Formally Documented",G84="Informally Documented"),H84="Not Implemented"),0.5*AVERAGE(S84:V84),AVERAGE(S84:V84))) -> 1 | L84: =IF(AND(D84="K",K84=1),'Maturity Rating'!$E$8,IF(K84="NA",K84,IF(D84="K",K84*'Maturity Rating'!$E$7,K84))) -> 1 | S84: =VLOOKUP(G84,'Maturity Rating'!A$2:B$5,2,FALSE) -> 1 | T84: =VLOOKUP(H84,'Maturity Rating'!A$8:B$11,2,FALSE) -> NA | U84: =VLOOKUP(I84,'Maturity Rating'!A$14:B$17,2,FALSE) -> NA | V84: =VLOOKUP(J84,'Maturity Rating'!A$20:B$23,2,FALSE) -> NA | W84: =CONCATENATE(S84,T84,U84,V84) -> 1NANANA
A85: 5.83 | E85: Vulnerability Assessment should be performed and identified gaps should be remediated before on-boarding in production | F85: Preventive | G85: Not Documented | H85: Not Applicable | I85: Not Applicable | J85: Not Applicable | K85: =IF(W85="NANANANA",S85,IF(AND(OR(G85="Formally Documented",G85="Informally Documented"),H85="Not Implemented"),0.5*AVERAGE(S85:V85),AVERAGE(S85:V85))) -> 1 | L85: =IF(AND(D85="K",K85=1),'Maturity Rating'!$E$8,IF(K85="NA",K85,IF(D85="K",K85*'Maturity Rating'!$E$7,K85))) -> 1 | S85: =VLOOKUP(G85,'Maturity Rating'!A$2:B$5,2,FALSE) -> 1 | T85: =VLOOKUP(H85,'Maturity Rating'!A$8:B$11,2,FALSE) -> NA | U85: =VLOOKUP(I85,'Maturity Rating'!A$14:B$17,2,FALSE) -> NA | V85: =VLOOKUP(J85,'Maturity Rating'!A$20:B$23,2,FALSE) -> NA | W85: =CONCATENATE(S85,T85,U85,V85) -> 1NANANA
A86: 5.84 | E86: There is authorized and hardened OS image deployed on all systems(server) | F86: Preventive | G86: Not Documented | H86: Not Applicable | I86: Not Applicable | J86: Not Applicable | K86: =IF(W86="NANANANA",S86,IF(AND(OR(G86="Formally Documented",G86="Informally Documented"),H86="Not Implemented"),0.5*AVERAGE(S86:V86),AVERAGE(S86:V86))) -> 1 | L86: =IF(AND(D86="K",K86=1),'Maturity Rating'!$E$8,IF(K86="NA",K86,IF(D86="K",K86*'Maturity Rating'!$E$7,K86))) -> 1 | S86: =VLOOKUP(G86,'Maturity Rating'!A$2:B$5,2,FALSE) -> 1 | T86: =VLOOKUP(H86,'Maturity Rating'!A$8:B$11,2,FALSE) -> NA | U86: =VLOOKUP(I86,'Maturity Rating'!A$14:B$17,2,FALSE) -> NA | V86: =VLOOKUP(J86,'Maturity Rating'!A$20:B$23,2,FALSE) -> NA | W86: =CONCATENATE(S86,T86,U86,V86) -> 1NANANA
A87: 5.85 | E87: Clipboard access from VM to local machine should be disabled | F87: Preventive | G87: Not Documented | H87: Not Applicable | I87: Not Applicable | J87: Not Applicable | K87: =IF(W87="NANANANA",S87,IF(AND(OR(G87="Formally Documented",G87="Informally Documented"),H87="Not Implemented"),0.5*AVERAGE(S87:V87),AVERAGE(S87:V87))) -> 1 | L87: =IF(AND(D87="K",K87=1),'Maturity Rating'!$E$8,IF(K87="NA",K87,IF(D87="K",K87*'Maturity Rating'!$E$7,K87))) -> 1 | S87: =VLOOKUP(G87,'Maturity Rating'!A$2:B$5,2,FALSE) -> 1 | T87: =VLOOKUP(H87,'Maturity Rating'!A$8:B$11,2,FALSE) -> NA | U87: =VLOOKUP(I87,'Maturity Rating'!A$14:B$17,2,FALSE) -> NA | V87: =VLOOKUP(J87,'Maturity Rating'!A$20:B$23,2,FALSE) -> NA | W87: =CONCATENATE(S87,T87,U87,V87) -> 1NANANA
A88: 5.86 | E88: All changes made to host and VMs should be carried out as per the change management policy | F88: Preventive | G88: Not Documented | H88: Not Applicable | I88: Not Applicable | J88: Not Applicable | K88: =IF(W88="NANANANA",S88,IF(AND(OR(G88="Formally Documented",G88="Informally Documented"),H88="Not Implemented"),0.5*AVERAGE(S88:V88),AVERAGE(S88:V88))) -> 1 | L88: =IF(AND(D88="K",K88=1),'Maturity Rating'!$E$8,IF(K88="NA",K88,IF(D88="K",K88*'Maturity Rating'!$E$7,K88))) -> 1 | S88: =VLOOKUP(G88,'Maturity Rating'!A$2:B$5,2,FALSE) -> 1 | T88: =VLOOKUP(H88,'Maturity Rating'!A$8:B$11,2,FALSE) -> NA | U88: =VLOOKUP(I88,'Maturity Rating'!A$14:B$17,2,FALSE) -> NA | V88: =VLOOKUP(J88,'Maturity Rating'!A$20:B$23,2,FALSE) -> NA | W88: =CONCATENATE(S88,T88,U88,V88) -> 1NANANA
A89: 5.87 | E89: File sharing between host and guest OS should be disabled | F89: Preventive | G89: Not Documented | H89: Not Applicable | I89: Not Applicable | J89: Not Applicable | K89: =IF(W89="NANANANA",S89,IF(AND(OR(G89="Formally Documented",G89="Informally Documented"),H89="Not Implemented"),0.5*AVERAGE(S89:V89),AVERAGE(S89:V89))) -> 1 | L89: =IF(AND(D89="K",K89=1),'Maturity Rating'!$E$8,IF(K89="NA",K89,IF(D89="K",K89*'Maturity Rating'!$E$7,K89))) -> 1 | S89: =VLOOKUP(G89,'Maturity Rating'!A$2:B$5,2,FALSE) -> 1 | T89: =VLOOKUP(H89,'Maturity Rating'!A$8:B$11,2,FALSE) -> NA | U89: =VLOOKUP(I89,'Maturity Rating'!A$14:B$17,2,FALSE) -> NA | V89: =VLOOKUP(J89,'Maturity Rating'!A$20:B$23,2,FALSE) -> NA | W89: =CONCATENATE(S89,T89,U89,V89) -> 1NANANA
A90: 5.88 | B90: Email Security | C90: To ensure that there are effective controls in place for protection data getting exfilitrated through email | E90: Anti-spam related controls such as spam filtering, spoofing detection software should be implemented | F90: Preventive | G90: Formally Documented | H90: 51 - 100% Implemented | I90: Automated | J90: Monitored & Reviewed | K90: =IF(W90="NANANANA",S90,IF(AND(OR(G90="Formally Documented",G90="Informally Documented"),H90="Not Implemented"),0.5*AVERAGE(S90:V90),AVERAGE(S90:V90))) -> 3 | L90: =IF(AND(D90="K",K90=1),'Maturity Rating'!$E$8,IF(K90="NA",K90,IF(D90="K",K90*'Maturity Rating'!$E$7,K90))) -> 3 | M90: =IF(X90="NANANANANANANANANANANA",K90,AVERAGE(L90:L95)) -> 2.2916667 | N90: =IF(M90<1.1,1,IF(M90="NA",M90,(MIN(5,M90/3*5)))) -> 3.8194444 | O90: =IF(N90="NA",N90,VLOOKUP(Q90,'Maturity Rating'!G4:H8,2,FALSE)) -> Defined | Q90: =IF(N90="NA",N90,ROUNDDOWN(N90,0)) -> 3 | S90: =VLOOKUP(G90,'Maturity Rating'!A$2:B$5,2,FALSE) -> 3 | T90: =VLOOKUP(H90,'Maturity Rating'!A$8:B$11,2,FALSE) -> 3 | U90: =VLOOKUP(I90,'Maturity Rating'!A$14:B$17,2,FALSE) -> 3 | V90: =VLOOKUP(J90,'Maturity Rating'!A$20:B$23,2,FALSE) -> 3 | W90: =CONCATENATE(S90,T90,U90,V90) -> 3333 | X90: =CONCATENATE(L90,L91,L92,L93,L94,L95) -> 32.753113
A91: 5.89 | E91: Emails are retained post separation as per the defined frequency in the policy/ procedure. | F91: Preventive | G91: Formally Documented | H91: 51 - 100% Implemented | I91: Partially Automated | J91: Monitored & Reviewed | K91: =IF(W91="NANANANA",S91,IF(AND(OR(G91="Formally Documented",G91="Informally Documented"),H91="Not Implemented"),0.5*AVERAGE(S91:V91),AVERAGE(S91:V91))) -> 2.75 | L91: =IF(AND(D91="K",K91=1),'Maturity Rating'!$E$8,IF(K91="NA",K91,IF(D91="K",K91*'Maturity Rating'!$E$7,K91))) -> 2.75 | S91: =VLOOKUP(G91,'Maturity Rating'!A$2:B$5,2,FALSE) -> 3 | T91: =VLOOKUP(H91,'Maturity Rating'!A$8:B$11,2,FALSE) -> 3 | U91: =VLOOKUP(I91,'Maturity Rating'!A$14:B$17,2,FALSE) -> 2 | V91: =VLOOKUP(J91,'Maturity Rating'!A$20:B$23,2,FALSE) -> 3 | W91: =CONCATENATE(S91,T91,U91,V91) -> 3323
A92: 5. 90 | E92: Appropriate controls are implemented for email relay server to restrict unauthorized usage. | F92: Preventive | G92: Formally Documented | H92: 51 - 100% Implemented | I92: Automated | J92: Monitored & Reviewed | K92: =IF(W92="NANANANA",S92,IF(AND(OR(G92="Formally Documented",G92="Informally Documented"),H92="Not Implemented"),0.5*AVERAGE(S92:V92),AVERAGE(S92:V92))) -> 3 | L92: =IF(AND(D92="K",K92=1),'Maturity Rating'!$E$8,IF(K92="NA",K92,IF(D92="K",K92*'Maturity Rating'!$E$7,K92))) -> 3 | S92: =VLOOKUP(G92,'Maturity Rating'!A$2:B$5,2,FALSE) -> 3 | T92: =VLOOKUP(H92,'Maturity Rating'!A$8:B$11,2,FALSE) -> 3 | U92: =VLOOKUP(I92,'Maturity Rating'!A$14:B$17,2,FALSE) -> 3 | V92: =VLOOKUP(J92,'Maturity Rating'!A$20:B$23,2,FALSE) -> 3 | W92: =CONCATENATE(S92,T92,U92,V92) -> 3333
A93: 5.91 | E93: OWA controls are implemented such as MFA, conditional access for O365 and on premise. | F93: Preventive | G93: Not Documented | H93: Not Applicable | I93: Not Applicable | J93: Not Applicable | K93: =IF(W93="NANANANA",S93,IF(AND(OR(G93="Formally Documented",G93="Informally Documented"),H93="Not Implemented"),0.5*AVERAGE(S93:V93),AVERAGE(S93:V93))) -> 1 | L93: =IF(AND(D93="K",K93=1),'Maturity Rating'!$E$8,IF(K93="NA",K93,IF(D93="K",K93*'Maturity Rating'!$E$7,K93))) -> 1 | S93: =VLOOKUP(G93,'Maturity Rating'!A$2:B$5,2,FALSE) -> 1 | T93: =VLOOKUP(H93,'Maturity Rating'!A$8:B$11,2,FALSE) -> NA | U93: =VLOOKUP(I93,'Maturity Rating'!A$14:B$17,2,FALSE) -> NA | V93: =VLOOKUP(J93,'Maturity Rating'!A$20:B$23,2,FALSE) -> NA | W93: =CONCATENATE(S93,T93,U93,V93) -> 1NANANA
A94: 5.92 | E94: MFA is implemented for email (both for webmail and Mobile email service) | F94: Preventive | G94: Not Documented | H94: Not Applicable | I94: Not Applicable | J94: Not Applicable | K94: =IF(W94="NANANANA",S94,IF(AND(OR(G94="Formally Documented",G94="Informally Documented"),H94="Not Implemented"),0.5*AVERAGE(S94:V94),AVERAGE(S94:V94))) -> 1 | L94: =IF(AND(D94="K",K94=1),'Maturity Rating'!$E$8,IF(K94="NA",K94,IF(D94="K",K94*'Maturity Rating'!$E$7,K94))) -> 1 | S94: =VLOOKUP(G94,'Maturity Rating'!A$2:B$5,2,FALSE) -> 1 | T94: =VLOOKUP(H94,'Maturity Rating'!A$8:B$11,2,FALSE) -> NA | U94: =VLOOKUP(I94,'Maturity Rating'!A$14:B$17,2,FALSE) -> NA | V94: =VLOOKUP(J94,'Maturity Rating'!A$20:B$23,2,FALSE) -> NA | W94: =CONCATENATE(S94,T94,U94,V94) -> 1NANANA
A95: 5.93 | E95: DMARC/ Anti-spoofing related controls should be implemented in email security | F95: Preventive | G95: Formally Documented | H95: 51 - 100% Implemented | I95: Automated | J95: Monitored & Reviewed | K95: =IF(W95="NANANANA",S95,IF(AND(OR(G95="Formally Documented",G95="Informally Documented"),H95="Not Implemented"),0.5*AVERAGE(S95:V95),AVERAGE(S95:V95))) -> 3 | L95: =IF(AND(D95="K",K95=1),'Maturity Rating'!$E$8,IF(K95="NA",K95,IF(D95="K",K95*'Maturity Rating'!$E$7,K95))) -> 3 | S95: =VLOOKUP(G95,'Maturity Rating'!A$2:B$5,2,FALSE) -> 3 | T95: =VLOOKUP(H95,'Maturity Rating'!A$8:B$11,2,FALSE) -> 3 | U95: =VLOOKUP(I95,'Maturity Rating'!A$14:B$17,2,FALSE) -> 3 | V95: =VLOOKUP(J95,'Maturity Rating'!A$20:B$23,2,FALSE) -> 3 | W95: =CONCATENATE(S95,T95,U95,V95) -> 3333

Sheet Emerging Technology
C1: Average Domain Rating | E1: =IF(F1="NA","Not Applicable",VLOOKUP(T1,'Maturity Rating'!G4:H8,2,FALSE)) -> Repeatable | F1: =IF(U1="NANANANA","NA",AVERAGE(N4:N28)) -> 4.3279672 | T1: =ROUNDDOWN(F1,0) -> 4 | U1: =CONCATENATE(N4,N7,N10,N17) -> 553.944444444444443.36742424242424
A3: S. No. | B3: High Level Description | C3: Control Description | D3: Identified Key Controls (K) | E3: Control | F3: Preventive/ Detective/Corrective | G3: Documentation | H3: Implementation | I3: Automation | J3: Monitor & Review | K3: Control Rating | L3: Rating with Key controls weightage | M3: Average Rating | N3: Maturity Rating (1 - 5) | O3: Category | S3: Doc | T3: Impl | U3: Auto | V3: Review
A4: 9.1 | B4: Policy & Procedure | C4: Policy is present to define the organizations security controls and to formalize the governance of the emerging technologies | D4: K | E4: There a defined process of identifying and implementing emerging technologies | F4: Preventive | G4: Formally Documented | H4: 51 - 100% Implemented | I4: Automated | J4: Monitored & Reviewed | K4: =IF(W4="NANANANA",S4,IF(AND(OR(G4="Formally Documented",G4="Informally Documented"),H4="Not Implemented"),0.5*AVERAGE(S4:V4),AVERAGE(S4:V4))) -> 3 | L4: =IF(AND(D4="K",K4=1),'Maturity Rating'!$E$8,IF(K4="NA",K4,IF(D4="K",K4*'Maturity Rating'!$E$7,K4))) -> 3.6 | M4: =IF(X4="NANANA",K4,AVERAGE(L4:L6)) -> 3.2 | N4: =IF(M4<1.1,1,IF(M4="NA",M4,(MIN(5,M4/3*5)))) -> 5 | O4: =IF(N4="NA",N4,VLOOKUP(Q4,'Maturity Rating'!G4:H8,2,FALSE)) -> Adaptive | Q4: =IF(N4="NA",N4,ROUNDDOWN(N4,0)) -> 5 | S4: =VLOOKUP(G4,'Maturity Rating'!A$2:B$5,2,FALSE) -> 3 | T4: =VLOOKUP(H4,'Maturity Rating'!A$8:B$11,2,FALSE) -> 3 | U4: =VLOOKUP(I4,'Maturity Rating'!A$14:B$17,2,FALSE) -> 3 | V4: =VLOOKUP(J4,'Maturity Rating'!A$20:B$23,2,FALSE) -> 3 | W4: =CONCATENATE(S4,T4,U4,V4) -> 3333 | X4: =CONCATENATE(L4,L5,L6,) -> 3.633
A5: 9.2 | E5: The documents are reviewed, updated and approved as per the defined frequency in the policy/ procedure. | F5: Preventive | G5: Formally Documented | H5: 51 - 100% Implemented | I5: Automated | J5: Monitored & Reviewed | K5: =IF(W5="NANANANA",S5,IF(AND(OR(G5="Formally Documented",G5="Informally Documented"),H5="Not Implemented"),0.5*AVERAGE(S5:V5),AVERAGE(S5:V5))) -> 3 | L5: =IF(AND(D5="K",K5=1),'Maturity Rating'!$E$8,IF(K5="NA",K5,IF(D5="K",K5*'Maturity Rating'!$E$7,K5))) -> 3 | S5: =VLOOKUP(G5,'Maturity Rating'!A$2:B$5,2,FALSE) -> 3 | T5: =VLOOKUP(H5,'Maturity Rating'!A$8:B$11,2,FALSE) -> 3 | U5: =VLOOKUP(I5,'Maturity Rating'!A$14:B$17,2,FALSE) -> 3 | V5: =VLOOKUP(J5,'Maturity Rating'!A$20:B$23,2,FALSE) -> 3 | W5: =CONCATENATE(S5,T5,U5,V5) -> 3333
A6: 9.3 | E6: The version control of the documents should be maintained | F6: Preventive | G6: Formally Documented | H6: 51 - 100% Implemented | I6: Automated | J6: Monitored & Reviewed | K6: =IF(W6="NANANANA",S6,IF(AND(OR(G6="Formally Documented",G6="Informally Documented"),H6="Not Implemented"),0.5*AVERAGE(S6:V6),AVERAGE(S6:V6))) -> 3 | L6: =IF(AND(D6="K",K6=1),'Maturity Rating'!$E$8,IF(K6="NA",K6,IF(D6="K",K6*'Maturity Rating'!$E$7,K6))) -> 3 | S6: =VLOOKUP(G6,'Maturity Rating'!A$2:B$5,2,FALSE) -> 3 | T6: =VLOOKUP(H6,'Maturity Rating'!A$8:B$11,2,FALSE) -> 3 | U6: =VLOOKUP(I6,'Maturity Rating'!A$14:B$17,2,FALSE) -> 3 | V6: =VLOOKUP(J6,'Maturity Rating'!A$20:B$23,2,FALSE) -> 3 | W6: =CONCATENATE(S6,T6,U6,V6) -> 3333
A7: 9.4 | B7: Ideation | C7: There is a defined process to establish consistency and security in the overall design and ideation of the emerging technologies | E7: Identified technologies are reviewed for their relevance | F7: Detective | G7: Formally Documented | H7: 51 - 100% Implemented | I7: Automated | J7: Monitored & Reviewed | K7: =IF(W7="NANANANA",S7,IF(AND(OR(G7="Formally Documented",G7="Informally Documented"),H7="Not Implemented"),0.5*AVERAGE(S7:V7),AVERAGE(S7:V7))) -> 3 | L7: =IF(AND(D7="K",K7=1),'Maturity Rating'!$E$8,IF(K7="NA",K7,IF(D7="K",K7*'Maturity Rating'!$E$7,K7))) -> 3 | M7: =IF(X7="NANANA",K7,AVERAGE(L7:L9)) -> 3 | N7: =IF(M7<1.1,1,IF(M7="NA",M7,(MIN(5,M7/3*5)))) -> 5 | O7: =IF(N7="NA",N7,VLOOKUP(Q7,'Maturity Rating'!G4:H8,2,FALSE)) -> Adaptive | Q7: =IF(N7="NA",N7,ROUNDDOWN(N7,0)) -> 5 | S7: =VLOOKUP(G7,'Maturity Rating'!A$2:B$5,2,FALSE) -> 3 | T7: =VLOOKUP(H7,'Maturity Rating'!A$8:B$11,2,FALSE) -> 3 | U7: =VLOOKUP(I7,'Maturity Rating'!A$14:B$17,2,FALSE) -> 3 | V7: =VLOOKUP(J7,'Maturity Rating'!A$20:B$23,2,FALSE) -> 3 | W7: =CONCATENATE(S7,T7,U7,V7) -> 3333 | X7: =CONCATENATE(L7,L8,L9,) -> 3NANA
A8: 9.5 | E8: Authorization is acquired from the management for pursuing solution from emerging technologies | F8: Detective | G8: Not Applicable | H8: Not Applicable | I8: Not Applicable | J8: Not Applicable | K8: =IF(W8="NANANANA",S8,IF(AND(OR(G8="Formally Documented",G8="Informally Documented"),H8="Not Implemented"),0.5*AVERAGE(S8:V8),AVERAGE(S8:V8))) -> NA | L8: =IF(AND(D8="K",K8=1),'Maturity Rating'!$E$8,IF(K8="NA",K8,IF(D8="K",K8*'Maturity Rating'!$E$7,K8))) -> NA | S8: =VLOOKUP(G8,'Maturity Rating'!A$2:B$5,2,FALSE) -> NA | T8: =VLOOKUP(H8,'Maturity Rating'!A$8:B$11,2,FALSE) -> NA | U8: =VLOOKUP(I8,'Maturity Rating'!A$14:B$17,2,FALSE) -> NA | V8: =VLOOKUP(J8,'Maturity Rating'!A$20:B$23,2,FALSE) -> NA | W8: =CONCATENATE(S8,T8,U8,V8) -> NANANANA
A9: 9.6 | E9: The approach is documented to track requirements and log outcomes of brainstorming sessions | F9: Detective | G9: Not Applicable | H9: Not Applicable | I9: Not Applicable | J9: Not Applicable | K9: =IF(W9="NANANANA",S9,IF(AND(OR(G9="Formally Documented",G9="Informally Documented"),H9="Not Implemented"),0.5*AVERAGE(S9:V9),AVERAGE(S9:V9))) -> NA | L9: =IF(AND(D9="K",K9=1),'Maturity Rating'!$E$8,IF(K9="NA",K9,IF(D9="K",K9*'Maturity Rating'!$E$7,K9))) -> NA | S9: =VLOOKUP(G9,'Maturity Rating'!A$2:B$5,2,FALSE) -> NA | T9: =VLOOKUP(H9,'Maturity Rating'!A$8:B$11,2,FALSE) -> NA | U9: =VLOOKUP(I9,'Maturity Rating'!A$14:B$17,2,FALSE) -> NA | V9: =VLOOKUP(J9,'Maturity Rating'!A$20:B$23,2,FALSE) -> NA | W9: =CONCATENATE(S9,T9,U9,V9) -> NANANANA
A10: 9.7 | B10: Secure Development | C10: There is a defined process to ensure secure development practices in the implementation and development of emerging technologies | E10: All requirements pertaining to the technology are documented and approved | F10: Preventive | G10: Informally Documented | H10: 0 - 50% Implemented | I10: Partially Automated | J10: Partially Monitored & Reviewed | K10: =IF(W10="NANANANA",S10,IF(AND(OR(G10="Formally Documented",G10="Informally Documented"),H10="Not Implemented"),0.5*AVERAGE(S10:V10),AVERAGE(S10:V10))) -> 2 | L10: =IF(AND(D10="K",K10=1),'Maturity Rating'!$E$8,IF(K10="NA",K10,IF(D10="K",K10*'Maturity Rating'!$E$7,K10))) -> 2 | M10: =IF(X10="NANANANANANANA",K10,AVERAGE(L10:L16)) -> 2.3666667 | N10: =IF(M10<1.1,1,IF(M10="NA",M10,(MIN(5,M10/3*5)))) -> 3.9444444 | O10: =IF(N10="NA",N10,VLOOKUP(Q10,'Maturity Rating'!G4:H8,2,FALSE)) -> Defined | Q10: =IF(N10="NA",N10,ROUNDDOWN(N10,0)) -> 3 | S10: =VLOOKUP(G10,'Maturity Rating'!A$2:B$5,2,FALSE) -> 2 | T10: =VLOOKUP(H10,'Maturity Rating'!A$8:B$11,2,FALSE) -> 2 | U10: =VLOOKUP(I10,'Maturity Rating'!A$14:B$17,2,FALSE) -> 2 | V10: =VLOOKUP(J10,'Maturity Rating'!A$20:B$23,2,FALSE) -> 2 | W10: =CONCATENATE(S10,T10,U10,V10) -> 2222 | X10: =CONCATENATE(L10,L11,L12,L13,L14,L15,L16) -> 232.43NA30.8
A11: 9.8 | E11: All individuals related to the project are aware of their roles and responsibilities | F11: Preventive | G11: Formally Documented | H11: 51 - 100% Implemented | I11: Automated | J11: Monitored & Reviewed | K11: =IF(W11="NANANANA",S11,IF(AND(OR(G11="Formally Documented",G11="Informally Documented"),H11="Not Implemented"),0.5*AVERAGE(S11:V11),AVERAGE(S11:V11))) -> 3 | L11: =IF(AND(D11="K",K11=1),'Maturity Rating'!$E$8,IF(K11="NA",K11,IF(D11="K",K11*'Maturity Rating'!$E$7,K11))) -> 3 | S11: =VLOOKUP(G11,'Maturity Rating'!A$2:B$5,2,FALSE) -> 3 | T11: =VLOOKUP(H11,'Maturity Rating'!A$8:B$11,2,FALSE) -> 3 | U11: =VLOOKUP(I11,'Maturity Rating'!A$14:B$17,2,FALSE) -> 3 | V11: =VLOOKUP(J11,'Maturity Rating'!A$20:B$23,2,FALSE) -> 3 | W11: =CONCATENATE(S11,T11,U11,V11) -> 3333
A12: 9.9 | D12: K | E12: There is robust mechanism to understand and capture data and insights for end users | F12: Preventive | G12: Informally Documented | H12: 0 - 50% Implemented | I12: Partially Automated | J12: Partially Monitored & Reviewed | K12: =IF(W12="NANANANA",S12,IF(AND(OR(G12="Formally Documented",G12="Informally Documented"),H12="Not Implemented"),0.5*AVERAGE(S12:V12),AVERAGE(S12:V12))) -> 2 | L12: =IF(AND(D12="K",K12=1),'Maturity Rating'!$E$8,IF(K12="NA",K12,IF(D12="K",K12*'Maturity Rating'!$E$7,K12))) -> 2.4 | S12: =VLOOKUP(G12,'Maturity Rating'!A$2:B$5,2,FALSE) -> 2 | T12: =VLOOKUP(H12,'Maturity Rating'!A$8:B$11,2,FALSE) -> 2 | U12: =VLOOKUP(I12,'Maturity Rating'!A$14:B$17,2,FALSE) -> 2 | V12: =VLOOKUP(J12,'Maturity Rating'!A$20:B$23,2,FALSE) -> 2 | W12: =CONCATENATE(S12,T12,U12,V12) -> 2222
A13: 9. 10 | E13: Security and privacy is built into each stage of the design | F13: Preventive | G13: Formally Documented | H13: 51 - 100% Implemented | I13: Automated | J13: Monitored & Reviewed | K13: =IF(W13="NANANANA",S13,IF(AND(OR(G13="Formally Documented",G13="Informally Documented"),H13="Not Implemented"),0.5*AVERAGE(S13:V13),AVERAGE(S13:V13))) -> 3 | L13: =IF(AND(D13="K",K13=1),'Maturity Rating'!$E$8,IF(K13="NA",K13,IF(D13="K",K13*'Maturity Rating'!$E$7,K13))) -> 3 | S13: =VLOOKUP(G13,'Maturity Rating'!A$2:B$5,2,FALSE) -> 3 | T13: =VLOOKUP(H13,'Maturity Rating'!A$8:B$11,2,FALSE) -> 3 | U13: =VLOOKUP(I13,'Maturity Rating'!A$14:B$17,2,FALSE) -> 3 | V13: =VLOOKUP(J13,'Maturity Rating'!A$20:B$23,2,FALSE) -> 3 | W13: =CONCATENATE(S13,T13,U13,V13) -> 3333
A14: 9.11 | D14: K | E14: All IP's & contracts are reviewed and corroborated | F14: Preventive | G14: Not Applicable | H14: Not Applicable | I14: Not Applicable | J14: Not Applicable | K14: =IF(W14="NANANANA",S14,IF(AND(OR(G14="Formally Documented",G14="Informally Documented"),H14="Not Implemented"),0.5*AVERAGE(S14:V14),AVERAGE(S14:V14))) -> NA | L14: =IF(AND(D14="K",K14=1),'Maturity Rating'!$E$8,IF(K14="NA",K14,IF(D14="K",K14*'Maturity Rating'!$E$7,K14))) -> NA | S14: =VLOOKUP(G14,'Maturity Rating'!A$2:B$5,2,FALSE) -> NA | T14: =VLOOKUP(H14,'Maturity Rating'!A$8:B$11,2,FALSE) -> NA | U14: =VLOOKUP(I14,'Maturity Rating'!A$14:B$17,2,FALSE) -> NA | V14: =VLOOKUP(J14,'Maturity Rating'!A$20:B$23,2,FALSE) -> NA | W14: =CONCATENATE(S14,T14,U14,V14) -> NANANANA
A15: 9.12 | E15: There are steps employed to review the risk exposure at each stage. | F15: Preventive | G15: Formally Documented | H15: 51 - 100% Implemented | I15: Automated | J15: Monitored & Reviewed | K15: =IF(W15="NANANANA",S15,IF(AND(OR(G15="Formally Documented",G15="Informally Documented"),H15="Not Implemented"),0.5*AVERAGE(S15:V15),AVERAGE(S15:V15))) -> 3 | L15: =IF(AND(D15="K",K15=1),'Maturity Rating'!$E$8,IF(K15="NA",K15,IF(D15="K",K15*'Maturity Rating'!$E$7,K15))) -> 3 | S15: =VLOOKUP(G15,'Maturity Rating'!A$2:B$5,2,FALSE) -> 3 | T15: =VLOOKUP(H15,'Maturity Rating'!A$8:B$11,2,FALSE) -> 3 | U15: =VLOOKUP(I15,'Maturity Rating'!A$14:B$17,2,FALSE) -> 3 | V15: =VLOOKUP(J15,'Maturity Rating'!A$20:B$23,2,FALSE) -> 3 | W15: =CONCATENATE(S15,T15,U15,V15) -> 3333
A16: 9.13 | D16: K | E16: Single point failures and redundancy requirements are addressed in the overall architecture and design | F16: Preventive | G16: Not Documented | H16: Not Implemented | I16: Not Applicable | J16: Not Monitored & Reviewed | K16: =IF(W16="NANANANA",S16,IF(AND(OR(G16="Formally Documented",G16="Informally Documented"),H16="Not Implemented"),0.5*AVERAGE(S16:V16),AVERAGE(S16:V16))) -> 1 | L16: =IF(AND(D16="K",K16=1),'Maturity Rating'!$E$8,IF(K16="NA",K16,IF(D16="K",K16*'Maturity Rating'!$E$7,K16))) -> 0.8 | S16: =VLOOKUP(G16,'Maturity Rating'!A$2:B$5,2,FALSE) -> 1 | T16: =VLOOKUP(H16,'Maturity Rating'!A$8:B$11,2,FALSE) -> 1 | U16: =VLOOKUP(I16,'Maturity Rating'!A$14:B$17,2,FALSE) -> NA | V16: =VLOOKUP(J16,'Maturity Rating'!A$20:B$23,2,FALSE) -> 1 | W16: =CONCATENATE(S16,T16,U16,V16) -> 11NA1
A17: 9.14 | B17: Secure Maintenance | C17: There is a defined process to ensure secure maintainance in the daily operation of the emerging technologies | E17: Access to information systems and services should be granted only post authorised approvals | F17: Preventive | G17: Formally Documented | H17: 51 - 100% Implemented | I17: Automated | J17: Monitored & Reviewed | K17: =IF(W17="NANANANA",S17,IF(AND(OR(G17="Formally Documented",G17="Informally Documented"),H17="Not Implemented"),0.5*AVERAGE(S17:V17),AVERAGE(S17:V17))) -> 3 | L17: =IF(AND(D17="K",K17=1),'Maturity Rating'!$E$8,IF(K17="NA",K17,IF(D17="K",K17*'Maturity Rating'!$E$7,K17))) -> 3 | M17: =IF(X17="NANANANANANANANANANANANA",K17,AVERAGE(L17:L28)) -> 2.0204545 | N17: =IF(M17<1.1,1,IF(M17="NA",M17,(MIN(5,M17/3*5)))) -> 3.3674242 | O17: =IF(N17="NA",N17,VLOOKUP(Q17,'Maturity Rating'!G4:H8,2,FALSE)) -> Defined | Q17: =IF(N17="NA",N17,ROUNDDOWN(N17,0)) -> 3 | S17: =VLOOKUP(G17,'Maturity Rating'!A$2:B$5,2,FALSE) -> 3 | T17: =VLOOKUP(H17,'Maturity Rating'!A$8:B$11,2,FALSE) -> 3 | U17: =VLOOKUP(I17,'Maturity Rating'!A$14:B$17,2,FALSE) -> 3 | V17: =VLOOKUP(J17,'Maturity Rating'!A$20:B$23,2,FALSE) -> 3 | W17: =CONCATENATE(S17,T17,U17,V17) -> 3333 | X17: =CONCATENATE(L17,L18,L19,L20,L21,L22,L23,L24,L25,L26,L27,L28) -> 33NA22.430.6250.83112.4
A18: 9.15 | E18: All privilege activities are logged, monitored and timely reviewed | F18: Preventive | G18: Formally Documented | H18: 51 - 100% Implemented | I18: Automated | J18: Monitored & Reviewed | K18: =IF(W18="NANANANA",S18,IF(AND(OR(G18="Formally Documented",G18="Informally Documented"),H18="Not Implemented"),0.5*AVERAGE(S18:V18),AVERAGE(S18:V18))) -> 3 | L18: =IF(AND(D18="K",K18=1),'Maturity Rating'!$E$8,IF(K18="NA",K18,IF(D18="K",K18*'Maturity Rating'!$E$7,K18))) -> 3 | S18: =VLOOKUP(G18,'Maturity Rating'!A$2:B$5,2,FALSE) -> 3 | T18: =VLOOKUP(H18,'Maturity Rating'!A$8:B$11,2,FALSE) -> 3 | U18: =VLOOKUP(I18,'Maturity Rating'!A$14:B$17,2,FALSE) -> 3 | V18: =VLOOKUP(J18,'Maturity Rating'!A$20:B$23,2,FALSE) -> 3 | W18: =CONCATENATE(S18,T18,U18,V18) -> 3333
A19: 9.16 | E19: Accesses are revoked when no longer necessary for performing tasks | F19: Preventive | G19: Not Applicable | H19: Not Applicable | I19: Not Applicable | J19: Not Applicable | K19: =IF(W19="NANANANA",S19,IF(AND(OR(G19="Formally Documented",G19="Informally Documented"),H19="Not Implemented"),0.5*AVERAGE(S19:V19),AVERAGE(S19:V19))) -> NA | L19: =IF(AND(D19="K",K19=1),'Maturity Rating'!$E$8,IF(K19="NA",K19,IF(D19="K",K19*'Maturity Rating'!$E$7,K19))) -> NA | S19: =VLOOKUP(G19,'Maturity Rating'!A$2:B$5,2,FALSE) -> NA | T19: =VLOOKUP(H19,'Maturity Rating'!A$8:B$11,2,FALSE) -> NA | U19: =VLOOKUP(I19,'Maturity Rating'!A$14:B$17,2,FALSE) -> NA | V19: =VLOOKUP(J19,'Maturity Rating'!A$20:B$23,2,FALSE) -> NA | W19: =CONCATENATE(S19,T19,U19,V19) -> NANANANA
A20: 9.17 | E20: Configurations are stored securely and backed up in a timely manner | F20: Preventive | G20: Informally Documented | H20: 0 - 50% Implemented | I20: Partially Automated | J20: Partially Monitored & Reviewed | K20: =IF(W20="NANANANA",S20,IF(AND(OR(G20="Formally Documented",G20="Informally Documented"),H20="Not Implemented"),0.5*AVERAGE(S20:V20),AVERAGE(S20:V20))) -> 2 | L20: =IF(AND(D20="K",K20=1),'Maturity Rating'!$E$8,IF(K20="NA",K20,IF(D20="K",K20*'Maturity Rating'!$E$7,K20))) -> 2 | S20: =VLOOKUP(G20,'Maturity Rating'!A$2:B$5,2,FALSE) -> 2 | T20: =VLOOKUP(H20,'Maturity Rating'!A$8:B$11,2,FALSE) -> 2 | U20: =VLOOKUP(I20,'Maturity Rating'!A$14:B$17,2,FALSE) -> 2 | V20: =VLOOKUP(J20,'Maturity Rating'!A$20:B$23,2,FALSE) -> 2 | W20: =CONCATENATE(S20,T20,U20,V20) -> 2222
A21: 9.18 | D21: K | E21: Access to the configuration backup is limited to authorized individuals | F21: Preventive | G21: Informally Documented | H21: 0 - 50% Implemented | I21: Partially Automated | J21: Partially Monitored & Reviewed | K21: =IF(W21="NANANANA",S21,IF(AND(OR(G21="Formally Documented",G21="Informally Documented"),H21="Not Implemented"),0.5*AVERAGE(S21:V21),AVERAGE(S21:V21))) -> 2 | L21: =IF(AND(D21="K",K21=1),'Maturity Rating'!$E$8,IF(K21="NA",K21,IF(D21="K",K21*'Maturity Rating'!$E$7,K21))) -> 2.4 | S21: =VLOOKUP(G21,'Maturity Rating'!A$2:B$5,2,FALSE) -> 2 | T21: =VLOOKUP(H21,'Maturity Rating'!A$8:B$11,2,FALSE) -> 2 | U21: =VLOOKUP(I21,'Maturity Rating'!A$14:B$17,2,FALSE) -> 2 | V21: =VLOOKUP(J21,'Maturity Rating'!A$20:B$23,2,FALSE) -> 2 | W21: =CONCATENATE(S21,T21,U21,V21) -> 2222
A22: 9.19 | E22: The technology implemented is reviewed for its compliance to the defined secure configuration guidelines. | F22: Preventive | G22: Formally Documented | H22: 51 - 100% Implemented | I22: Automated | J22: Monitored & Reviewed | K22: =IF(W22="NANANANA",S22,IF(AND(OR(G22="Formally Documented",G22="Informally Documented"),H22="Not Implemented"),0.5*AVERAGE(S22:V22),AVERAGE(S22:V22))) -> 3 | L22: =IF(AND(D22="K",K22=1),'Maturity Rating'!$E$8,IF(K22="NA",K22,IF(D22="K",K22*'Maturity Rating'!$E$7,K22))) -> 3 | S22: =VLOOKUP(G22,'Maturity Rating'!A$2:B$5,2,FALSE) -> 3 | T22: =VLOOKUP(H22,'Maturity Rating'!A$8:B$11,2,FALSE) -> 3 | U22: =VLOOKUP(I22,'Maturity Rating'!A$14:B$17,2,FALSE) -> 3 | V22: =VLOOKUP(J22,'Maturity Rating'!A$20:B$23,2,FALSE) -> 3 | W22: =CONCATENATE(S22,T22,U22,V22) -> 3333
A23: 9. 20 | E23: The technology components are patched parodically to prevent vulnerabilities | F23: Preventive | G23: Informally Documented | H23: Not Implemented | I23: Not Automated | J23: Not Monitored & Reviewed | K23: =IF(W23="NANANANA",S23,IF(AND(OR(G23="Formally Documented",G23="Informally Documented"),H23="Not Implemented"),0.5*AVERAGE(S23:V23),AVERAGE(S23:V23))) -> 0.625 | L23: =IF(AND(D23="K",K23=1),'Maturity Rating'!$E$8,IF(K23="NA",K23,IF(D23="K",K23*'Maturity Rating'!$E$7,K23))) -> 0.625 | S23: =VLOOKUP(G23,'Maturity Rating'!A$2:B$5,2,FALSE) -> 2 | T23: =VLOOKUP(H23,'Maturity Rating'!A$8:B$11,2,FALSE) -> 1 | U23: =VLOOKUP(I23,'Maturity Rating'!A$14:B$17,2,FALSE) -> 1 | V23: =VLOOKUP(J23,'Maturity Rating'!A$20:B$23,2,FALSE) -> 1 | W23: =CONCATENATE(S23,T23,U23,V23) -> 2111
A24: 9.21 | D24: K | E24: Configuration changes are made only post authorized approvals | F24: Preventive | G24: Not Documented | H24: Not Implemented | I24: Not Automated | J24: Not Monitored & Reviewed | K24: =IF(W24="NANANANA",S24,IF(AND(OR(G24="Formally Documented",G24="Informally Documented"),H24="Not Implemented"),0.5*AVERAGE(S24:V24),AVERAGE(S24:V24))) -> 1 | L24: =IF(AND(D24="K",K24=1),'Maturity Rating'!$E$8,IF(K24="NA",K24,IF(D24="K",K24*'Maturity Rating'!$E$7,K24))) -> 0.8 | S24: =VLOOKUP(G24,'Maturity Rating'!A$2:B$5,2,FALSE) -> 1 | T24: =VLOOKUP(H24,'Maturity Rating'!A$8:B$11,2,FALSE) -> 1 | U24: =VLOOKUP(I24,'Maturity Rating'!A$14:B$17,2,FALSE) -> 1 | V24: =VLOOKUP(J24,'Maturity Rating'!A$20:B$23,2,FALSE) -> 1 | W24: =CONCATENATE(S24,T24,U24,V24) -> 1111
A25: 9.22 | E25: Wherever feasible changes are tested before deployment in production | F25: Preventive | G25: Formally Documented | H25: 51 - 100% Implemented | I25: Automated | J25: Monitored & Reviewed | K25: =IF(W25="NANANANA",S25,IF(AND(OR(G25="Formally Documented",G25="Informally Documented"),H25="Not Implemented"),0.5*AVERAGE(S25:V25),AVERAGE(S25:V25))) -> 3 | L25: =IF(AND(D25="K",K25=1),'Maturity Rating'!$E$8,IF(K25="NA",K25,IF(D25="K",K25*'Maturity Rating'!$E$7,K25))) -> 3 | S25: =VLOOKUP(G25,'Maturity Rating'!A$2:B$5,2,FALSE) -> 3 | T25: =VLOOKUP(H25,'Maturity Rating'!A$8:B$11,2,FALSE) -> 3 | U25: =VLOOKUP(I25,'Maturity Rating'!A$14:B$17,2,FALSE) -> 3 | V25: =VLOOKUP(J25,'Maturity Rating'!A$20:B$23,2,FALSE) -> 3 | W25: =CONCATENATE(S25,T25,U25,V25) -> 3333
A26: 9.23 | E26: The logs of the the devices are centrally stored and parodically monitored for malicious activity | F26: Detective | G26: Not Documented | H26: Not Implemented | I26: Not Automated | J26: Not Monitored & Reviewed | K26: =IF(W26="NANANANA",S26,IF(AND(OR(G26="Formally Documented",G26="Informally Documented"),H26="Not Implemented"),0.5*AVERAGE(S26:V26),AVERAGE(S26:V26))) -> 1 | L26: =IF(AND(D26="K",K26=1),'Maturity Rating'!$E$8,IF(K26="NA",K26,IF(D26="K",K26*'Maturity Rating'!$E$7,K26))) -> 1 | S26: =VLOOKUP(G26,'Maturity Rating'!A$2:B$5,2,FALSE) -> 1 | T26: =VLOOKUP(H26,'Maturity Rating'!A$8:B$11,2,FALSE) -> 1 | U26: =VLOOKUP(I26,'Maturity Rating'!A$14:B$17,2,FALSE) -> 1 | V26: =VLOOKUP(J26,'Maturity Rating'!A$20:B$23,2,FALSE) -> 1 | W26: =CONCATENATE(S26,T26,U26,V26) -> 1111
A27: 9.24 | E27: The logs are stored for a minimum period of 6 months or more depending on any regulatory or contractual requirement | F27: Detective | G27: Not Documented | H27: Not Implemented | I27: Not Automated | J27: Not Monitored & Reviewed | K27: =IF(W27="NANANANA",S27,IF(AND(OR(G27="Formally Documented",G27="Informally Documented"),H27="Not Implemented"),0.5*AVERAGE(S27:V27),AVERAGE(S27:V27))) -> 1 | L27: =IF(AND(D27="K",K27=1),'Maturity Rating'!$E$8,IF(K27="NA",K27,IF(D27="K",K27*'Maturity Rating'!$E$7,K27))) -> 1 | S27: =VLOOKUP(G27,'Maturity Rating'!A$2:B$5,2,FALSE) -> 1 | T27: =VLOOKUP(H27,'Maturity Rating'!A$8:B$11,2,FALSE) -> 1 | U27: =VLOOKUP(I27,'Maturity Rating'!A$14:B$17,2,FALSE) -> 1 | V27: =VLOOKUP(J27,'Maturity Rating'!A$20:B$23,2,FALSE) -> 1 | W27: =CONCATENATE(S27,T27,U27,V27) -> 1111
A28: 9.25 | D28: K | E28: The technical components are regularly monitored for their resource utilization and acted upon. | F28: Detective | G28: Informally Documented | H28: 0 - 50% Implemented | I28: Partially Automated | J28: Partially Monitored & Reviewed | K28: =IF(W28="NANANANA",S28,IF(AND(OR(G28="Formally Documented",G28="Informally Documented"),H28="Not Implemented"),0.5*AVERAGE(S28:V28),AVERAGE(S28:V28))) -> 2 | L28: =IF(AND(D28="K",K28=1),'Maturity Rating'!$E$8,IF(K28="NA",K28,IF(D28="K",K28*'Maturity Rating'!$E$7,K28))) -> 2.4 | S28: =VLOOKUP(G28,'Maturity Rating'!A$2:B$5,2,FALSE) -> 2 | T28: =VLOOKUP(H28,'Maturity Rating'!A$8:B$11,2,FALSE) -> 2 | U28: =VLOOKUP(I28,'Maturity Rating'!A$14:B$17,2,FALSE) -> 2 | V28: =VLOOKUP(J28,'Maturity Rating'!A$20:B$23,2,FALSE) -> 2 | W28: =CONCATENATE(S28,T28,U28,V28) -> 2222

Sheet Network Security
C1: Average Domain Rating | E1: =IF(F1="NA","Not Applicable",VLOOKUP(T1,'Maturity Rating'!G4:H8,2,FALSE)) -> Partial | F1: =IF(U1="NANANANANANANANANANANANA","NA",AVERAGE(N4:N94)) -> 2.9475565 | H1: =ROUNDDOWN(#REF!,0) -> #REF! | T1: =ROUNDDOWN(F1,0) -> 2 | U1: =CONCATENATE(N4,N8,N19,N27,N34,N42,N47,N53,N58,N68,N75,N84,L86) -> 4.416666666666673.840909090909092.795138888888893.063492063492063.041666666666672.11.611111111111112.444444444444442.480555555555562.817460317460322.962962962962963.751
A3: S. No. | B3: High Level Description | C3: Control Description | D3: Identified Key Controls (K) | E3: Control | F3: Preventive/ Detective/Corrective | G3: Documentation | H3: Implementation | I3: Automation | J3: Monitor & Review | K3: Control Rating | L3: Rating with Key controls weightage | M3: Average Rating | N3: Maturity Rating (1 - 5) | O3: Category | S3: Doc | T3: Impl | U3: Auto | V3: Review
A4: 10.1 | B4: Policy and procedures | C4: Formal policies, procedures and controls shall be in place to protect the organizations network including critical data & all types of communication facilities. | D4: K | E4: Organization should have a network security policy/ procedure defined and approved by the management. | F4: Preventive | G4: Formally Documented | H4: 51 - 100% Implemented | I4: Automated | J4: Not Applicable | K4: =IF(W4="NANANANA",S4,IF(AND(OR(G4="Formally Documented",G4="Informally Documented"),H4="Not Implemented"),0.5*AVERAGE(S4:V4),AVERAGE(S4:V4))) -> 3 | L4: =IF(AND(D4="K",K4=1),'Maturity Rating'!$E$8,IF(K4="NA",K4,IF(D4="K",K4*'Maturity Rating'!$E$7,K4))) -> 3.6 | M4: =IF(X4="NANANANANA",K4,AVERAGE(L4:L7)) -> 2.65 | N4: =IF(M4<1.1,1,IF(M4="NA",M4,(MIN(5,M4/3*5)))) -> 4.4166667 | O4: =IF(N4="NA",N4,VLOOKUP(Q4,'Maturity Rating'!G4:H8,2,FALSE)) -> Repeatable | Q4: =IF(N4="NA",N4,ROUNDDOWN(N4,0)) -> 4 | S4: =VLOOKUP(G4,'Maturity Rating'!A$2:B$5,2,FALSE) -> 3 | T4: =VLOOKUP(H4,'Maturity Rating'!A$8:B$11,2,FALSE) -> 3 | U4: =VLOOKUP(I4,'Maturity Rating'!A$14:B$17,2,FALSE) -> 3 | V4: =VLOOKUP(J4,'Maturity Rating'!A$20:B$23,2,FALSE) -> NA | W4: =CONCATENATE(S4,T4,U4,V4) -> 333NA | X4: =CONCATENATE(L4,L5,L6,L7) -> 3.6331
A5: 10.2 | E5: There is a documented and approved high level and low level network architecture diagram | F5: Preventive | G5: Formally Documented | H5: 51 - 100% Implemented | I5: Automated | J5: Not Applicable | K5: =IF(W5="NANANANA",S5,IF(AND(OR(G5="Formally Documented",G5="Informally Documented"),H5="Not Implemented"),0.5*AVERAGE(S5:V5),AVERAGE(S5:V5))) -> 3 | L5: =IF(AND(D5="K",K5=1),'Maturity Rating'!$E$8,IF(K5="NA",K5,IF(D5="K",K5*'Maturity Rating'!$E$7,K5))) -> 3 | S5: =VLOOKUP(G5,'Maturity Rating'!A$2:B$5,2,FALSE) -> 3 | T5: =VLOOKUP(H5,'Maturity Rating'!A$8:B$11,2,FALSE) -> 3 | U5: =VLOOKUP(I5,'Maturity Rating'!A$14:B$17,2,FALSE) -> 3 | V5: =VLOOKUP(J5,'Maturity Rating'!A$20:B$23,2,FALSE) -> NA | W5: =CONCATENATE(S5,T5,U5,V5) -> 333NA
A6: 10.3 | E6: The documents are reviewed, updated and approved as per the defined frequency in the policy/ procedure. | F6: Preventive | G6: Formally Documented | H6: 51 - 100% Implemented | I6: Automated | J6: Not Applicable | K6: =IF(W6="NANANANA",S6,IF(AND(OR(G6="Formally Documented",G6="Informally Documented"),H6="Not Implemented"),0.5*AVERAGE(S6:V6),AVERAGE(S6:V6))) -> 3 | L6: =IF(AND(D6="K",K6=1),'Maturity Rating'!$E$8,IF(K6="NA",K6,IF(D6="K",K6*'Maturity Rating'!$E$7,K6))) -> 3 | S6: =VLOOKUP(G6,'Maturity Rating'!A$2:B$5,2,FALSE) -> 3 | T6: =VLOOKUP(H6,'Maturity Rating'!A$8:B$11,2,FALSE) -> 3 | U6: =VLOOKUP(I6,'Maturity Rating'!A$14:B$17,2,FALSE) -> 3 | V6: =VLOOKUP(J6,'Maturity Rating'!A$20:B$23,2,FALSE) -> NA | W6: =CONCATENATE(S6,T6,U6,V6) -> 333NA
A7: 10.4 | E7: The version control of the documents should be maintained | F7: Preventive | G7: Not Documented | H7: Not Implemented | I7: Not Applicable | J7: Not Applicable | K7: =IF(W7="NANANANA",S7,IF(AND(OR(G7="Formally Documented",G7="Informally Documented"),H7="Not Implemented"),0.5*AVERAGE(S7:V7),AVERAGE(S7:V7))) -> 1 | L7: =IF(AND(D7="K",K7=1),'Maturity Rating'!$E$8,IF(K7="NA",K7,IF(D7="K",K7*'Maturity Rating'!$E$7,K7))) -> 1 | S7: =VLOOKUP(G7,'Maturity Rating'!A$2:B$5,2,FALSE) -> 1 | T7: =VLOOKUP(H7,'Maturity Rating'!A$8:B$11,2,FALSE) -> 1 | U7: =VLOOKUP(I7,'Maturity Rating'!A$14:B$17,2,FALSE) -> NA | V7: =VLOOKUP(J7,'Maturity Rating'!A$20:B$23,2,FALSE) -> NA | W7: =CONCATENATE(S7,T7,U7,V7) -> 11NANA
A8: 10.5 | B8: Security tools | C8: Ensure sufficient technological and process checks are employed to monitor the Network | E8: The organization has a firewall or equivalent in place to protect the internal network and devices against unauthorized access | F8: Preventive | G8: Formally Documented | H8: 51 - 100% Implemented | I8: Automated | J8: Monitored & Reviewed | K8: =IF(W8="NANANANA",S8,IF(AND(OR(G8="Formally Documented",G8="Informally Documented"),H8="Not Implemented"),0.5*AVERAGE(S8:V8),AVERAGE(S8:V8))) -> 3 | L8: =IF(AND(D8="K",K8=1),'Maturity Rating'!$E$8,IF(K8="NA",K8,IF(D8="K",K8*'Maturity Rating'!$E$7,K8))) -> 3 | M8: =IF(X8="NANANANANANANANANANANANANA",K8,AVERAGE(L8:L18)) -> 2.3045455 | N8: =IF(M8<1.1,1,IF(M8="NA",M8,(MIN(5,M8/3*5)))) -> 3.8409091 | O8: =IF(N8="NA",N8,VLOOKUP(Q8,'Maturity Rating'!G4:H8,2,FALSE)) -> Defined | Q8: =IF(N8="NA",N8,ROUNDDOWN(N8,0)) -> 3 | S8: =VLOOKUP(G8,'Maturity Rating'!A$2:B$5,2,FALSE) -> 3 | T8: =VLOOKUP(H8,'Maturity Rating'!A$8:B$11,2,FALSE) -> 3 | U8: =VLOOKUP(I8,'Maturity Rating'!A$14:B$17,2,FALSE) -> 3 | V8: =VLOOKUP(J8,'Maturity Rating'!A$20:B$23,2,FALSE) -> 3 | W8: =CONCATENATE(S8,T8,U8,V8) -> 3333 | X8: =CONCATENATE(L8,L9,L10,L11,L12,L13,L14,L15,L16,L17,L18) -> 32.2531.752.75313113.6
A9: 10.6 | E9: Network devices are AAA authenticated | F9: Detective | G9: Informally Documented | H9: 51 - 100% Implemented | I9: Not Automated | J9: Monitored & Reviewed | K9: =IF(W9="NANANANA",S9,IF(AND(OR(G9="Formally Documented",G9="Informally Documented"),H9="Not Implemented"),0.5*AVERAGE(S9:V9),AVERAGE(S9:V9))) -> 2.25 | L9: =IF(AND(D9="K",K9=1),'Maturity Rating'!$E$8,IF(K9="NA",K9,IF(D9="K",K9*'Maturity Rating'!$E$7,K9))) -> 2.25 | S9: =VLOOKUP(G9,'Maturity Rating'!A$2:B$5,2,FALSE) -> 2 | T9: =VLOOKUP(H9,'Maturity Rating'!A$8:B$11,2,FALSE) -> 3 | U9: =VLOOKUP(I9,'Maturity Rating'!A$14:B$17,2,FALSE) -> 1 | V9: =VLOOKUP(J9,'Maturity Rating'!A$20:B$23,2,FALSE) -> 3 | W9: =CONCATENATE(S9,T9,U9,V9) -> 2313
A10: 10.7 | E10: Organization has controls in place for monitoring network activity | F10: Detective | G10: Formally Documented | H10: 51 - 100% Implemented | I10: Automated | J10: Monitored & Reviewed | K10: =IF(W10="NANANANA",S10,IF(AND(OR(G10="Formally Documented",G10="Informally Documented"),H10="Not Implemented"),0.5*AVERAGE(S10:V10),AVERAGE(S10:V10))) -> 3 | L10: =IF(AND(D10="K",K10=1),'Maturity Rating'!$E$8,IF(K10="NA",K10,IF(D10="K",K10*'Maturity Rating'!$E$7,K10))) -> 3 | S10: =VLOOKUP(G10,'Maturity Rating'!A$2:B$5,2,FALSE) -> 3 | T10: =VLOOKUP(H10,'Maturity Rating'!A$8:B$11,2,FALSE) -> 3 | U10: =VLOOKUP(I10,'Maturity Rating'!A$14:B$17,2,FALSE) -> 3 | V10: =VLOOKUP(J10,'Maturity Rating'!A$20:B$23,2,FALSE) -> 3 | W10: =CONCATENATE(S10,T10,U10,V10) -> 3333
A11: 10.8 | E11: Organization has systems or modules in place for intrusion prevention/ detection | F11: Preventive/Detective | G11: Informally Documented | H11: 0 - 50% Implemented | I11: Not Automated | J11: Partially Monitored & Reviewed | K11: =IF(W11="NANANANA",S11,IF(AND(OR(G11="Formally Documented",G11="Informally Documented"),H11="Not Implemented"),0.5*AVERAGE(S11:V11),AVERAGE(S11:V11))) -> 1.75 | L11: =IF(AND(D11="K",K11=1),'Maturity Rating'!$E$8,IF(K11="NA",K11,IF(D11="K",K11*'Maturity Rating'!$E$7,K11))) -> 1.75 | S11: =VLOOKUP(G11,'Maturity Rating'!A$2:B$5,2,FALSE) -> 2 | T11: =VLOOKUP(H11,'Maturity Rating'!A$8:B$11,2,FALSE) -> 2 | U11: =VLOOKUP(I11,'Maturity Rating'!A$14:B$17,2,FALSE) -> 1 | V11: =VLOOKUP(J11,'Maturity Rating'!A$20:B$23,2,FALSE) -> 2 | W11: =CONCATENATE(S11,T11,U11,V11) -> 2212
A12: 10.9 | E12: Organization has controls in place to ensure secure remote access to the network and its resources | F12: Preventive | G12: Formally Documented | H12: 0 - 50% Implemented | I12: Automated | J12: Monitored & Reviewed | K12: =IF(W12="NANANANA",S12,IF(AND(OR(G12="Formally Documented",G12="Informally Documented"),H12="Not Implemented"),0.5*AVERAGE(S12:V12),AVERAGE(S12:V12))) -> 2.75 | L12: =IF(AND(D12="K",K12=1),'Maturity Rating'!$E$8,IF(K12="NA",K12,IF(D12="K",K12*'Maturity Rating'!$E$7,K12))) -> 2.75 | S12: =VLOOKUP(G12,'Maturity Rating'!A$2:B$5,2,FALSE) -> 3 | T12: =VLOOKUP(H12,'Maturity Rating'!A$8:B$11,2,FALSE) -> 2 | U12: =VLOOKUP(I12,'Maturity Rating'!A$14:B$17,2,FALSE) -> 3 | V12: =VLOOKUP(J12,'Maturity Rating'!A$20:B$23,2,FALSE) -> 3 | W12: =CONCATENATE(S12,T12,U12,V12) -> 3233
A13: 10. 10 | E13: Organization has controls in place for detecting denial of service attacks | F13: Detective | G13: Formally Documented | H13: 51 - 100% Implemented | I13: Automated | J13: Monitored & Reviewed | K13: =IF(W13="NANANANA",S13,IF(AND(OR(G13="Formally Documented",G13="Informally Documented"),H13="Not Implemented"),0.5*AVERAGE(S13:V13),AVERAGE(S13:V13))) -> 3 | L13: =IF(AND(D13="K",K13=1),'Maturity Rating'!$E$8,IF(K13="NA",K13,IF(D13="K",K13*'Maturity Rating'!$E$7,K13))) -> 3 | S13: =VLOOKUP(G13,'Maturity Rating'!A$2:B$5,2,FALSE) -> 3 | T13: =VLOOKUP(H13,'Maturity Rating'!A$8:B$11,2,FALSE) -> 3 | U13: =VLOOKUP(I13,'Maturity Rating'!A$14:B$17,2,FALSE) -> 3 | V13: =VLOOKUP(J13,'Maturity Rating'!A$20:B$23,2,FALSE) -> 3 | W13: =CONCATENATE(S13,T13,U13,V13) -> 3333
A14: 10.12 | E14: Rules and policies are configured on network devices only post authorized approvals & testing | F14: Preventive | G14: Not Documented | H14: Not Implemented | I14: Not Automated | J14: Not Monitored & Reviewed | K14: =IF(W14="NANANANA",S14,IF(AND(OR(G14="Formally Documented",G14="Informally Documented"),H14="Not Implemented"),0.5*AVERAGE(S14:V14),AVERAGE(S14:V14))) -> 1 | L14: =IF(AND(D14="K",K14=1),'Maturity Rating'!$E$8,IF(K14="NA",K14,IF(D14="K",K14*'Maturity Rating'!$E$7,K14))) -> 1 | S14: =VLOOKUP(G14,'Maturity Rating'!A$2:B$5,2,FALSE) -> 1 | T14: =VLOOKUP(H14,'Maturity Rating'!A$8:B$11,2,FALSE) -> 1 | U14: =VLOOKUP(I14,'Maturity Rating'!A$14:B$17,2,FALSE) -> 1 | V14: =VLOOKUP(J14,'Maturity Rating'!A$20:B$23,2,FALSE) -> 1 | W14: =CONCATENATE(S14,T14,U14,V14) -> 1111
